Workbook

Sheet README
A1: BSI (BRIS) integrated valuation model v11.2
A2: Valuation date 16-Oct-2026 | price Rp 1,095 | units Rp bn unless stated | template: Quick FM (Alip), fixed and extended by the team
A4: Colour code
A5: Blue text | B5: Input you can change
A6: Black text | B6: Formula
A7: Green text | B7: Link to another sheet
A8: Orange fill | B8: Input still estimated (see Input_Register)
A10: Sheet | B10: Role | C10: What it holds | D10: Open items
A11: Dashboard | B11: Output | C11: One-page view: verdict, cost of equity, story to numbers, methods, scenarios, checks, where to change what | D11: Start here
A12: Sheet1 | B12: Engine | C12: Inputs, income statement, balance sheet, cash flow, capital, DDM, residual income, 12m PT, scenarios, tornado, peers, charts | D12: Scenario and tornado blocks are static snapshots (flags E444, E455)
A13: Valuation_Checks | B13: Valuation | C13: Banking FCFE, justified and exit P/B, Ke x terminal-ROE-spread grid | D13: Cross-checks only
A14: Charts | B14: Output | C14: Chart data blocks and the 11 model charts (moved out of Sheet1)
A15: Terminal_ROE | B15: Valuation | C15: Evidence for terminal ROE = Ke + spread, scenario spreads, live sensitivity
A16: Beta_Evidence | B16: Valuation | C16: Observed betas, Blume adjustment, lambda cross-check, beta sensitivity of PT (static) | D16: Confirm raw-beta source and period with Alip
A17: Prob_Justification | B17: Valuation | C17: Evidence tally behind the Bear / Base / Bull probabilities | D17: Weights are judgement
A18: Damodaran_Audit | B18: Check | C18: Structural checks against Damodaran bank valuation; BRIS P/B history
A19: Driver_Check | B19: Evidence | C19: Forecast drivers vs history and 1H26 run-rate | D19: Settle financing growth
A20: CF_Direct | B20: Evidence | C20: Direct cash flow FY21A-FY25A as reported
A21: Input_Register | B21: Evidence | C21: Status and source of every market input and estimate | D21: Peer 16-Oct closes, 52-week high, sell-side targets
A22: Beta / Returns / Prices | B22: Data | C22: Monthly closes and regression beta vs IHSG
A23: Change_Log | B23: Admin | C23: Version history
A25: Model notes (moved from Sheet1 section 7)
A26: Orange cells = estimates (BS detail, debt tranches, fixed assets, rates, market inputs) -> replace via research pass; model recalculates.
A27: Half-year memo (cols T:V): Jun-25A, Jun-26A and implied 2H26E. Quarterly split not built: only 1H26 flows disclosed in the source decks.
A28: FY25 deck prints operating income 25,279; NMI + fee-based = 25,937 and PPOP 12,365 ties to 25,937 -> model uses 25,937.
A29: Hist NIM (reported) vs model NIM differ by definition (earning-asset base); gap held flat in forecast (S4).
A30: Dividends paid in year t = payout x NI of year t-1. Policy payout 15% FY23-24; FY25 payout pending 2026 RUPST.
A31: Scenario summary (4h) and tornado (4i) remain static values (regenerated in v4.0); staleness flags in E471 and E482 show STALE if inputs change after the snapshot.
A32: Rights issue (up to 6.8bn shares, EGM 6-Nov-26, Q1-27): per-share values are per EXISTING share assuming pro-rata subscription (net distribution = dividends - subscription). Issue price undisclosed (placeholder).
A33: FY21A: income statement mapped to deck presentation (wadiah bonus 120 moved out of overhead into PSE / fee, as in FY22 deck vs audited). FY21 personnel/promotion split, segment balances (Rp0.1tn rounding) and DPK split are ESTIMATES (orange). NIM, cost of funds, yield and cost of credit not available for FY21: left blank.
A34: FY31-35E: drivers faded/held (financing growth fades to 5.0/6.5/8.0%, fee growth to 5/7/9%, other ratios held at FY30E). Payout ramps toward sustainable level (1-g/ROE) as growth slows - JUDGMENT. Sukuk rolled 1:1. No new equity raise after the 2027 rights issue.
A35: Remaining non-primary inputs: 52-week high, sell-side targets, peer 16-Oct closes. See Input_Register.

Sheet Dashboard
A1: BSI (BRIS) - Valuation dashboard
A2: Live links (green) to Sheet1 and supporting sheets; section 5 is a static scenario snapshot. Rp per share unless stated. The rating is the mechanical output of the +15% / -10% rule, not the team recommendation.
A4: 1. Recommendation (mechanical)
A5: Rating (> +15% BUY, < -10% SELL, else HOLD) | B5: =Sheet1!E408 -> BUY
A6: Current price, close 16-Oct-26 | B6: =Sheet1!E20 -> 1095 | H6: BSI IR historical prices
A7: Value today: intrinsic (DDM = RI) / relative / blended | B7: =Sheet1!E402 -> 2019.8393 | C7: =Sheet1!E411 -> 1142.2663 | D7: =(1-Sheet1!E29)*Sheet1!E402+Sheet1!E29*Sheet1!E411 -> 1727.315 | H7: Blend weight on relative = Sheet1 E29
A8: 12-month target price (blended) | B8: =Sheet1!E406 -> 1881.1248 | H8: Each value rolled forward 12 months at Ke, less dividends
A9: Upside to 12-month target price | B9: =Sheet1!E407 -> 0.71792219
A10: Probability-weighted 12-month target price | B10: =Sheet1!H439 -> 1854.5971 | H10: Static snapshot; weights in Prob_Justification
A11: Master model check | B11: =Sheet1!E420 -> OK | H11: OK = every integrity test passes
A13: 2. Cost of equity, terminal assumptions and weights
A14: Risk-free rate, IDR (10Y yield less default spread) | B14: =Sheet1!E24 -> 0.0556
A15: Beta: raw (selected) / Blume-adjusted year 1 | B15: =Beta_Evidence!B39 -> 0.64 | C15: =Sheet1!E26 -> 0.7588 | H15: Choice in Beta_Evidence B38; converges to 1.0 by FY35E
A16: ERP incl. country risk / country risk premium (added in full) | B16: =Sheet1!E25 -> 0.0669 | C16: =Beta_Evidence!B17 -> 0.0246 | H16: Lambda approach, Beta_Evidence B41
A17: Cost of equity: year 1 / stable (FY35E) | B17: =Sheet1!E34 -> 0.11229724 | C17: =Sheet1!S378 -> 0.1225
A18: Terminal growth / terminal ROE (stable Ke + spread) | B18: =Sheet1!E31 -> 0.045 | C18: =Sheet1!E382 -> 0.1425 | H18: Evidence in Terminal_ROE
A19: Weight on relative valuation in the target | B19: =Sheet1!E29 -> 0.33333333 | H19: MSCI Standalone consultation (15 Oct 2026); sensitivity in Valuation_Checks 4
A21: 3. Story to numbers | B21: FY25A | C21: FY26E | D21: FY28E | E21: FY30E | F21: FY35E
A22: Gross financing growth | B22: =Sheet1!I212/Sheet1!H212-1 -> 0.14493987 | C22: =Sheet1!J212/Sheet1!I212-1 -> 0.14380587 | D22: =Sheet1!L212/Sheet1!K212-1 -> 0.11540909 | E22: =Sheet1!N212/Sheet1!M212-1 -> 0.098190951 | F22: =Sheet1!S212/Sheet1!R212-1 -> 0.065
A23: Net profit (Rp bn) | B23: =Sheet1!I154 -> 7567.523 | C23: =Sheet1!J154 -> 8421.2868 | D23: =Sheet1!L154 -> 12070.327 | E23: =Sheet1!N154 -> 15139.179 | F23: =Sheet1!S154 -> 22490.829
A24: ROE (average equity) | B24: =Sheet1!I347 -> 0.15604034 | C24: =Sheet1!J347 -> 0.15199023 | D24: =Sheet1!L347 -> 0.15372455 | E24: =Sheet1!N347 -> 0.15271595 | F24: =Sheet1!S347 -> 0.14619715
A25: Cost-to-income ratio | B25: =Sheet1!I95 -> 0.52562269 | C25: =Sheet1!J95 -> 0.545 | D25: =Sheet1!L95 -> 0.515 | E25: =Sheet1!N95 -> 0.505 | F25: =Sheet1!S95 -> 0.505
A26: Cost of credit | B26: =Sheet1!I99 -> 0.0078916871 | C26: =Sheet1!J99 -> 0.007 | D26: =Sheet1!L99 -> 0.0075 | E26: =Sheet1!N99 -> 0.0075 | F26: =Sheet1!S99 -> 0.0075
A27: Gross NPF | B27: =Sheet1!I103 -> 0.0181 | C27: =Sheet1!J103 -> 0.0185 | D27: =Sheet1!L103 -> 0.018 | E27: =Sheet1!N103 -> 0.018 | F27: =Sheet1!S103 -> 0.018
A28: Dividend payout | B28: =Sheet1!I108 -> 0.2 | C28: =Sheet1!J108 -> 0.22 | D28: =Sheet1!L108 -> 0.27 | E28: =Sheet1!N108 -> 0.3 | F28: =Sheet1!S108 -> 0.65
A29: CAR | B29: =Sheet1!I328 -> 0.21996525 | C29: =Sheet1!J328 -> 0.22000884 | D29: =Sheet1!L328 -> 0.24758547 | E29: =Sheet1!N328 -> 0.2565125 | F29: =Sheet1!S328 -> 0.26696653
A30: BVPS (Rp) | B30: =Sheet1!I351 -> 1126.2456 | C30: =Sheet1!J351 -> 1275.9939 | D30: =Sheet1!L351 -> 1572.9793 | E30: =Sheet1!N351 -> 1977.3847 | F30: =Sheet1!S351 -> 2999.7819
A32: 4. Valuation by method (Rp per share) | B32: Dec-25 | C32: Today | D32: 12m
A33: Intrinsic: DDM = residual income (same terminal ROE) | B33: =Sheet1!E387 -> 1890.6207 | C33: =Sheet1!E402 -> 2019.8393 | D33: =AVERAGE(Sheet1!E404,Sheet1!E405) -> 2206.4988
A34: Cross-check: banking FCFE | B34: =Valuation_Checks!B5 -> 2356.9226 | C34: =Valuation_Checks!C5 -> 2526.1039 | D34: =Valuation_Checks!D5 -> 2769.6155 | H34: Valuation_Checks section 1
A35: Cross-check: justified P/B on FY26E book | B35: =Valuation_Checks!B8 -> 1736.88 | H35: Valuation_Checks section 2
A36: Cross-check: exit P/B at peer median | B36: =Valuation_Checks!B9 -> 1562.6414
A37: Relative: 70% P/B x Jun-26 book + 30% P/E x 1H26 annualised EPS | C37: =Sheet1!E411 -> 1142.2663 | D37: =Sheet1!E411*(1+Sheet1!E34)-Sheet1!E401 -> 1230.3768 | H37: P/B-implied Sheet1 E474, P/E-implied E480
A38: Target price: 2/3 intrinsic + 1/3 relative | C38: =(1-Sheet1!E29)*Sheet1!E402+Sheet1!E29*Sheet1!E411 -> 1727.315 | D38: =Sheet1!E406 -> 1881.1248
A39: Market-implied sustainable ROE at current price | B39: =Sheet1!E414 -> 0.12034991 | H39: Compare with terminal ROE in section 2
A41: 5. Scenarios (static snapshot) | B41: Bear | C41: Base | D41: Bull | E41: Prob-wtd
A42: Probability | B42: =Sheet1!E5 -> 0.29166667 | C42: =Sheet1!F5 -> 0.5 | D42: =Sheet1!G5 -> 0.20833333 | E42: =SUM(B42:D42) -> 1
A43: Net profit FY30E (Rp bn) | B43: =Sheet1!E426 -> 10838.649 | C43: =Sheet1!F426 -> 15139.179 | D43: =Sheet1!G426 -> 19313.348 | E43: =Sheet1!H426 -> 14754.476
A44: ROE FY35E | B44: =Sheet1!E429 -> 0.10620161 | C44: =Sheet1!F429 -> 0.14619715 | D44: =Sheet1!G429 -> 0.17805393 | E44: =Sheet1!H429 -> 0.14116861
A45: 12-month target price | B45: =Sheet1!E439 -> 1325.1816 | C45: =Sheet1!F439 -> 1881.1248 | D45: =Sheet1!G439 -> 2532.1125 | E45: =Sheet1!H439 -> 1854.5971
A46: Upside vs current price | B46: =Sheet1!E440 -> 0.21021155 | C46: =Sheet1!F440 -> 0.71792219 | D46: =Sheet1!G440 -> 1.3124315 | E46: =Sheet1!H440 -> 0.69369602
A47: Current price (chart line) | B47: =Sheet1!$E$20 -> 1095 | C47: =Sheet1!$E$20 -> 1095 | D47: =Sheet1!$E$20 -> 1095
A48: Snapshot status (must read OK; else re-run scenarios) | B48: =Sheet1!E444 -> OK
A50: 6. Model integrity checks | B50: Result
A51: Master check (all tests) | B51: =Sheet1!E420 -> OK
A52: Direct cash flow ties to indirect (0 = OK) | B52: =Sheet1!E373 -> 0
A53: Cash above GWM liquidity floor (0 = OK) | B53: =Sheet1!E372 -> 0
A54: Tornado shocks off (Sheet1 E8:E15 all zero) | B54: =IF(SUMPRODUCT(ABS(Sheet1!E8:E15))=0,"OK","SHOCKS ON") -> OK
A56: 7. Where to change what | H56: Chart: bars = 12-month target price by scenario; dashed line = current price.
A57: Scenario (Bear / Base / Bull) | B57: Sheet1 E3
A58: Price, shares, risk-free, ERP | B58: Sheet1 E20:E25
A59: Raw beta choice, country-risk method, beta convergence | B59: Beta_Evidence B38, B41, B42
A60: Relative weight, terminal growth | B60: Sheet1 E29, E31
A61: Terminal ROE spread by scenario | B61: Sheet1 E39:G39
A62: Operating drivers by scenario | B62: Sheet1 rows 88-108
A63: One-at-a-time shocks (tornado) | B63: Sheet1 E8:E15, reset to 0
A64: Scenario probabilities | B64: Prob_Justification
A65: Peer data and BRIS trailing inputs | B65: Sheet1 rows 459-480
A66: Open items and sources | B66: Input_Register, Driver_Check, README

Sheet Sheet1
B1: PT BANK SYARIAH INDONESIA (PERSERO) TBK (IDX: BRIS)
B2: Rp bn unless stated | Blue = hardcode input | Black = formula | Green = cross-ref | Orange fill = ESTIMATE/PLACEHOLDER (replace with researched value) | Yellow = research input | Grey = forecast
B3: SCENARIO SELECTOR (1=Bear, 2=Base, 3=Bull) | C3: # | D3: Drives every live driver below | E3: 2
B4: Active scenario | E4: =CHOOSE($E$3,"Bear","Base","Bull") -> Base
B5: Scenario probability Bear / Base / Bull | C5: % | D5: Linked to sheet Prob_Justification (evidence tally). Was 25/50/25 hardcoded | E5: =Prob_Justification!$B$25 -> 0.29166667 | F5: =Prob_Justification!$B$26 -> 0.5 | G5: =Prob_Justification!$B$27 -> 0.20833333
B7: Sensitivity shocks (leave 0 for the case; used by tornado runner). Added to the live driver in every forecast year:
B8: Shock: gross margin yield (pp) | C8: pp | E8: 0
B9: Shock: cost of credit (pp) | C9: pp | E9: 0
B10: Shock: CIR (pp) | C10: pp | E10: 0
B11: Shock: financing growth, all segments (pp) | C11: pp | E11: 0
B12: Shock: fee income growth (pp) | C12: pp | E12: 0
B13: Shock: payout ratio (pp) | C13: pp | E13: 0
B14: Shock: cost of equity (pp) | C14: pp | E14: 0
B15: Shock: time-deposit rate change (pp) | C15: pp | E15: 0
B16: Data flags | E16: FY25 deck op income 25,279 vs NMI+fee 25,937 (PPOP ties to 25,937: used). Gemini cost/yield/NIM/fee/NPF tables conflict with IR decks: NOT used.
B18: 1. INPUTS
B19: 1a. Market & valuation inputs (RESEARCH - orange cells are placeholders)
B20: Current share price | C20: Rp | D20: Last trade 8-Oct-26 (journalarta); 6-Oct close 1,385 (Investing.com). Update to latest close before final run | E20: 1095
B21: Shares outstanding (pre rights issue) | C21: mn | D21: 46,129,260,138 sh at 31-Aug-26 (BSI IR/IDX) | E21: 46129.26
B22: Valuation date | C22: date | E22: 46304
B23: FY25 dividend payment date (paid in FY26) | C23: date | D23: RUPST May-26: Rp1,513.5bn, DPS 32.81, 20% payout | E23: 46178
B24: Risk-free rate, IDR (10Y INDOGB less sovereign default spread) | C24: % | D24: G24 = 10Y INDOGB 7.18% (6-Oct-26). H24 = Damodaran default spread for Baa2, 1.62% (Jan-26). Net rf = gross - spread (CRP is added once, inside the ERP) | E24: =$G$24-$H$24 -> 0.0556 | F24: gross / spread | G24: 0.0718 | H24: 0.0162
B25: Equity risk premium (Indonesia) | C25: % | D25: Damodaran Jan-26: 4.23% mature + 2.46% CRP | E25: 0.0669
B26: Beta, Blume-adjusted year 1 (raw beta chosen in Beta_Evidence B38) | C26: x | D26: Linked to Beta_Evidence B12; converges to 1.0 by FY35E when Beta_Evidence B42 = 1 | E26: =Beta_Evidence!$B$12 -> 0.7588
B27: Size / liquidity premium | C27: % | D27: Set to 0 in v4.0 (was +1.0%, pure judgment, would double count the CRP). Kept as a toggle. Lambda approach (beta on mature ERP, full CRP) equals about +0.6% here | E27: 0
B28: Cost of equity year 1 (method per Beta_Evidence B41) | C28: % | E28: =$E$24+IF(Beta_Evidence!$B$41=2,$E$26*($E$25-Beta_Evidence!$B$17)+Beta_Evidence!$B$17,$E$26*$E$25)+$E$27 -> 0.11229724
B29: Weight on relative valuation in the 12m target price (rest = DDM = RI) | C29: % | D29: Team judgement: MSCI consultation on Standalone status (15 Oct 2026) is market-wide; peer multiples carry it. Sensitivity in Valuation_Checks section 4 | E29: 0.33333333
B30: Terminal growth (g) - Bear / Base / Bull | C30: % | E30: 0.04 | F30: 0.045 | G30: 0.05
B31: Terminal growth (g) (live) | C31: % | E31: =CHOOSE($E$3,$E$30,$F$30,$G$30) -> 0.045
B32: Scenario CoE adder - Bear / Base / Bull | C32: % | D32: Set to 0 in v4.0 (was +0.5% / 0 / -0.25%): scenarios now differ by operating drivers only, Ke is a single estimate | E32: 0 | F32: 0 | G32: 0
B33: Scenario CoE adder (live) | C33: % | E33: =CHOOSE($E$3,$E$32,$F$32,$G$32)+$E$14 -> 0
B34: Cost of equity year 1 (live); yearly path in row 378 | C34: % | E34: =$E$28+$E$33 -> 0.11229724
B35: Target CAR (internal floor) | C35: % | D35: Reported CAR 20.41% at Jun-26 (Q2-26 statement); mgmt aim to stay >20%; post-rights-issue 22-24% (prospectus) | E35: 0.2
B36: Regulatory minimum CAR incl. buffers | C36: % | D36: AR2025: KPMM per risk profile 9.99% + capital conservation buffer 2.5% + D-SIB 1.0%; countercyclical 0% | E36: 0.1349
B37: FDR cap | C37: % | E37: 0.92
B38: Min cash & BI placements / DPK (GWM proxy) | C38: % | D38: Sharia GWM 7.5% (conventional 9.0%) | E38: 0.075
B39: Terminal ROE spread over Ke - Bear / Base / Bull | C39: % | D39: Terminal ROE = Ke + spread. Evidence and anchors in sheet Terminal_ROE | E39: 0 | F39: 0.02 | G39: 0.04
B40: 1b. Macro (scenario) | E40: FY21A | F40: FY22A | G40: FY23A | H40: FY24A | I40: FY25A | J40: FY26E | K40: FY27E | L40: FY28E | M40: FY29E | N40: FY30E | O40: FY31E | P40: FY32E | Q40: FY33E | R40: FY34E | S40: FY35E
B41: BI rate (year-end) - Bear | C41: % | J41: 0.0625 | K41: 0.0575 | L41: 0.055 | M41: 0.0525 | N41: 0.05 | O41: 0.05 | P41: 0.05 | Q41: 0.05 | R41: 0.05 | S41: 0.05
B42: BI rate (year-end) - Base | C42: % | J42: 0.0575 | K42: 0.0525 | L42: 0.0475 | M42: 0.045 | N42: 0.045 | O42: 0.045 | P42: 0.045 | Q42: 0.045 | R42: 0.045 | S42: 0.045
B43: BI rate (year-end) - Bull | C43: % | J43: 0.0525 | K43: 0.0475 | L43: 0.045 | M43: 0.0425 | N43: 0.0425 | O43: 0.0425 | P43: 0.0425 | Q43: 0.0425 | R43: 0.0425 | S43: 0.0425
B44: BI rate (year-end) (live) | C44: % | D44: BI rate 5.75% (Sep-26); hist per BI | E44: 0.035 | F44: 0.055 | G44: 0.06 | H44: 0.06 | I44: 0.0475 | J44: =CHOOSE($E$3,J41,J42,J43) -> 0.0575 | K44: =CHOOSE($E$3,K41,K42,K43) -> 0.0525 | L44: =CHOOSE($E$3,L41,L42,L43) -> 0.0475 | M44: =CHOOSE($E$3,M41,M42,M43) -> 0.045 | N44: =CHOOSE($E$3,N41,N42,N43) -> 0.045 | O44: =CHOOSE($E$3,O41,O42,O43) -> 0.045 | P44: =CHOOSE($E$3,P41,P42,P43) -> 0.045 | Q44: =CHOOSE($E$3,Q41,Q42,Q43) -> 0.045 | ... S44: =CHOOSE($E$3,S41,S42,S43) -> 0.045
B45: Pass-through of BI rate change to time-deposit rate | C45: x | E45: 0.6
B46: Pass-through to CASA rate | C46: x | E46: 0.1
B47: Pass-through to gross financing yield | C47: x | E47: 0.15
B49: 1c. Scenario drivers - volume | E49: FY21A | F49: FY22A | G49: FY23A | H49: FY24A | I49: FY25A | J49: FY26E | K49: FY27E | L49: FY28E | M49: FY29E | N49: FY30E | O49: FY31E | P49: FY32E | Q49: FY33E | R49: FY34E | S49: FY35E
B50: Financing growth - Corporate - Bear | C50: % | J50: 0.115 | K50: 0.095 | L50: 0.085 | M50: 0.075 | N50: 0.065 | O50: 0.062 | P50: 0.059 | Q50: 0.056 | R50: 0.053 | S50: 0.05
B51: Financing growth - Corporate - Base | C51: % | J51: 0.15 | K51: 0.13 | L51: 0.12 | M51: 0.11 | N51: 0.1 | O51: 0.093 | P51: 0.086 | Q51: 0.079 | R51: 0.072 | S51: 0.065
B52: Financing growth - Corporate - Bull | C52: % | J52: 0.175 | K52: 0.155 | L52: 0.145 | M52: 0.135 | N52: 0.125 | O52: 0.116 | P52: 0.107 | Q52: 0.098 | R52: 0.089 | S52: 0.08
B53: Financing growth - Corporate (live) | C53: % | D53: FY26 guidance 14-16% total; FY31-35 fades to 5.0/6.5/8.0% (bear/base/bull) | F53: =F207/E207-1 -> 0.14257069 | G53: =G207/F207-1 -> 0.17281645 | H53: =H207/G207-1 -> 0.14332304 | I53: =I207/H207-1 -> 0.18868083 | J53: =CHOOSE($E$3,J50,J51,J52)+$E$11 -> 0.15 | K53: =CHOOSE($E$3,K50,K51,K52)+$E$11 -> 0.13 | L53: =CHOOSE($E$3,L50,L51,L52)+$E$11 -> 0.12 | M53: =CHOOSE($E$3,M50,M51,M52)+$E$11 -> 0.11 | N53: =CHOOSE($E$3,N50,N51,N52)+$E$11 -> 0.1 | O53: =CHOOSE($E$3,O50,O51,O52)+$E$11 -> 0.093 | P53: =CHOOSE($E$3,P50,P51,P52)+$E$11 -> 0.086 | Q53: =CHOOSE($E$3,Q50,Q51,Q52)+$E$11 -> 0.079 | ... S53: =CHOOSE($E$3,S50,S51,S52)+$E$11 -> 0.065
B54: Financing growth - Commercial - Bear | C54: % | J54: 0.025 | K54: 0.045 | L54: 0.045 | M54: 0.045 | N54: 0.045 | O54: 0.046 | P54: 0.047 | Q54: 0.048 | R54: 0.049 | S54: 0.05
B55: Financing growth - Commercial - Base | C55: % | J55: 0.06 | K55: 0.08 | L55: 0.08 | M55: 0.08 | N55: 0.08 | O55: 0.077 | P55: 0.074 | Q55: 0.071 | R55: 0.068 | S55: 0.065
B56: Financing growth - Commercial - Bull | C56: % | J56: 0.085 | K56: 0.105 | L56: 0.105 | M56: 0.105 | N56: 0.105 | O56: 0.1 | P56: 0.095 | Q56: 0.09 | R56: 0.085 | S56: 0.08
B57: Financing growth - Commercial (live) | C57: % | D57: FY26 guidance 14-16% total; FY31-35 fades to 5.0/6.5/8.0% (bear/base/bull) | F57: =F208/E208-1 -> 0.22663462 | G57: =G208/F208-1 -> 0.20623971 | H57: =H208/G208-1 -> 0.14511308 | I57: =I208/H208-1 -> 0.13256909 | J57: =CHOOSE($E$3,J54,J55,J56)+$E$11 -> 0.06 | K57: =CHOOSE($E$3,K54,K55,K56)+$E$11 -> 0.08 | L57: =CHOOSE($E$3,L54,L55,L56)+$E$11 -> 0.08 | M57: =CHOOSE($E$3,M54,M55,M56)+$E$11 -> 0.08 | N57: =CHOOSE($E$3,N54,N55,N56)+$E$11 -> 0.08 | O57: =CHOOSE($E$3,O54,O55,O56)+$E$11 -> 0.077 | P57: =CHOOSE($E$3,P54,P55,P56)+$E$11 -> 0.074 | Q57: =CHOOSE($E$3,Q54,Q55,Q56)+$E$11 -> 0.071 | ... S57: =CHOOSE($E$3,S54,S55,S56)+$E$11 -> 0.065
B58: Financing growth - SME - Bear | C58: % | J58: 0.115 | K58: 0.095 | L58: 0.085 | M58: 0.075 | N58: 0.065 | O58: 0.062 | P58: 0.059 | Q58: 0.056 | R58: 0.053 | S58: 0.05
B59: Financing growth - SME - Base | C59: % | J59: 0.15 | K59: 0.13 | L59: 0.12 | M59: 0.11 | N59: 0.1 | O59: 0.093 | P59: 0.086 | Q59: 0.079 | R59: 0.072 | S59: 0.065
B60: Financing growth - SME - Bull | C60: % | J60: 0.175 | K60: 0.155 | L60: 0.145 | M60: 0.135 | N60: 0.125 | O60: 0.116 | P60: 0.107 | Q60: 0.098 | R60: 0.089 | S60: 0.08
B61: Financing growth - SME (live) | C61: % | D61: FY26 guidance 14-16% total; FY31-35 fades to 5.0/6.5/8.0% (bear/base/bull) | F61: =F209/E209-1 -> 0.032021858 | G61: =G209/F209-1 -> 0.024144869 | H61: =H209/G209-1 -> 0.1184469 | I61: =I209/H209-1 -> 0.13673554 | J61: =CHOOSE($E$3,J58,J59,J60)+$E$11 -> 0.15 | K61: =CHOOSE($E$3,K58,K59,K60)+$E$11 -> 0.13 | L61: =CHOOSE($E$3,L58,L59,L60)+$E$11 -> 0.12 | M61: =CHOOSE($E$3,M58,M59,M60)+$E$11 -> 0.11 | N61: =CHOOSE($E$3,N58,N59,N60)+$E$11 -> 0.1 | O61: =CHOOSE($E$3,O58,O59,O60)+$E$11 -> 0.093 | P61: =CHOOSE($E$3,P58,P59,P60)+$E$11 -> 0.086 | Q61: =CHOOSE($E$3,Q58,Q59,Q60)+$E$11 -> 0.079 | ... S61: =CHOOSE($E$3,S58,S59,S60)+$E$11 -> 0.065
B62: Financing growth - Micro - Bear | C62: % | J62: 0.045 | K62: 0.055 | L62: 0.055 | M62: 0.055 | N62: 0.055 | O62: 0.054 | P62: 0.053 | Q62: 0.052 | R62: 0.051 | S62: 0.05
B63: Financing growth - Micro - Base | C63: % | J63: 0.08 | K63: 0.09 | L63: 0.09 | M63: 0.09 | N63: 0.09 | O63: 0.085 | P63: 0.08 | Q63: 0.075 | R63: 0.07 | S63: 0.065
B64: Financing growth - Micro - Bull | C64: % | J64: 0.105 | K64: 0.115 | L64: 0.115 | M64: 0.115 | N64: 0.115 | O64: 0.108 | P64: 0.101 | Q64: 0.094 | R64: 0.087 | S64: 0.08
B65: Financing growth - Micro (live) | C65: % | D65: FY26 guidance 14-16% total; FY31-35 fades to 5.0/6.5/8.0% (bear/base/bull) | F65: =F210/E210-1 -> 0.32907801 | G65: =G210/F210-1 -> 0.2226254 | H65: =H210/G210-1 -> 0.21098115 | I65: =I210/H210-1 -> -0.0028472573 | J65: =CHOOSE($E$3,J62,J63,J64)+$E$11 -> 0.08 | K65: =CHOOSE($E$3,K62,K63,K64)+$E$11 -> 0.09 | L65: =CHOOSE($E$3,L62,L63,L64)+$E$11 -> 0.09 | M65: =CHOOSE($E$3,M62,M63,M64)+$E$11 -> 0.09 | N65: =CHOOSE($E$3,N62,N63,N64)+$E$11 -> 0.09 | O65: =CHOOSE($E$3,O62,O63,O64)+$E$11 -> 0.085 | P65: =CHOOSE($E$3,P62,P63,P64)+$E$11 -> 0.08 | Q65: =CHOOSE($E$3,Q62,Q63,Q64)+$E$11 -> 0.075 | ... S65: =CHOOSE($E$3,S62,S63,S64)+$E$11 -> 0.065
B66: Financing growth - Consumer incl. gold & card - Bear | C66: % | J66: 0.125 | K66: 0.105 | L66: 0.085 | M66: 0.075 | N66: 0.065 | O66: 0.062 | P66: 0.059 | Q66: 0.056 | R66: 0.053 | S66: 0.05
B67: Financing growth - Consumer incl. gold & card - Base | C67: % | J67: 0.16 | K67: 0.14 | L67: 0.12 | M67: 0.11 | N67: 0.1 | O67: 0.093 | P67: 0.086 | Q67: 0.079 | R67: 0.072 | S67: 0.065
B68: Financing growth - Consumer incl. gold & card - Bull | C68: % | J68: 0.185 | K68: 0.165 | L68: 0.145 | M68: 0.135 | N68: 0.125 | O68: 0.116 | P68: 0.107 | Q68: 0.098 | R68: 0.089 | S68: 0.08
B69: Financing growth - Consumer incl. gold & card (live) | C69: % | D69: FY26 guidance 14-16% total; FY31-35 fades to 5.0/6.5/8.0% (bear/base/bull) | F69: =F211/E211-1 -> 0.25989218 | G69: =G211/F211-1 -> 0.15656257 | H69: =H211/G211-1 -> 0.16343539 | I69: =I211/H211-1 -> 0.15737772 | J69: =CHOOSE($E$3,J66,J67,J68)+$E$11 -> 0.16 | K69: =CHOOSE($E$3,K66,K67,K68)+$E$11 -> 0.14 | L69: =CHOOSE($E$3,L66,L67,L68)+$E$11 -> 0.12 | M69: =CHOOSE($E$3,M66,M67,M68)+$E$11 -> 0.11 | N69: =CHOOSE($E$3,N66,N67,N68)+$E$11 -> 0.1 | O69: =CHOOSE($E$3,O66,O67,O68)+$E$11 -> 0.093 | P69: =CHOOSE($E$3,P66,P67,P68)+$E$11 -> 0.086 | Q69: =CHOOSE($E$3,Q66,Q67,Q68)+$E$11 -> 0.079 | ... S69: =CHOOSE($E$3,S66,S67,S68)+$E$11 -> 0.065
B70: CASA ratio - Bear | C70: % | J70: 0.595 | K70: 0.585 | L70: 0.58 | M70: 0.58 | N70: 0.58 | O70: 0.58 | P70: 0.58 | Q70: 0.58 | R70: 0.58 | S70: 0.58
B71: CASA ratio - Base | C71: % | J71: 0.61 | K71: 0.61 | L71: 0.61 | M71: 0.61 | N71: 0.61 | O71: 0.61 | P71: 0.61 | Q71: 0.61 | R71: 0.61 | S71: 0.61
B72: CASA ratio - Bull | C72: % | J72: 0.62 | K72: 0.625 | L72: 0.63 | M72: 0.63 | N72: 0.63 | O72: 0.63 | P72: 0.63 | Q72: 0.63 | R72: 0.63 | S72: 0.63
B73: CASA ratio (live) | C73: % | E73: =(E219+E220)/E222 -> 0.57908273 | F73: =(F219+F220)/F222 -> 0.61571909 | G73: =(G219+G220)/G222 -> 0.60565739 | H73: =(H219+H220)/H222 -> 0.60121422 | I73: =(I219+I220)/I222 -> 0.61619653 | J73: =CHOOSE($E$3,J70,J71,J72) -> 0.61 | K73: =CHOOSE($E$3,K70,K71,K72) -> 0.61 | L73: =CHOOSE($E$3,L70,L71,L72) -> 0.61 | M73: =CHOOSE($E$3,M70,M71,M72) -> 0.61 | N73: =CHOOSE($E$3,N70,N71,N72) -> 0.61 | O73: =CHOOSE($E$3,O70,O71,O72) -> 0.61 | P73: =CHOOSE($E$3,P70,P71,P72) -> 0.61 | Q73: =CHOOSE($E$3,Q70,Q71,Q72) -> 0.61 | ... S73: =CHOOSE($E$3,S70,S71,S72) -> 0.61
B74: FDR target (financing / third-party funds) | C74: % | D74: EST path - RESEARCH mgmt LDR view | E74: =E212/E222 -> 0.73420917 | F74: =F212/F222 -> 0.7943065 | G74: =G212/G222 -> 0.8180274 | H74: =H212/H222 -> 0.85044312 | I74: =I212/I222 -> 0.8379848 | J74: 0.85 | K74: 0.86 | L74: 0.87 | M74: 0.87 | N74: 0.87 | O74: 0.87 | P74: 0.87 | Q74: 0.87 | R74: 0.87 | S74: 0.87
B76: 1d. Scenario drivers - pricing | E76: FY21A | F76: FY22A | G76: FY23A | H76: FY24A | I76: FY25A | J76: FY26E | K76: FY27E | L76: FY28E | M76: FY29E | N76: FY30E | O76: FY31E | P76: FY32E | Q76: FY33E | R76: FY34E | S76: FY35E
B77: Change in gross margin yield - Bear | C77: pp | J77: -0.0095 | K77: 0 | L77: 0 | M77: 0 | N77: 0 | O77: 0 | P77: 0 | Q77: 0 | R77: 0 | S77: 0
B78: Change in gross margin yield - Base | C78: pp | J78: -0.009 | K78: 0 | L78: 0 | M78: 0 | N78: 0 | O78: 0 | P78: 0 | Q78: 0 | R78: 0 | S78: 0
B79: Change in gross margin yield - Bull | C79: pp | J79: -0.0085 | K79: 0 | L79: 0.0005 | M79: 0.0005 | N79: 0.0005 | O79: 0 | P79: 0 | Q79: 0 | R79: 0 | S79: 0
B80: Change in gross margin yield (live) | C80: pp | D80: 1H26 reported yield -76bp YoY | F80: =F235-E235 -> 0.1035521 | G80: =G235-F235 -> -0.0042184011 | H80: =H235-G235 -> -0.0018072995 | I80: =I235-H235 -> -0.0028861633 | J80: =CHOOSE($E$3,J77,J78,J79)+$E$8 -> -0.009 | K80: =CHOOSE($E$3,K77,K78,K79)+$E$8 -> 0 | L80: =CHOOSE($E$3,L77,L78,L79)+$E$8 -> 0 | M80: =CHOOSE($E$3,M77,M78,M79)+$E$8 -> 0 | N80: =CHOOSE($E$3,N77,N78,N79)+$E$8 -> 0 | O80: =CHOOSE($E$3,O77,O78,O79)+$E$8 -> 0 | P80: =CHOOSE($E$3,P77,P78,P79)+$E$8 -> 0 | Q80: =CHOOSE($E$3,Q77,Q78,Q79)+$E$8 -> 0 | ... S80: =CHOOSE($E$3,S77,S78,S79)+$E$8 -> 0
B81: Change in time-deposit rate (ex BI pass-through) - Bear | C81: pp | J81: -0.0085 | K81: 0 | L81: 0 | M81: 0 | N81: 0 | O81: 0 | P81: 0 | Q81: 0 | R81: 0 | S81: 0
B82: Change in time-deposit rate (ex BI pass-through) - Base | C82: pp | J82: -0.01 | K82: 0 | L82: 0 | M82: 0 | N82: 0 | O82: 0 | P82: 0 | Q82: 0 | R82: 0 | S82: 0
B83: Change in time-deposit rate (ex BI pass-through) - Bull | C83: pp | J83: -0.0115 | K83: -0.0005 | L83: 0 | M83: 0 | N83: 0 | O83: 0 | P83: 0 | Q83: 0 | R83: 0 | S83: 0
B84: Change in time-deposit rate (ex BI pass-through) (live) | C84: pp | D84: 1H26 CoF -49bp YoY | F84: =F226-E226 -> -0.006 | G84: =G226-F226 -> 0.013 | H84: =H226-G226 -> 0.004 | I84: =I226-H226 -> -0.001 | J84: =CHOOSE($E$3,J81,J82,J83)+$E$15 -> -0.01 | K84: =CHOOSE($E$3,K81,K82,K83)+$E$15 -> 0 | L84: =CHOOSE($E$3,L81,L82,L83)+$E$15 -> 0 | M84: =CHOOSE($E$3,M81,M82,M83)+$E$15 -> 0 | N84: =CHOOSE($E$3,N81,N82,N83)+$E$15 -> 0 | O84: =CHOOSE($E$3,O81,O82,O83)+$E$15 -> 0 | P84: =CHOOSE($E$3,P81,P82,P83)+$E$15 -> 0 | Q84: =CHOOSE($E$3,Q81,Q82,Q83)+$E$15 -> 0 | ... S84: =CHOOSE($E$3,S81,S82,S83)+$E$15 -> 0
B85: Change in CASA rate (ex BI pass-through) | C85: pp | J85: -0.003 | K85: 0 | L85: 0 | M85: 0 | N85: 0 | O85: 0 | P85: 0 | Q85: 0 | R85: 0 | S85: 0
B87: 1e. Scenario drivers - fees, cost, credit, payout | E87: FY21A | F87: FY22A | G87: FY23A | H87: FY24A | I87: FY25A | J87: FY26E | K87: FY27E | L87: FY28E | M87: FY29E | N87: FY30E | O87: FY31E | P87: FY32E | Q87: FY33E | R87: FY34E | S87: FY35E
B88: Fee-based income growth - Bear | C88: % | J88: 0.2 | K88: 0.08 | L88: 0.06 | M88: 0.06 | N88: 0.06 | O88: 0.058 | P88: 0.056 | Q88: 0.054 | R88: 0.052 | S88: 0.05
B89: Fee-based income growth - Base | C89: % | J89: 0.25 | K89: 0.15 | L89: 0.12 | M89: 0.1 | N89: 0.1 | O89: 0.094 | P89: 0.088 | Q89: 0.082 | R89: 0.076 | S89: 0.07
B90: Fee-based income growth - Bull | C90: % | J90: 0.32 | K90: 0.2 | L90: 0.15 | M90: 0.12 | N90: 0.12 | O90: 0.114 | P90: 0.108 | Q90: 0.102 | R90: 0.096 | S90: 0.09
B91: Fee-based income growth (live) | C91: % | D91: 1H26 +38% YoY | F91: =F144/E144-1 -> 0.22868816 | G91: =G144/F144-1 -> 0.13600105 | H91: =H144/G144-1 -> 0.32156593 | I91: =I144/H144-1 -> 0.24837977 | J91: =CHOOSE($E$3,J88,J89,J90)+$E$12 -> 0.25 | K91: =CHOOSE($E$3,K88,K89,K90)+$E$12 -> 0.15 | L91: =CHOOSE($E$3,L88,L89,L90)+$E$12 -> 0.12 | M91: =CHOOSE($E$3,M88,M89,M90)+$E$12 -> 0.1 | N91: =CHOOSE($E$3,N88,N89,N90)+$E$12 -> 0.1 | O91: =CHOOSE($E$3,O88,O89,O90)+$E$12 -> 0.094 | P91: =CHOOSE($E$3,P88,P89,P90)+$E$12 -> 0.088 | Q91: =CHOOSE($E$3,Q88,Q89,Q90)+$E$12 -> 0.082 | ... S91: =CHOOSE($E$3,S88,S89,S90)+$E$12 -> 0.07
B92: Cost-to-income ratio - Bear | C92: % | J92: 0.555 | K92: 0.54 | L92: 0.535 | M92: 0.535 | N92: 0.53 | O92: 0.53 | P92: 0.53 | Q92: 0.53 | R92: 0.53 | S92: 0.53
B93: Cost-to-income ratio - Base | C93: % | J93: 0.545 | K93: 0.52 | L93: 0.515 | M93: 0.51 | N93: 0.505 | O93: 0.505 | P93: 0.505 | Q93: 0.505 | R93: 0.505 | S93: 0.505
B94: Cost-to-income ratio - Bull | C94: % | J94: 0.535 | K94: 0.505 | L94: 0.495 | M94: 0.49 | N94: 0.485 | O94: 0.485 | P94: 0.485 | Q94: 0.485 | R94: 0.485 | S94: 0.485
B95: Cost-to-income ratio (live) | C95: % | D95: 1H26 CIR 52.7% | E95: =E149/E145 -> 0.53417114 | F95: =F149/F145 -> 0.51292945 | G95: =G149/G145 -> 0.50086417 | H95: =H149/H145 -> 0.51353393 | I95: =I149/I145 -> 0.52562269 | J95: =CHOOSE($E$3,J92,J93,J94)+$E$10 -> 0.545 | K95: =CHOOSE($E$3,K92,K93,K94)+$E$10 -> 0.52 | L95: =CHOOSE($E$3,L92,L93,L94)+$E$10 -> 0.515 | M95: =CHOOSE($E$3,M92,M93,M94)+$E$10 -> 0.51 | N95: =CHOOSE($E$3,N92,N93,N94)+$E$10 -> 0.505 | O95: =CHOOSE($E$3,O92,O93,O94)+$E$10 -> 0.505 | P95: =CHOOSE($E$3,P92,P93,P94)+$E$10 -> 0.505 | Q95: =CHOOSE($E$3,Q92,Q93,Q94)+$E$10 -> 0.505 | ... S95: =CHOOSE($E$3,S92,S93,S94)+$E$10 -> 0.505
B96: Cost of credit (provisions / avg financing) - Bear | C96: % | J96: 0.009 | K96: 0.01 | L96: 0.01 | M96: 0.009 | N96: 0.009 | O96: 0.009 | P96: 0.009 | Q96: 0.009 | R96: 0.009 | S96: 0.009
B97: Cost of credit (provisions / avg financing) - Base | C97: % | J97: 0.007 | K97: 0.0075 | L97: 0.0075 | M97: 0.0075 | N97: 0.0075 | O97: 0.0075 | P97: 0.0075 | Q97: 0.0075 | R97: 0.0075 | S97: 0.0075
B98: Cost of credit (provisions / avg financing) - Bull | C98: % | J98: 0.006 | K98: 0.006 | L98: 0.0065 | M98: 0.0065 | N98: 0.0065 | O98: 0.0065 | P98: 0.0065 | Q98: 0.0065 | R98: 0.0065 | S98: 0.0065
B99: Cost of credit (provisions / avg financing) (live) | C99: % | D99: Guidance <1.00%; 1H26 0.62% | F99: =F151/AVERAGE(F212,E212) -> 0.019782831 | G99: =G151/AVERAGE(G212,F212) -> 0.011706973 | H99: =H151/AVERAGE(H212,G212) -> 0.0073009944 | I99: =I151/AVERAGE(I212,H212) -> 0.0078916871 | J99: =CHOOSE($E$3,J96,J97,J98)+$E$9 -> 0.007 | K99: =CHOOSE($E$3,K96,K97,K98)+$E$9 -> 0.0075 | L99: =CHOOSE($E$3,L96,L97,L98)+$E$9 -> 0.0075 | M99: =CHOOSE($E$3,M96,M97,M98)+$E$9 -> 0.0075 | N99: =CHOOSE($E$3,N96,N97,N98)+$E$9 -> 0.0075 | O99: =CHOOSE($E$3,O96,O97,O98)+$E$9 -> 0.0075 | P99: =CHOOSE($E$3,P96,P97,P98)+$E$9 -> 0.0075 | Q99: =CHOOSE($E$3,Q96,Q97,Q98)+$E$9 -> 0.0075 | ... S99: =CHOOSE($E$3,S96,S97,S98)+$E$9 -> 0.0075
B100: Gross NPF - Bear | C100: % | J100: 0.021 | K100: 0.024 | L100: 0.023 | M100: 0.022 | N100: 0.021 | O100: 0.021 | P100: 0.021 | Q100: 0.021 | R100: 0.021 | S100: 0.021
B101: Gross NPF - Base | C101: % | J101: 0.0185 | K101: 0.0185 | L101: 0.018 | M101: 0.018 | N101: 0.018 | O101: 0.018 | P101: 0.018 | Q101: 0.018 | R101: 0.018 | S101: 0.018
B102: Gross NPF - Bull | C102: % | J102: 0.0175 | K102: 0.0165 | L102: 0.016 | M102: 0.016 | N102: 0.016 | O102: 0.016 | P102: 0.016 | Q102: 0.016 | R102: 0.016 | S102: 0.016
B103: Gross NPF (live) | C103: % | D103: Hist = reported (FY21: Q4-23 public expose) | E103: 0.0293 | F103: 0.0242 | G103: 0.0208 | H103: 0.019 | I103: 0.0181 | J103: =CHOOSE($E$3,J100,J101,J102) -> 0.0185 | K103: =CHOOSE($E$3,K100,K101,K102) -> 0.0185 | L103: =CHOOSE($E$3,L100,L101,L102) -> 0.018 | M103: =CHOOSE($E$3,M100,M101,M102) -> 0.018 | N103: =CHOOSE($E$3,N100,N101,N102) -> 0.018 | O103: =CHOOSE($E$3,O100,O101,O102) -> 0.018 | P103: =CHOOSE($E$3,P100,P101,P102) -> 0.018 | Q103: =CHOOSE($E$3,Q100,Q101,Q102) -> 0.018 | ... S103: =CHOOSE($E$3,S100,S101,S102) -> 0.018
B104: NPF coverage (CKPN / gross NPF) | C104: % | D104: Hist = reported | E104: 1.4887 | F104: 1.8312 | G104: 1.9435 | H104: 1.9501 | I104: 1.9088 | J104: 1.9 | K104: 1.9 | L104: 1.9 | M104: 1.9 | N104: 1.9 | O104: 1.9 | P104: 1.9 | Q104: 1.9 | R104: 1.9 | S104: 1.9
B105: Dividend payout ratio (on year-t earnings, paid t+1) - Bear | C105: % | J105: 0.2 | K105: 0.2 | L105: 0.2 | M105: 0.2 | N105: 0.2 | O105: 0.3 | P105: 0.35 | Q105: 0.4 | R105: 0.45 | S105: 0.5
...

Sheet Valuation_Checks
A1: Valuation cross-checks
A2: Cross-check methods only; the target price comes from Sheet1 (DDM = residual income). Peer multiples and their implied prices sit in Sheet1 section 5.
A4: 1. Banking FCFE (excess capital over the target CAR is distributable) | B4: Dec-25 | C4: Valuation date | D4: 12m PT
A5: Banking FCFE value per share (Rp) | B5: =(SUMPRODUCT(Sheet1!J416:S416,Sheet1!J377:S377)+Sheet1!E383*Sheet1!E382*Sheet1!S175/(Sheet1!S378-Sheet1!E31)*Sheet1!S377)/Sheet1!E21*1000 -> 2356.9226 | C5: =B5*(1+Sheet1!E34)^Sheet1!E399-Sheet1!E400 -> 2526.1039 | D5: =C5*(1+Sheet1!E34)-Sheet1!E401 -> 2769.6155 | H5: FCFE = NI + OCI - target CAR x change in RWA (Sheet1 row 416). Above DDM because the target CAR (Sheet1 E35) is below the forecast CAR.
A7: 2. Price-to-book cross-checks | B7: Value / share (Rp) | C7: Multiple
A8: Justified P/B on FY26E BVPS = (average ROE FY26E-35E - g)/(Ke - g) | B8: =C8*Sheet1!J351 -> 1736.88 | C8: =(AVERAGE(Sheet1!J347:S347)-Sheet1!E31)/(Sheet1!S378-Sheet1!E31) -> 1.3611977
A9: Exit P/B at peer median (MRQ) on FY35E BVPS, plus PV of dividends FY26E-35E | B9: =SUM(Sheet1!J381:S381)+C9*Sheet1!S351*Sheet1!S377 -> 1562.6414 | C9: =Sheet1!G466 -> 1.1117615 | H9: Exit multiple = peer median P/B on Jun-26 book (Sheet1 G466), not a judgement input.
A10: Average of the two P/B checks | B10: =AVERAGE(B8:B9) -> 1649.7607
A12: 3. Sensitivity: value per share at Dec-25 (Rp), flat Ke (around the stable Ke) down, terminal growth across; spread = live | B12: 3.5% | C12: 4.0% | D12: 4.5% | E12: 5.0% | F12: 5.5%
A13: Terminal growth | B13: 0.035 | C13: 0.04 | D13: 0.045 | E13: 0.05 | F13: 0.055
A14: =Sheet1!$S$378+(-0.02) -> 0.1025 | B14: =(Sheet1!$I$175+SUMPRODUCT((Sheet1!$J$154:$S$154-$A14*Sheet1!$I$175:$R$175)/(1+$A14)^Sheet1!$J$376:$S$376)+Sheet1!$S$175*(Sheet1!$E$382-Sheet1!$S$378)/($A14-B$13)/(1+$A14)^10)/Sheet1!$E$21*1000 -> 2191.4118 | C14: =(Sheet1!$I$175+SUMPRODUCT((Sheet1!$J$154:$S$154-$A14*Sheet1!$I$175:$R$175)/(1+$A14)^Sheet1!$J$376:$S$376)+Sheet1!$S$175*(Sheet1!$E$382-Sheet1!$S$378)/($A14-C$13)/(1+$A14)^10)/Sheet1!$E$21*1000 -> 2222.1614 | D14: =(Sheet1!$I$175+SUMPRODUCT((Sheet1!$J$154:$S$154-$A14*Sheet1!$I$175:$R$175)/(1+$A14)^Sheet1!$J$376:$S$376)+Sheet1!$S$175*(Sheet1!$E$382-Sheet1!$S$378)/($A14-D$13)/(1+$A14)^10)/Sheet1!$E$21*1000 -> 2258.2587 | E14: =(Sheet1!$I$175+SUMPRODUCT((Sheet1!$J$154:$S$154-$A14*Sheet1!$I$175:$R$175)/(1+$A14)^Sheet1!$J$376:$S$376)+Sheet1!$S$175*(Sheet1!$E$382-Sheet1!$S$378)/($A14-E$13)/(1+$A14)^10)/Sheet1!$E$21*1000 -> 2301.2318 | F14: =(Sheet1!$I$175+SUMPRODUCT((Sheet1!$J$154:$S$154-$A14*Sheet1!$I$175:$R$175)/(1+$A14)^Sheet1!$J$376:$S$376)+Sheet1!$S$175*(Sheet1!$E$382-Sheet1!$S$378)/($A14-F$13)/(1+$A14)^10)/Sheet1!$E$21*1000 -> 2353.2517 | H14: Row 3 is the live Ke; column 3 is the Base spread. Terminal growth = Sheet1 E31.
A15: =Sheet1!$S$378+(-0.01) -> 0.1125 | B15: =(Sheet1!$I$175+SUMPRODUCT((Sheet1!$J$154:$S$154-$A15*Sheet1!$I$175:$R$175)/(1+$A15)^Sheet1!$J$376:$S$376)+Sheet1!$S$175*(Sheet1!$E$382-Sheet1!$S$378)/($A15-B$13)/(1+$A15)^10)/Sheet1!$E$21*1000 -> 1966.8415 | C15: =(Sheet1!$I$175+SUMPRODUCT((Sheet1!$J$154:$S$154-$A15*Sheet1!$I$175:$R$175)/(1+$A15)^Sheet1!$J$376:$S$376)+Sheet1!$S$175*(Sheet1!$E$382-Sheet1!$S$378)/($A15-C$13)/(1+$A15)^10)/Sheet1!$E$21*1000 -> 1987.936 | D15: =(Sheet1!$I$175+SUMPRODUCT((Sheet1!$J$154:$S$154-$A15*Sheet1!$I$175:$R$175)/(1+$A15)^Sheet1!$J$376:$S$376)+Sheet1!$S$175*(Sheet1!$E$382-Sheet1!$S$378)/($A15-D$13)/(1+$A15)^10)/Sheet1!$E$21*1000 -> 2012.1556 | E15: =(Sheet1!$I$175+SUMPRODUCT((Sheet1!$J$154:$S$154-$A15*Sheet1!$I$175:$R$175)/(1+$A15)^Sheet1!$J$376:$S$376)+Sheet1!$S$175*(Sheet1!$E$382-Sheet1!$S$378)/($A15-E$13)/(1+$A15)^10)/Sheet1!$E$21*1000 -> 2040.2504 | F15: =(Sheet1!$I$175+SUMPRODUCT((Sheet1!$J$154:$S$154-$A15*Sheet1!$I$175:$R$175)/(1+$A15)^Sheet1!$J$376:$S$376)+Sheet1!$S$175*(Sheet1!$E$382-Sheet1!$S$378)/($A15-F$13)/(1+$A15)^10)/Sheet1!$E$21*1000 -> 2073.2312
A16: =Sheet1!$S$378+(0) -> 0.1225 | B16: =(Sheet1!$I$175+SUMPRODUCT((Sheet1!$J$154:$S$154-$A16*Sheet1!$I$175:$R$175)/(1+$A16)^Sheet1!$J$376:$S$376)+Sheet1!$S$175*(Sheet1!$E$382-Sheet1!$S$378)/($A16-B$13)/(1+$A16)^10)/Sheet1!$E$21*1000 -> 1775.8334 | C16: =(Sheet1!$I$175+SUMPRODUCT((Sheet1!$J$154:$S$154-$A16*Sheet1!$I$175:$R$175)/(1+$A16)^Sheet1!$J$376:$S$376)+Sheet1!$S$175*(Sheet1!$E$382-Sheet1!$S$378)/($A16-C$13)/(1+$A16)^10)/Sheet1!$E$21*1000 -> 1790.847 | D16: =(Sheet1!$I$175+SUMPRODUCT((Sheet1!$J$154:$S$154-$A16*Sheet1!$I$175:$R$175)/(1+$A16)^Sheet1!$J$376:$S$376)+Sheet1!$S$175*(Sheet1!$E$382-Sheet1!$S$378)/($A16-D$13)/(1+$A16)^10)/Sheet1!$E$21*1000 -> 1807.7978 | E16: =(Sheet1!$I$175+SUMPRODUCT((Sheet1!$J$154:$S$154-$A16*Sheet1!$I$175:$R$175)/(1+$A16)^Sheet1!$J$376:$S$376)+Sheet1!$S$175*(Sheet1!$E$382-Sheet1!$S$378)/($A16-E$13)/(1+$A16)^10)/Sheet1!$E$21*1000 -> 1827.0866 | F16: =(Sheet1!$I$175+SUMPRODUCT((Sheet1!$J$154:$S$154-$A16*Sheet1!$I$175:$R$175)/(1+$A16)^Sheet1!$J$376:$S$376)+Sheet1!$S$175*(Sheet1!$E$382-Sheet1!$S$378)/($A16-F$13)/(1+$A16)^10)/Sheet1!$E$21*1000 -> 1849.233
A17: =Sheet1!$S$378+(0.01) -> 0.1325 | B17: =(Sheet1!$I$175+SUMPRODUCT((Sheet1!$J$154:$S$154-$A17*Sheet1!$I$175:$R$175)/(1+$A17)^Sheet1!$J$376:$S$376)+Sheet1!$S$175*(Sheet1!$E$382-Sheet1!$S$378)/($A17-B$13)/(1+$A17)^10)/Sheet1!$E$21*1000 -> 1610.595 | C17: =(Sheet1!$I$175+SUMPRODUCT((Sheet1!$J$154:$S$154-$A17*Sheet1!$I$175:$R$175)/(1+$A17)^Sheet1!$J$376:$S$376)+Sheet1!$S$175*(Sheet1!$E$382-Sheet1!$S$378)/($A17-C$13)/(1+$A17)^10)/Sheet1!$E$21*1000 -> 1621.5921 | D17: =(Sheet1!$I$175+SUMPRODUCT((Sheet1!$J$154:$S$154-$A17*Sheet1!$I$175:$R$175)/(1+$A17)^Sheet1!$J$376:$S$376)+Sheet1!$S$175*(Sheet1!$E$382-Sheet1!$S$378)/($A17-D$13)/(1+$A17)^10)/Sheet1!$E$21*1000 -> 1633.8461 | E17: =(Sheet1!$I$175+SUMPRODUCT((Sheet1!$J$154:$S$154-$A17*Sheet1!$I$175:$R$175)/(1+$A17)^Sheet1!$J$376:$S$376)+Sheet1!$S$175*(Sheet1!$E$382-Sheet1!$S$378)/($A17-E$13)/(1+$A17)^10)/Sheet1!$E$21*1000 -> 1647.5854 | F17: =(Sheet1!$I$175+SUMPRODUCT((Sheet1!$J$154:$S$154-$A17*Sheet1!$I$175:$R$175)/(1+$A17)^Sheet1!$J$376:$S$376)+Sheet1!$S$175*(Sheet1!$E$382-Sheet1!$S$378)/($A17-F$13)/(1+$A17)^10)/Sheet1!$E$21*1000 -> 1663.0975
A18: =Sheet1!$S$378+(0.02) -> 0.1425 | B18: =(Sheet1!$I$175+SUMPRODUCT((Sheet1!$J$154:$S$154-$A18*Sheet1!$I$175:$R$175)/(1+$A18)^Sheet1!$J$376:$S$376)+Sheet1!$S$175*(Sheet1!$E$382-Sheet1!$S$378)/($A18-B$13)/(1+$A18)^10)/Sheet1!$E$21*1000 -> 1465.9083 | C18: =(Sheet1!$I$175+SUMPRODUCT((Sheet1!$J$154:$S$154-$A18*Sheet1!$I$175:$R$175)/(1+$A18)^Sheet1!$J$376:$S$376)+Sheet1!$S$175*(Sheet1!$E$382-Sheet1!$S$378)/($A18-C$13)/(1+$A18)^10)/Sheet1!$E$21*1000 -> 1474.1518 | D18: =(Sheet1!$I$175+SUMPRODUCT((Sheet1!$J$154:$S$154-$A18*Sheet1!$I$175:$R$175)/(1+$A18)^Sheet1!$J$376:$S$376)+Sheet1!$S$175*(Sheet1!$E$382-Sheet1!$S$378)/($A18-D$13)/(1+$A18)^10)/Sheet1!$E$21*1000 -> 1483.2409 | E18: =(Sheet1!$I$175+SUMPRODUCT((Sheet1!$J$154:$S$154-$A18*Sheet1!$I$175:$R$175)/(1+$A18)^Sheet1!$J$376:$S$376)+Sheet1!$S$175*(Sheet1!$E$382-Sheet1!$S$378)/($A18-E$13)/(1+$A18)^10)/Sheet1!$E$21*1000 -> 1493.3125 | F18: =(Sheet1!$I$175+SUMPRODUCT((Sheet1!$J$154:$S$154-$A18*Sheet1!$I$175:$R$175)/(1+$A18)^Sheet1!$J$376:$S$376)+Sheet1!$S$175*(Sheet1!$E$382-Sheet1!$S$378)/($A18-F$13)/(1+$A18)^10)/Sheet1!$E$21*1000 -> 1504.5352
A19: Flat Ke at the stable level; the model uses a rising path from the year-1 Ke, so no cell equals Sheet1 E387.
A21: 4. Weight on relative valuation: value today and 12m target (Rp per share) | B21: Today | C21: 12m target
A22: 0 | B22: =(1-A22)*Sheet1!$E$402+A22*Sheet1!$E$411 -> 2019.8393 | C22: =(1-A22)*AVERAGE(Sheet1!$E$404,Sheet1!$E$405)+A22*(Sheet1!$E$411*(1+Sheet1!$E$34)-Sheet1!$E$401) -> 2206.4988 | H22: Row = weight on relative valuation (Sheet1 E29). Relative value today = Sheet1 E411; 12m = rolled at Ke less the next dividend.
A23: 0.2 | B23: =(1-A23)*Sheet1!$E$402+A23*Sheet1!$E$411 -> 1844.3247 | C23: =(1-A23)*AVERAGE(Sheet1!$E$404,Sheet1!$E$405)+A23*(Sheet1!$E$411*(1+Sheet1!$E$34)-Sheet1!$E$401) -> 2011.2744
A24: 0.25 | B24: =(1-A24)*Sheet1!$E$402+A24*Sheet1!$E$411 -> 1800.446 | C24: =(1-A24)*AVERAGE(Sheet1!$E$404,Sheet1!$E$405)+A24*(Sheet1!$E$411*(1+Sheet1!$E$34)-Sheet1!$E$401) -> 1962.4683
A25: 0.33333333 | B25: =(1-A25)*Sheet1!$E$402+A25*Sheet1!$E$411 -> 1727.315 | C25: =(1-A25)*AVERAGE(Sheet1!$E$404,Sheet1!$E$405)+A25*(Sheet1!$E$411*(1+Sheet1!$E$34)-Sheet1!$E$401) -> 1881.1248
A26: 0.4 | B26: =(1-A26)*Sheet1!$E$402+A26*Sheet1!$E$411 -> 1668.8101 | C26: =(1-A26)*AVERAGE(Sheet1!$E$404,Sheet1!$E$405)+A26*(Sheet1!$E$411*(1+Sheet1!$E$34)-Sheet1!$E$401) -> 1816.05
A27: 0.5 | B27: =(1-A27)*Sheet1!$E$402+A27*Sheet1!$E$411 -> 1581.0528 | C27: =(1-A27)*AVERAGE(Sheet1!$E$404,Sheet1!$E$405)+A27*(Sheet1!$E$411*(1+Sheet1!$E$34)-Sheet1!$E$401) -> 1718.4378

Sheet Charts
B1: Charts (data blocks sit above each chart; schedules read from Sheet1)
B2: Chart 1 - Operating income bridge FY25A to FY35E (Rp bn)
E3: Value | F3: Base (hidden) | G3: Increase | H3: Decrease | I3: Total | J3: Cumulative
B4: FY25A operating income | E4: =Sheet1!$I$145 -> 26065.682 | F4: 0 | G4: 0 | H4: 0 | I4: =E4 -> 26065.682 | J4: =E4 -> 26065.682
B5: Financing volume | E5: =(Sheet1!$S$214-Sheet1!$I$214)*Sheet1!$I$235 -> 46413.355 | F5: =MIN(J4,J4+E5) -> 26065.682 | G5: =MAX(E5,0) -> 46413.355 | H5: =MAX(-E5,0) -> 0 | I5: 0 | J5: =J4+E5 -> 72479.037
B6: Gross yield | E6: =(Sheet1!$S$235-Sheet1!$I$235)*Sheet1!$S$214 -> -7397.6373 | F6: =MIN(J5,J5+E6) -> 65081.4 | G6: =MAX(E6,0) -> 0 | H6: =MAX(-E6,0) -> 7397.6373 | I6: 0 | J6: =J5+E6 -> 65081.4
B7: Funding cost | E7: =-(Sheet1!$S$142-Sheet1!$I$142) -> -6558.6895 | F7: =MIN(J6,J6+E7) -> 58522.71 | G7: =MAX(E7,0) -> 0 | H7: =MAX(-E7,0) -> 6558.6895 | I7: 0 | J7: =J6+E7 -> 58522.71
B8: Fee income | E8: =Sheet1!$S$144-Sheet1!$I$144 -> 13100.149 | F8: =MIN(J7,J7+E8) -> 58522.71 | G8: =MAX(E8,0) -> 13100.149 | H8: =MAX(-E8,0) -> 0 | I8: 0 | J8: =J7+E8 -> 71622.859
B9: Rights-issue capital deployed | E9: =Sheet1!$S$326 -> 575.28 | F9: =MIN(J8,J8+E9) -> 71622.859 | G9: =MAX(E9,0) -> 575.28 | H9: =MAX(-E9,0) -> 0 | I9: 0 | J9: =J8+E9 -> 72198.139
B10: FY35E operating income | E10: =Sheet1!$S$145 -> 72198.139 | F10: 0 | G10: 0 | H10: 0 | I10: =E10 -> 72198.139 | J10: =E10 -> 72198.139
B11: Check: cumulative before end total = end total | E11: =J9-E10 -> 0
B33: Chart 2 - Net margin income bridge FY25A to FY35E (Rp bn)
E34: Value | F34: Base (hidden) | G34: Increase | H34: Decrease | I34: Total | J34: Cumulative
B35: FY25A NMI | E35: =Sheet1!$I$143 -> 19129.086 | F35: 0 | G35: 0 | H35: 0 | I35: =E35 -> 19129.086 | J35: =E35 -> 19129.086
B36: Earning-asset volume | E36: =(Sheet1!$S$214-Sheet1!$I$214)*Sheet1!$I$235 -> 46413.355 | F36: =MIN(J35,J35+E36) -> 19129.086 | G36: =MAX(E36,0) -> 46413.355 | H36: =MAX(-E36,0) -> 0 | I36: 0 | J36: =J35+E36 -> 65542.441
B37: Gross yield | E37: =(Sheet1!$S$235-Sheet1!$I$235)*Sheet1!$S$214 -> -7397.6373 | F37: =MIN(J36,J36+E37) -> 58144.804 | G37: =MAX(E37,0) -> 0 | H37: =MAX(-E37,0) -> 7397.6373 | I37: 0 | J37: =J36+E37 -> 58144.804
B38: Funding volume | E38: =-(AVERAGE(Sheet1!$S$222,Sheet1!$R$222)-AVERAGE(Sheet1!$I$222,Sheet1!$H$222))*Sheet1!$I$229 -> -14274.034 | F38: =MIN(J37,J37+E38) -> 43870.77 | G38: =MAX(E38,0) -> 0 | H38: =MAX(-E38,0) -> 14274.034 | I38: 0 | J38: =J37+E38 -> 43870.77
B39: Funding rate | E39: =-(Sheet1!$S$229-Sheet1!$I$229)*AVERAGE(Sheet1!$S$222,Sheet1!$R$222) -> 7715.3443 | F39: =MIN(J38,J38+E39) -> 43870.77 | G39: =MAX(E39,0) -> 7715.3443 | H39: =MAX(-E39,0) -> 0 | I39: 0 | J39: =J38+E39 -> 51586.114
B40: Rights-issue capital deployed | E40: =Sheet1!$S$326 -> 575.28 | F40: =MIN(J39,J39+E40) -> 51586.114 | G40: =MAX(E40,0) -> 575.28 | H40: =MAX(-E40,0) -> 0 | I40: 0 | J40: =J39+E40 -> 52161.394
B41: FY35E NMI | E41: =Sheet1!$S$143 -> 52161.394 | F41: 0 | G41: 0 | H41: 0 | I41: =E41 -> 52161.394 | J41: =E41 -> 52161.394
B42: Check: cumulative before end total = end total | E42: =J40-E41 -> 0
B64: Chart 3 - Revenue-to-net-profit walk FY35E (Rp bn)
E65: Value | F65: Base (hidden) | G65: Increase | H65: Decrease | I65: Total | J65: Cumulative
B66: Gross margin income | E66: =Sheet1!$S$141 -> 67856.489 | F66: 0 | G66: 0 | H66: 0 | I66: =E66 -> 67856.489 | J66: =E66 -> 67856.489
B67: Profit-sharing expense | E67: =-Sheet1!$S$142 -> -15695.095 | F67: =MIN(J66,J66+E67) -> 52161.394 | G67: =MAX(E67,0) -> 0 | H67: =MAX(-E67,0) -> 15695.095 | I67: 0 | J67: =J66+E67 -> 52161.394
B68: Fee income | E68: =Sheet1!$S$144 -> 20036.745 | F68: =MIN(J67,J67+E68) -> 52161.394 | G68: =MAX(E68,0) -> 20036.745 | H68: =MAX(-E68,0) -> 0 | I68: 0 | J68: =J67+E68 -> 72198.139
B69: Overhead | E69: =-Sheet1!$S$149 -> -36460.06 | F69: =MIN(J68,J68+E69) -> 35738.079 | G69: =MAX(E69,0) -> 0 | H69: =MAX(-E69,0) -> 36460.06 | I69: 0 | J69: =J68+E69 -> 35738.079
B70: Provisions | E70: =-Sheet1!$S$151 -> -5918.1099 | F70: =MIN(J69,J69+E70) -> 29819.969 | G70: =MAX(E70,0) -> 0 | H70: =MAX(-E70,0) -> 5918.1099 | I70: 0 | J70: =J69+E70 -> 29819.969
B71: Tax & other | E71: =-Sheet1!$S$153 -> -7329.1398 | F71: =MIN(J70,J70+E71) -> 22490.829 | G71: =MAX(E71,0) -> 0 | H71: =MAX(-E71,0) -> 7329.1398 | I71: 0 | J71: =J70+E71 -> 22490.829
B72: Net profit FY35E | E72: =Sheet1!$S$154 -> 22490.829 | F72: 0 | G72: 0 | H72: 0 | I72: =E72 -> 22490.829 | J72: =E72 -> 22490.829
B73: Check: cumulative before end total = end total | E73: =J71-E72 -> 0
B95: Chart 7 - ROE walk FY25A to FY35E (% of avg equity)
E96: Value | F96: Base (hidden) | G96: Increase | H96: Decrease | I96: Total | J96: Cumulative
B97: FY25A ROE | E97: =Sheet1!$I$359 -> 0.15604034 | F97: 0 | G97: 0 | H97: 0 | I97: =E97 -> 0.15604034 | J97: =E97 -> 0.15604034
B98: NMI / equity | E98: =Sheet1!$S$354-Sheet1!$I$354 -> -0.05537199 | F98: =MIN(J97,J97+E98) -> 0.10066835 | G98: =MAX(E98,0) -> 0 | H98: =MAX(-E98,0) -> 0.05537199 | I98: 0 | J98: =J97+E98 -> 0.10066835
B99: Fees / equity | E99: =Sheet1!$S$355-Sheet1!$I$355 -> -0.012785922 | F99: =MIN(J98,J98+E99) -> 0.087882424 | G99: =MAX(E99,0) -> 0 | H99: =MAX(-E99,0) -> 0.012785922 | I99: 0 | J99: =J98+E99 -> 0.087882424
B100: Overhead / equity | E100: =Sheet1!$S$356-Sheet1!$I$356 -> 0.045503774 | F100: =MIN(J99,J99+E100) -> 0.087882424 | G100: =MAX(E100,0) -> 0.045503774 | H100: =MAX(-E100,0) -> 0 | I100: 0 | J100: =J99+E100 -> 0.1333862
B101: Provisions / equity | E101: =Sheet1!$S$357-Sheet1!$I$357 -> 0.010130218 | F101: =MIN(J100,J100+E101) -> 0.1333862 | G101: =MAX(E101,0) -> 0.010130218 | H101: =MAX(-E101,0) -> 0 | I101: 0 | J101: =J100+E101 -> 0.14351642
B102: Tax / equity | E102: =Sheet1!$S$358-Sheet1!$I$358 -> 0.0026807337 | F102: =MIN(J101,J101+E102) -> 0.14351642 | G102: =MAX(E102,0) -> 0.0026807337 | H102: =MAX(-E102,0) -> 0 | I102: 0 | J102: =J101+E102 -> 0.14619715
B103: FY35E ROE | E103: =Sheet1!$S$359 -> 0.14619715 | F103: 0 | G103: 0 | H103: 0 | I103: =E103 -> 0.14619715 | J103: =E103 -> 0.14619715
B104: Check: cumulative before end total = end total | E104: =J102-E103 -> 0
B126: Chart 9 - Residual income value bridge, Rp per share @ Dec-25
E127: Value | F127: Base (hidden) | G127: Increase | H127: Decrease | I127: Total | J127: Cumulative
B128: BVPS FY25A | E128: =Sheet1!$I$175/Sheet1!$E$21*1000 -> 1126.2456 | F128: 0 | G128: 0 | H128: 0 | I128: =E128 -> 1126.2456 | J128: =E128 -> 1126.2456
B129: PV RI FY26E | E129: =Sheet1!$J$392/Sheet1!$E$21*1000 -> 50.42195 | F129: =MIN(J128,J128+E129) -> 1126.2456 | G129: =MAX(E129,0) -> 50.42195 | H129: =MAX(-E129,0) -> 0 | I129: 0 | J129: =J128+E129 -> 1176.6675
B130: PV RI FY27E | E130: =Sheet1!$K$392/Sheet1!$E$21*1000 -> 64.855401 | F130: =MIN(J129,J129+E130) -> 1176.6675 | G130: =MAX(E130,0) -> 64.855401 | H130: =MAX(-E130,0) -> 0 | I130: 0 | J130: =J129+E130 -> 1241.5229
B131: PV RI FY28E | E131: =Sheet1!$L$392/Sheet1!$E$21*1000 -> 56.81323 | F131: =MIN(J130,J130+E131) -> 1241.5229 | G131: =MAX(E131,0) -> 56.81323 | H131: =MAX(-E131,0) -> 0 | I131: 0 | J131: =J130+E131 -> 1298.3361
B132: PV RI FY29E | E132: =Sheet1!$M$392/Sheet1!$E$21*1000 -> 55.939916 | F132: =MIN(J131,J131+E132) -> 1298.3361 | G132: =MAX(E132,0) -> 55.939916 | H132: =MAX(-E132,0) -> 0 | I132: 0 | J132: =J131+E132 -> 1354.2761
B133: PV RI FY30E | E133: =Sheet1!$N$392/Sheet1!$E$21*1000 -> 52.976266 | F133: =MIN(J132,J132+E133) -> 1354.2761 | G133: =MAX(E133,0) -> 52.976266 | H133: =MAX(-E133,0) -> 0 | I133: 0 | J133: =J132+E133 -> 1407.2523
B134: PV RI FY31-35E | E134: =SUM(Sheet1!$O$392:$S$392)/Sheet1!$E$21*1000 -> 190.63353 | F134: =MIN(J133,J133+E134) -> 1407.2523 | G134: =MAX(E134,0) -> 190.63353 | H134: =MAX(-E134,0) -> 0 | I134: 0 | J134: =J133+E134 -> 1597.8858
B135: PV terminal RI | E135: =Sheet1!$E$394/Sheet1!$E$21*1000 -> 292.73486 | F135: =MIN(J134,J134+E135) -> 1597.8858 | G135: =MAX(E135,0) -> 292.73486 | H135: =MAX(-E135,0) -> 0 | I135: 0 | J135: =J134+E135 -> 1890.6207
B136: RI value / share | E136: =Sheet1!$E$396 -> 1890.6207 | F136: 0 | G136: 0 | H136: 0 | I136: =E136 -> 1890.6207 | J136: =E136 -> 1890.6207
B137: Check: cumulative before end total = end total | E137: =J135-E136 -> 0
B159: Chart 10 - Football field data (Rp per share; DDM/RI/blend = Bear to Bull 12m PT from snapshot)
E160: Low | F160: Range (high-low) | G160: High
B161: DDM 12m PT (Bear-Bull) | E161: =Sheet1!E437 -> 1368.0841 | F161: =MAX(G161-E161,0) -> 1820.3939 | G161: =Sheet1!G437 -> 3188.478
B162: RI 12m PT (Bear-Bull) | E162: =Sheet1!E438 -> 1368.0841 | F162: =MAX(G162-E162,0) -> 1820.3939 | G162: =Sheet1!G438 -> 3188.478
B163: Blended 12m PT (Bear-Bull) | E163: =Sheet1!E439 -> 1325.1816 | F163: =MAX(G163-E163,0) -> 1206.9308 | G163: =Sheet1!G439 -> 2532.1125
B164: Peer P/B regression (+/-10%) | E164: =IFERROR(Sheet1!$E$473*0.9,0) -> 1012.9127 | F164: =MAX(G164-E164,0) -> 225.0917 | G164: =IFERROR(Sheet1!$E$473*1.1,0) -> 1238.0044
B165: Peer-median P/B (+/-10%) | E165: =IFERROR(Sheet1!$E$474*0.9,0) -> 1107.1173 | F165: =MAX(G165-E165,0) -> 246.02606 | G165: =IFERROR(Sheet1!$E$474*1.1,0) -> 1353.1433
B166: 52-week trading range | E166: =Sheet1!$E$475 -> 1095 | F166: =MAX(G166-E166,0) -> 1645 | G166: =Sheet1!$E$476 -> 2740
B167: Sell-side TP range (consensus avg ~2,740) | E167: =Sheet1!$E$477 -> 2460 | F167: =MAX(G167-E167,0) -> 1340 | G167: =Sheet1!$E$478 -> 3800
B168: Current price | E168: =Sheet1!$E$20*0.995 -> 1089.525 | F168: =MAX(G168-E168,0) -> 10.95 | G168: =Sheet1!$E$20*1.005 -> 1100.475
B190: Chart 7 - Tornado (data in section 4i, static snapshot)
B212: Charts 8-11 read the schedules directly (CAR, ROE vs cost of equity, financing and net profit, CIR and cost of credit)
B213: CAR target line | C213: % | E213: =Sheet1!$E$35 -> 0.2 | F213: =Sheet1!$E$35 -> 0.2 | G213: =Sheet1!$E$35 -> 0.2 | H213: =Sheet1!$E$35 -> 0.2 | I213: =Sheet1!$E$35 -> 0.2 | J213: =Sheet1!$E$35 -> 0.2 | K213: =Sheet1!$E$35 -> 0.2 | L213: =Sheet1!$E$35 -> 0.2 | ... S213: =Sheet1!$E$35 -> 0.2
B214: CAR regulatory minimum line | C214: % | E214: =Sheet1!$E$36 -> 0.1349 | F214: =Sheet1!$E$36 -> 0.1349 | G214: =Sheet1!$E$36 -> 0.1349 | H214: =Sheet1!$E$36 -> 0.1349 | I214: =Sheet1!$E$36 -> 0.1349 | J214: =Sheet1!$E$36 -> 0.1349 | K214: =Sheet1!$E$36 -> 0.1349 | L214: =Sheet1!$E$36 -> 0.1349 | ... S214: =Sheet1!$E$36 -> 0.1349
B215: Cost of equity line | C215: % | E215: =Sheet1!$J$378 -> 0.11229724 | F215: =Sheet1!$J$378 -> 0.11229724 | G215: =Sheet1!$J$378 -> 0.11229724 | H215: =Sheet1!$J$378 -> 0.11229724 | I215: =Sheet1!$J$378 -> 0.11229724 | J215: =Sheet1!J378 -> 0.11229724 | K215: =Sheet1!K378 -> 0.11343088 | L215: =Sheet1!L378 -> 0.11456452 | M215: =Sheet1!M378 -> 0.11569816 | N215: =Sheet1!N378 -> 0.1168318 | O215: =Sheet1!O378 -> 0.11796544 | P215: =Sheet1!P378 -> 0.11909908 | Q215: =Sheet1!Q378 -> 0.12023272 | ... S215: =Sheet1!S378 -> 0.1225

Sheet Terminal_ROE
A1: Terminal ROE: evidence, choice and sensitivity
A2: Rule: terminal ROE = stable cost of equity (Sheet1 S378, beta 1.0) + spread (Sheet1 row 39). Country risk therefore raises Ke and terminal ROE together, and the same terminal ROE drives the DDM (payout 1 - g/ROE) and the residual income terminal value, so both give the same value.
A4: 1. Evidence (live links) | B4: ROE | C4: Spread vs Ke
A6: Stable cost of equity (FY35E, floor: no excess return) | B6: =Sheet1!S378 -> 0.1225 | C6: =B6-$B$6 -> 0 | H6: Damodaran limiting case for stable growth: excess returns competed away
A7: Market-implied sustainable ROE at current price | B7: =Sheet1!E414 -> 0.12034991 | C7: =B7-$B$6 -> -0.002150091 | H7: PB x (Ke - g) + g at the current price
A8: BBNI ROE, 1H26 annualised (lowest-ROE KBMI 4 state bank) | B8: =Sheet1!J461 -> 0.1299486 | C8: =B8-$B$6 -> 0.0074486015 | H8: BBNI 1H26 statements
A9: BRIS ROE, 1H26 annualised | B9: =Sheet1!J464 -> 0.16139695 | C9: =B9-$B$6 -> 0.03889695 | H9: 1H26 interim statement
A10: BRIS highest annual ROE FY22A-FY25A | B10: =MAX(Sheet1!F347:I347) -> 0.1672435 | C10: =B10-$B$6 -> 0.044743496 | H10: Annual reports
A11: Midpoint of Ke and model FY35E ROE | B11: =AVERAGE(B6,B14) -> 0.13434857 | C11: =B11-$B$6 -> 0.011848575 | H11: Half of the FY35E excess return survives in perpetuity
A12: Peer median ROE, 1H26 annualised (5 banks incl. BTPS) | B12: =Sheet1!J466 -> 0.1871695 | C12: =B12-$B$6 -> 0.064669505 | H12: Includes BBCA and BMRI, which have structural franchise advantages
A13: BRIS lowest annual ROE FY22A-FY25A | B13: =MIN(Sheet1!F347:I347) -> 0.14559142 | C13: =B13-$B$6 -> 0.023091415 | H13: Annual reports
A14: Model FY35E ROE (end of explicit forecast) | B14: =Sheet1!S347 -> 0.14619715 | C14: =B14-$B$6 -> 0.02369715 | H14: Output of the operating drivers
A15: BRIS average ROE FY22A-FY25A | B15: =AVERAGE(Sheet1!F347:I347) -> 0.15669375 | C15: =B15-$B$6 -> 0.034193748 | H15: Annual reports
A17: 2. Choice by scenario | B17: Bear | C17: Base | D17: Bull
A18: Spread over Ke (input, Sheet1 row 39) | B18: =Sheet1!E39 -> 0 | C18: =Sheet1!F39 -> 0.02 | D18: =Sheet1!G39 -> 0.04
A19: Terminal ROE at live Ke | B19: =$B$6+B18 -> 0.1225 | C19: =$B$6+C18 -> 0.1425 | D19: =$B$6+D18 -> 0.1625
A20: Implied terminal P/B = (ROE - g)/(Ke - g), Base g | B20: =(B19-Sheet1!$F$30)/($B$6-Sheet1!$F$30) -> 1 | C20: =(C19-Sheet1!$F$30)/($B$6-Sheet1!$F$30) -> 1.2580645 | D20: =(D19-Sheet1!$F$30)/($B$6-Sheet1!$F$30) -> 1.516129
A21: Sustainable terminal payout = 1 - g/ROE, Base g | B21: =1-Sheet1!$F$30/B19 -> 0.63265306 | C21: =1-Sheet1!$F$30/C19 -> 0.68421053 | D21: =1-Sheet1!$F$30/D19 -> 0.72307692
A23: Why these spreads
A24: Bear, +0pp (= stable Ke, about 12.3%): no excess return in perpetuity (Damodaran limiting case); close to the market-implied sustainable ROE at the current price (row 7) and to BBNI ROE TTM (row 8).
A25: Base, +2.0pp (about 14.3%): just below BRIS's lowest annual ROE of FY22A-FY25A (row 13) and the model FY35E ROE (row 14), so the case assumes modest erosion of today's returns; implied terminal P/B about 1.3x sits between the peer median of about 1.2x (Sheet1 G466) and BRIS's FY22-FY25 year-end range of 1.8x-2.9x; sustainable payout about 68% is close to the FY35E policy payout of 65% (Sheet1 S106).
A26: Bull, +4.0pp (about 16.3%): BRIS keeps the returns it earned in FY22A-FY25A (average row 15, highest row 10).
A27: Peer ROEs: 1H26 interim statements and presentations, profit annualised. BRIS from its 1H26 interim statement.
A29: 3. Sensitivity of intrinsic value (DDM = RI) to the spread; target-price blend excluded | B29: Spread | C29: Terminal ROE | D29: Terminal P/B | E29: Value Dec-25 (Rp) | F29: 12m PT (Rp) | G29: Upside
B30: 0 | C30: =(Sheet1!$S$378+B30) -> 0.1225 | D30: =((Sheet1!$S$378+B30)-Sheet1!$E$31)/(Sheet1!$S$378-Sheet1!$E$31) -> 1 | E30: =(Sheet1!$I$175+SUM(Sheet1!$J$392:$S$392)+Sheet1!$S$175*B30/(Sheet1!$S$378-Sheet1!$E$31)*Sheet1!$S$377)/Sheet1!$E$21*1000 -> 1597.8858 | F30: =(E30*(1+Sheet1!$E$34)^Sheet1!$E$399-Sheet1!$E$400)*(1+Sheet1!$E$34)-Sheet1!$E$401 -> 1852.9856 | G30: =F30/Sheet1!$E$20-1 -> 0.69222429
B31: 0.01 | C31: =(Sheet1!$S$378+B31) -> 0.1325 | D31: =((Sheet1!$S$378+B31)-Sheet1!$E$31)/(Sheet1!$S$378-Sheet1!$E$31) -> 1.1290323 | E31: =(Sheet1!$I$175+SUM(Sheet1!$J$392:$S$392)+Sheet1!$S$175*B31/(Sheet1!$S$378-Sheet1!$E$31)*Sheet1!$S$377)/Sheet1!$E$21*1000 -> 1744.2533 | F31: =(E31*(1+Sheet1!$E$34)^Sheet1!$E$399-Sheet1!$E$400)*(1+Sheet1!$E$34)-Sheet1!$E$401 -> 2029.7422 | G31: =F31/Sheet1!$E$20-1 -> 0.85364585
B32: 0.02 | C32: =(Sheet1!$S$378+B32) -> 0.1425 | D32: =((Sheet1!$S$378+B32)-Sheet1!$E$31)/(Sheet1!$S$378-Sheet1!$E$31) -> 1.2580645 | E32: =(Sheet1!$I$175+SUM(Sheet1!$J$392:$S$392)+Sheet1!$S$175*B32/(Sheet1!$S$378-Sheet1!$E$31)*Sheet1!$S$377)/Sheet1!$E$21*1000 -> 1890.6207 | F32: =(E32*(1+Sheet1!$E$34)^Sheet1!$E$399-Sheet1!$E$400)*(1+Sheet1!$E$34)-Sheet1!$E$401 -> 2206.4988 | G32: =F32/Sheet1!$E$20-1 -> 1.0150674
B33: 0.03 | C33: =(Sheet1!$S$378+B33) -> 0.1525 | D33: =((Sheet1!$S$378+B33)-Sheet1!$E$31)/(Sheet1!$S$378-Sheet1!$E$31) -> 1.3870968 | E33: =(Sheet1!$I$175+SUM(Sheet1!$J$392:$S$392)+Sheet1!$S$175*B33/(Sheet1!$S$378-Sheet1!$E$31)*Sheet1!$S$377)/Sheet1!$E$21*1000 -> 2036.9881 | F33: =(E33*(1+Sheet1!$E$34)^Sheet1!$E$399-Sheet1!$E$400)*(1+Sheet1!$E$34)-Sheet1!$E$401 -> 2383.2554 | G33: =F33/Sheet1!$E$20-1 -> 1.176489
B34: 0.04 | C34: =(Sheet1!$S$378+B34) -> 0.1625 | D34: =((Sheet1!$S$378+B34)-Sheet1!$E$31)/(Sheet1!$S$378-Sheet1!$E$31) -> 1.516129 | E34: =(Sheet1!$I$175+SUM(Sheet1!$J$392:$S$392)+Sheet1!$S$175*B34/(Sheet1!$S$378-Sheet1!$E$31)*Sheet1!$S$377)/Sheet1!$E$21*1000 -> 2183.3556 | F34: =(E34*(1+Sheet1!$E$34)^Sheet1!$E$399-Sheet1!$E$400)*(1+Sheet1!$E$34)-Sheet1!$E$401 -> 2560.012 | G34: =F34/Sheet1!$E$20-1 -> 1.3379105
B35: 0.05 | C35: =(Sheet1!$S$378+B35) -> 0.1725 | D35: =((Sheet1!$S$378+B35)-Sheet1!$E$31)/(Sheet1!$S$378-Sheet1!$E$31) -> 1.6451613 | E35: =(Sheet1!$I$175+SUM(Sheet1!$J$392:$S$392)+Sheet1!$S$175*B35/(Sheet1!$S$378-Sheet1!$E$31)*Sheet1!$S$377)/Sheet1!$E$21*1000 -> 2329.723 | F35: =(E35*(1+Sheet1!$E$34)^Sheet1!$E$399-Sheet1!$E$400)*(1+Sheet1!$E$34)-Sheet1!$E$401 -> 2736.7687 | G35: =F35/Sheet1!$E$20-1 -> 1.4993321
A36: Check: table at live spread equals Sheet1 intrinsic 12m value (must be 0) | B36: =ROUND(((Sheet1!$I$175+SUM(Sheet1!$J$392:$S$392)+Sheet1!$S$175*(Sheet1!$E$382-Sheet1!$S$378)/(Sheet1!$S$378-Sheet1!$E$31)*Sheet1!$S$377)/Sheet1!$E$21*1000*(1+Sheet1!$E$34)^Sheet1!$E$399-Sheet1!$E$400)*(1+Sheet1!$E$34)-Sheet1!$E$401-AVERAGE(Sheet1!$E$404,Sheet1!$E$405),6) -> 0

Sheet Beta_Evidence
A1: Beta evidence and cost of equity
A3: Observed betas (inputs, blue) | B3: Beta | C3: Source
A4: BRIS regression beta, 1Y | B4: 0.64 | C4: TradingView IDX:BRIS 1Y (checked by user 7-Oct-26). Alip labels this raw 0.64 as "2y weekly vs IHSG" (Bloomberg?): source and period to be confirmed
A5: BRIS regression beta, 5Y | B5: 0.13 | C5: TradingView IDX:BRIS (user-supplied). Not usable: very low explanatory power.
A6: BMRI regression beta, 5Y | B6: -0.05 | C6: TradingView (user-supplied). Shows IDX bank regressions vs IHSG are not informative.
A7: Damodaran Global Banks (Regional), 825 firms | B7: 0.51 | C7: Damodaran, Jan 2026, Betas by sector
A8: Damodaran Global Money Center, 604 firms | B8: 0.7 | C8: Damodaran, Jan 2026
A9: Damodaran US Money Center | B9: 0.76 | C9: Damodaran, Jan 2026
A10: Damodaran total market | B10: 1.04 | C10: Damodaran, Jan 2026
A11: BRIS regression beta, 60m monthly vs IHSG (own calc, sheet Beta) | B11: =Beta!B28 -> 0.69327187 | C11: Own regression from Investing.com monthly closes; standard error about 0.29, R-squared about 0.09: low precision
A12: Blume-adjusted selected raw beta = 0.67 x raw + 0.33 (feeds Sheet1 E26) | B12: =0.67*B39+0.33 -> 0.7588
A14: Cost of equity under two framings
A15: Risk-free (IDR), net of default spread | B15: =Sheet1!E24 -> 0.0556
A16: Total ERP incl. country risk (Indonesia) | B16: =Sheet1!E25 -> 0.0669
A17: Country risk premium (CRP) | B17: 0.0246 | C17: Damodaran Jan 2026, Indonesia (Baa2)
A18: Mature-market ERP = total ERP - CRP | B18: =B16-B17 -> 0.0423
A19: Beta used in model, year 1 (Sheet1!E26) | B19: =Sheet1!E26 -> 0.7588
A20: Ke year 1 (Sheet1!E28, method per B41) | B20: =Sheet1!E28 -> 0.11229724
A21: Ke (lambda, lambda=1): rf + CRP + beta x mature ERP, using BRIS 1Y raw | B21: =B15+B17+B4*B18 -> 0.107272
A22: Ke (lambda) using Blume-adjusted beta | B22: =B15+B17+B12*B18 -> 0.11229724
A23: Beta to enter in model to match lambda Ke (Blume) | B23: =(B22-B15)/B16 -> 0.84749238
A25: Sensitivity of the 12m blended target to the raw-beta choice (static runs; lambda method and beta convergence on)
A26: Raw beta choice (Beta_Evidence B38) | B26: Ke year 1 | C26: PT Bear | D26: PT Base | E26: PT Bull | F26: Prob-weighted PT | G26: Upside (prob-wtd)
A27: 1. TradingView 1Y raw 0.64 (default) | B27: 0.11229724 | C27: 1325.1816 | D27: 1881.1248 | E27: 2532.1125 | F27: =Prob_Justification!$B$25*C27+Prob_Justification!$B$26*D27+Prob_Justification!$B$27*E27 -> 1854.5971 | G27: =F27/Sheet1!$E$20-1 -> 0.69369602
A28: 2. Own 60m regression raw 0.69 | B28: 0.11380702 | C28: 1321.569 | D28: 1875.2219 | E28: 2523.4718 | F28: =Prob_Justification!$B$25*C28+Prob_Justification!$B$26*D28+Prob_Justification!$B$27*E28 -> 1848.7919 | G28: =F28/Sheet1!$E$20-1 -> 0.68839441
A29: 3. KSI broker raw 0.937 | B29: 0.12071452 | C29: 1305.3055 | D29: 1848.6233 | E29: 2484.5206 | F29: =Prob_Justification!$B$25*C29+Prob_Justification!$B$26*D29+Prob_Justification!$B$27*E29 -> 1822.6342 | G29: =F29/Sheet1!$E$20-1 -> 0.66450612
A30: 4. Manual raw 1.00 | B30: 0.1225 | C30: 1301.1714 | D30: 1841.8555 | E30: 2474.6055 | F30: =Prob_Justification!$B$25*C30+Prob_Justification!$B$26*D30+Prob_Justification!$B$27*E30 -> 1815.9789 | G30: =F30/Sheet1!$E$20-1 -> 0.6584282
A32: Static values from running the integrated workbook v11.2 on 17-Oct-26 (peers on 1H26 data). They do not update if inputs change. Ratings are not concluded here.
A33: Other observed estimates (not used in the model)
A34: Broker beta (KSI Equity Update, 10 Sep 2026, p.3) | B34: 0.937 | C34: Regression window and benchmark not disclosed
A35: TradingView 1Y beta, retrieved 17 Oct 2026 | B35: 0.63 | C35: Model keeps 0.64 (checked 7 Oct 2026); difference is within estimation error
A37: Beta and country-risk settings (feed Sheet1 cost of equity)
A38: Raw beta choice: 1 TradingView 1Y, 2 own 60m regression, 3 KSI broker, 4 manual | B38: 1 | C38: Default 1: model raw beta 0.64 (confirm source with Alip). With convergence on, the choice moves value about 3%.
A39: Selected raw beta | B39: =CHOOSE(B38,B4,B11,B34,B40) -> 0.64
A40: Manual raw beta | B40: 1
A41: Country risk premium: 1 = scaled by beta (Ke = rf + beta x total ERP), 2 = added in full (lambda = 1) | B41: 2 | C41: Default 2 (Damodaran lambda approach): a domestic bank carries the full country risk; scaling the 2.46% CRP by a 0.76 beta understates it. Relevant after MSCI consulted on reclassifying Indonesia to Standalone Market (15 Oct 2026).
A42: Beta converges to 1.0 by FY35E: 1 = yes, 0 = no | B42: 1 | C42: Default 1: Damodaran stable-growth convention, beta moves to 1.0 in the terminal period.

Sheet Prob_Justification
A1: Scenario probability justification
A2: Method: Base fixed by how much of FY26 is already known; the remaining probability is split Bear/Bull by the balance of dated evidence. Structured judgement, not a statistical estimate. Blue cells are inputs.
A4: Step 1. Base probability | C4: Why
A5: Probability of Base | B5: 0.5 | C5: 1H26 is reported (6 of 12 months of FY26). Base FY26 drivers sit on the 1H26 run-rate and inside management 2026 targets (financing +10-14%, cost of credit <0.84%, NIM >5.50%). Outcomes beyond FY26 are open, so no more than half.
A7: Step 2. Evidence tally (1 = point to that side) | B7: Weight | C7: Evidence (source) | D7: Direction
A8: HBH growth only +2.0% in 1H26 | B8: 1 | C8: Net funding income lagging asset growth, margin pressure (Q2 interim statement) | D8: Down
A9: Opex +17.5% vs revenue +10.5% | B9: 1 | C9: Cost growth above revenue; 2H25 CIR was 55.4% vs 52.6% in 1H26 (interim statements, AR2025) | D9: Down
A10: Q2 net income -11% QoQ | B10: 1 | C10: Earnings momentum slowing into 2H (Q1 and Q2 2026 statements) | D10: Down
A11: Fee income +55%, securities gains +42% not repeatable | B11: 1 | C11: Rahn is 33% of fee income; part of 1H26 income is one-off or concentrated | D11: Down
A12: Recoveries -24% | B12: 1 | C12: Support to cost of credit is fading; Base impairment already normalises to 0.80% | D12: Down
A13: Related-party musyarakah financing +45% YTD | B13: 1 | C13: Concentration and governance watch item (Q2 statement) | D13: Down
A14: Macro: BI-Rate 5.75%, SUN 10Y 7.16%, rupiah, geopolitics | B14: 1 | C14: Group view; raises funding cost and credit risk (Antara, market data 1 Oct 2026) | D14: Down
A15: Financing +16.2% YoY (Aug-26), DPK +17.7% | B15: 1 | C15: Growth ahead of the 10-14% 2026 target (OJK Aug-26, Q2 statement) | D15: Up
A16: Cost of credit 0.62% in 1H26 vs guidance <0.84% | B16: 1 | C16: Asset quality better than guided (interim statement) | D16: Up
A17: CAR 22-24% after rights issue | B17: 1 | C17: Capital buffer funds growth and absorbs stress (Prospektus, Q2 statement) | D17: Up
A18: Payout rising from 20% toward 30% | B18: 1 | C18: Capital-return optionality (AR2025 dividend policy) | D18: Up
A19: Industry credit growth 8-12% (BI) and sharia share rising | B19: 1 | C19: Structural tailwind (AR2025 p.182) | D19: Up
A21: Weight on downside evidence | B21: =SUMIF(D8:D19,"Down",B8:B19) -> 7
A22: Weight on upside evidence | B22: =SUMIF(D8:D19,"Up",B8:B19) -> 5
A24: Step 3. Resulting probabilities
A25: Bear = (1 - Base) x down / (down + up) | B25: =(1-B5)*B21/(B21+B22) -> 0.29166667
A26: Base | B26: =B5 -> 0.5
A27: Bull = (1 - Base) x up / (down + up) | B27: =(1-B5)*B22/(B21+B22) -> 0.20833333
A28: Check: sums to 100% (must be 0) | B28: =B25+B26+B27-1 -> 0
A30: Why Bear carries more weight than Bull: (1) the Bull case needs five drivers to move favourably at once, while a bank credit-cycle shock moves them together on the downside; (2) the 1H26 beat came from items flagged as not repeatable; (3) macro and rate risk is placed here, in cash flows, not in the cost of equity. Equal weights (33/33/33) would ignore that asymmetry; 25/50/25 would ignore the dated downside evidence.

Sheet Damodaran_Audit
A1: Audit against Damodaran bank valuation, live on the integrated model (active scenario)
A3: 1. Structural checks (live) | B3: Value | G3: Reading
A4: Cost of equity year 1 / stable (C4) | B4: =Sheet1!E34 -> 0.11229724 | C4: =Sheet1!S378 -> 0.1225 | G4: Ke only, no WACC: consistent (debt is raw material for a bank)
A5: Risk-free, IDR (gross yield less default spread) | B5: =Sheet1!E24 -> 0.0556 | G5: Local-currency rf, CRP counted once inside ERP
A6: Terminal growth g (live) | B6: =Sheet1!E31 -> 0.045 | G6: =IF(B6>B5,"g above rf: reduce","g does not exceed rf: OK") -> g does not exceed rf: OK
A7: Terminal ROE = Ke + spread (Sheet1 row 39) | B7: =Sheet1!E382 -> 0.1425 | G7: Tied to Ke; evidence in sheet Terminal_ROE
A8: Excess return in perpetuity = terminal ROE - Ke | B8: =Sheet1!E382-Sheet1!S378 -> 0.02 | G8: Damodaran: stable-growth ROE should converge to Ke plus a modest spread
A9: Terminal P/B implied = (ROE - g)/(Ke - g) | B9: =(B7-B6)/(B4-B6) -> 1.4487964 | G9: Compare with the historical range in section 3 (1.8x to 2.9x year-end, 1.3x today)
A10: Residual-income terminal value share of RI equity value | B10: =Sheet1!E394/Sheet1!E395 -> 0.15483532 | G10: Share of RI value from the terminal excess return
A11: DDM terminal value share of DDM value | B11: =Sheet1!E388 -> 0.75482218 | G11: Above about 75% means DDM is mostly terminal assumption
A12: Sustainable terminal payout = 1 - g/ROE | B12: =Sheet1!E383 -> 0.68421053 | G12: Used by the DDM terminal value
A13: Policy payout FY35E (input) | B13: =Sheet1!S108 -> 0.65 | G13: =IF(B13<B12,"Policy payout below sustainable payout: excess capital retained","Policy payout at or above sustainable payout") -> Policy payout below sustainable payout: excess capital retained
A14: CAR FY26E | B14: =Sheet1!J328 -> 0.22000884 | G14: Target floor in Sheet1!E35
A15: CAR FY30E | B15: =Sheet1!N328 -> 0.2565125 | G15: Rising CAR = capital over-retained
A16: CAR FY35E | B16: =Sheet1!S328 -> 0.26696653
A17: Excess capital FY35E over target (Rp bn) | B17: =Sheet1!S329 -> 38820.258 | G17: RIM assumes this earns full ROE; FCFE would distribute it
A18: DDM vs RI gap | B18: =Sheet1!E418 -> 0 | G18: =IF(ABS(B18)>0.25,"Above the 25% model tolerance: master check flags it","Within tolerance") -> Within tolerance
A20: 3. BRIS share price history (annual reports 2021-2025, year-end close) and market-implied Ke
A21: Period end | B21: Close (IDR) | C21: BVPS (IDR) | D21: P/B | E21: P/E (trailing) | F21: Implied Ke*
A22: Dec-2021 | B22: 1780 | C22: 608 | D22: 2.93 | E22: 24.2
A23: Dec-2022 | B23: 1290 | C23: 726 | D23: 1.78 | E23: 14 | F23: 0.106
A24: Dec-2023 | B24: 1740 | C24: 840 | D24: 2.07 | E24: 14.1 | F24: 0.1047
A25: Dec-2024 | B25: 2730 | C25: 976 | D25: 2.8 | E25: 18 | F25: 0.0951
A26: Dec-2025 | B26: 2230 | C26: 1126 | D26: 1.98 | E26: 13.6 | F26: 0.106
A27: 16 Oct 2026 (price; BVPS at 30 Jun 2026) | B27: =Sheet1!E20 -> 1095 | C27: =Sheet1!I464 -> 1106.4695 | D27: =B27/C27 -> 0.98963411 | E27: =B27/Sheet1!F464 -> 6.0773673 | F27: =Sheet1!E31+(Sheet1!J464-Sheet1!E31)/D27 -> 0.16261615
A29: *Implied Ke = g + (ROE - g)/PB. Rows 22-26: annual reports, g = 5.5%, trailing ROE of that year; Dec-2021 P/E uses 41.1bn shares (pre rights issue). Row 27 is live: Sheet1 E31 for g, ROE 1H26 annualised and BVPS at 30 Jun 2026.
A30: Annualised volatility from 19 quarterly closes (Q1-21 to Q4-25): about 32% (understated versus daily data). Only post-merger history (2021 onward) is comparable; BRIsyariah before Feb-2021 is a different entity.
A31: IHSG and peer monthly prices are now in sheets Prices, Returns and Beta (60m beta BRIS 0.69, SE about 0.29). Sharia peers BANK and PNBS not covered.

Sheet Driver_Check
A1: Driver check: template drivers vs evidence from AR2025 and 1H26 interim statements
A2: History and FY26E/FY30E of the template are live from Sheet1 (active scenario). 1H26 run-rate, team-model Base and evidence text are static from the team model v9. Positive gap = template higher than team evidence.
A4: Driver | B4: FY22A | C4: FY23A | D4: FY24A | E4: FY25A | F4: 1H26 run-rate (static) | G4: Pre-merge team model Base FY26E | H4: Template FY26E | I4: Gap FY26E | J4: Pre-merge team model Base FY30E | K4: Template FY30E | L4: Reading | M4: Evidence (AR2025, interim statements) | N4: External factors | O4: Pre-merge team model verdict (against v9 Base)
A5: Total asset growth | B5: =Sheet1!F169/Sheet1!E169-1 -> 0.15242999 | C5: =Sheet1!G169/Sheet1!F169-1 -> 0.15666591 | D5: =Sheet1!H169/Sheet1!G169-1 -> 0.15550132 | E5: =Sheet1!I169/Sheet1!H169-1 -> 0.1164427 | F5: 0.16 | G5: 0.13 | H5: =Sheet1!J169/Sheet1!I169-1 -> 0.1232986 | I5: =H5-G5 -> -0.0067013963 | J5: 0.09 | K5: =Sheet1!N169/Sheet1!M169-1 -> 0.10098853 | L5: =IF(ABS(I5)>0.02,"Review FY26E: template "&IF(I5>0,"higher","lower")&" than team evidence",IF(ABS(K5-J5)>0.04,"Review FY30E: template "&IF(K5>J5,"higher","lower")&" than team evidence","Within tolerance")) -> Within tolerance | M5: Assets grew 15.2%, 15.7%, 15.6% and 11.6% in FY22-25. Jun-26 assets of Rp464.5tn are +16% YoY (1H26 results). Gross financing +16.2% YoY and deposits +17.7% YoY at Aug-26. AR2025 (p.236) guides financing growth of 10-14% for 2026, so Aug-26 is above the top of range. Assets are seasonal: Dec-24 408.6tn, Jun-25 about 400tn (derived from the 16% YoY), Dec-25 456.2tn. FY26E of 515.5tn needs +11% in 2H26 versus +14% in 2H25. Fade to 9% reflects scale and CAR of 20.4% (Jun-26); the planned rights issue (Q1 2027) supports growth capacity. | N5: Bank Indonesia projects bank credit growth of 8-12% in 2026 (AR2025 p.182). BSI projects industry sharia assets of Rp1,205tn in 2026 (+12.9% on Rp1,067.7tn). OJK: sharia financing +11.61% YoY at Aug-26. BSI holds about 43% of industry assets and gains share (42.7% in 2025). Headwinds: BI-Rate held at 5.75% in Sep-26 (tight liquidity, rupiah pressure) and spin-offs of sharia units create new competitors. Bear 9% equals 2025 industry growth of 8.9% (share gains stop). Bull 16% equals the Jun-26 YoY pace. | O5: Supported. Keep Base 13% fading to 9%.
A6: HBH / average assets | B6: =Sheet1!F143/AVERAGE(Sheet1!F169,Sheet1!E169) -> 0.054606862 | C6: =Sheet1!G143/AVERAGE(Sheet1!G169,Sheet1!F169) -> 0.049316904 | D6: =Sheet1!H143/AVERAGE(Sheet1!H169,Sheet1!G169) -> 0.045679163 | E6: =Sheet1!I143/AVERAGE(Sheet1!I169,Sheet1!H169) -> 0.044239022 | F6: 0.042178674 | G6: 0.042 | H6: =Sheet1!J143/AVERAGE(Sheet1!J169,Sheet1!I169) -> 0.043622104 | I6: =H6-G6 -> 0.0016221045 | J6: 0.041 | K6: =Sheet1!N143/AVERAGE(Sheet1!N169,Sheet1!M169) -> 0.046963169 | L6: =IF(ABS(I6)>0.0015,"Review FY26E: template "&IF(I6>0,"higher","lower")&" than team evidence",IF(ABS(K6-J6)>0.003,"Review FY30E: template "&IF(K6>J6,"higher","lower")&" than team evidence","Within tolerance")) -> Review FY26E: template higher than team evidence | M6: Ratio fell from 5.46% (FY22) to 4.42% (FY25), about 25-50bp a year. In 1H26 HBH grew only 2.0% YoY (Rp9.71tn vs Rp9.52tn) while assets grew about 16%. Income from sales and purchases fell 7.7%; third-party share fell 6.6%; profit-sharing income rose 17.5%. Reported NIM was about 5.4% in 1H26 (-31bp YoY) against AR2025 guidance of above 5.50% (p.236). Financing yield fell about 77bp and cost of funds fell about 49bp (2.19%-2.30%). Mix shifts to gold-backed financing and securities (Rp61tn, mostly related party), which carry lower yields. Original Base of 4.30% implied HBH +9% for FY26E, needing +16% YoY in 2H26. | N6: BI-Rate was held at 5.75% in Sep-26, while the AR2025 macro assumption was 4.25%. Rate relief that would lift margins is not in sight. Deposit competition from state banks and digital banks keeps funding costs sticky. Murabahah is mostly fixed-rate, so repricing lags. Bear -0.2pp reflects continued yield compression; Bull +0.1pp reflects cost-of-fund gains. | O6: Not supported at 4.30%. Revised Base to 4.20%, fading to 4.10%.
A7: Other operating income / average assets | B7: =Sheet1!F144/AVERAGE(Sheet1!F169,Sheet1!E169) -> 0.012963248 | C7: =Sheet1!G144/AVERAGE(Sheet1!G169,Sheet1!F169) -> 0.012753347 | D7: =Sheet1!H144/AVERAGE(Sheet1!H169,Sheet1!G169) -> 0.0145794 | E7: =Sheet1!I144/AVERAGE(Sheet1!I169,Sheet1!H169) -> 0.01604197 | F7: 0.017694858 | G7: 0.0172 | H7: =Sheet1!J144/AVERAGE(Sheet1!J169,Sheet1!I169) -> 0.017903037 | I7: =H7-G7 -> 0.00070303739 | J7: 0.0162 | K7: =Sheet1!N144/AVERAGE(Sheet1!N169,Sheet1!M169) -> 0.018069785 | L7: =IF(ABS(I7)>0.001,"Review FY26E: template "&IF(I7>0,"higher","lower")&" than team evidence",IF(ABS(K7-J7)>0.002,"Review FY30E: template "&IF(K7>J7,"higher","lower")&" than team evidence","Within tolerance")) -> Within tolerance | M7: Ratio rose from 1.30% (FY22) to 1.60% (FY25) and 1.77% annualised in 1H26. 1H26: fee income +55% (Rp2.98tn vs Rp1.92tn), securities gains +42%, recoveries -24%. Fee-based income reached Rp5.6tn at Aug-26 (+36.3% YoY, 23.1% of revenue). Gold business +81% YoY with 1.22m gold customers. Quality flags from FY25: Rahn (gold pawn) is 33% of fee income, securities gains are 8.1% of PPOP, recoveries cover 55% of impairment. Base sits below the 1H26 run-rate because securities gains and recoveries do not repeat at this pace. | N7: Gold price and bullion regulation drive Rahn and gold instalment fees. Digital adoption (24.3m customers, BYOND) and hajj-related flows (7.69m hajj customers) support fee growth. Interest-rate moves drive securities gains: valuation losses already hit OCI in 1H26 (-Rp0.78tn). Bear -0.1pp, Bull +0.1pp. | O7: Base 1.62% was below run-rate. Revised Base to 1.72%, fading to 1.62%. Net revenue / assets is unchanged at 5.92%.
A8: Cost-to-income | B8: =Sheet1!F149/Sheet1!F145 -> 0.51292945 | C8: =Sheet1!G149/Sheet1!G145 -> 0.50086417 | D8: =Sheet1!H149/Sheet1!H145 -> 0.51353393 | E8: =Sheet1!I149/Sheet1!I145 -> 0.52562269 | F8: 0.52624585 | G8: 0.545 | H8: =Sheet1!J149/Sheet1!J145 -> 0.545 | I8: =H8-G8 -> 0 | J8: 0.52 | K8: =Sheet1!N149/Sheet1!N145 -> 0.505 | L8: =IF(ABS(I8)>0.01,"Review FY26E: template "&IF(I8>0,"higher","lower")&" than team evidence",IF(ABS(K8-J8)>0.02,"Review FY30E: template "&IF(K8>J8,"higher","lower")&" than team evidence","Within tolerance")) -> Within tolerance | M8: CIR was 51.3%, 50.1%, 51.4%, 52.6% in FY22-25. 1H26 opex grew 17.5% (G&A +19.1%, salaries +14.9%) against net revenue +10.5%; CIR 52.6% vs 49.5% in 1H25. Seasonality: 2H25 CIR was 55.4%, so FY26 at the same pattern would be near 55%. AR2025 reports 52.13% on the OJK basis (different definition; note it). Original Base of 53.5% needed opex growth to drop to +8% YoY in 2H26. Technology and digital investment (BYOND migration, cyber security after the 2023 ransomware incident) keep costs high near term; operating leverage arrives only as revenue per asset stabilises. | N8: Wage and general inflation (AR2025 assumes 2.34% CPI) is below BSI cost growth, so the gap is investment-driven, not inflation. Regulatory and cyber compliance costs are rising industry-wide. Bear +1.5pp, Bull -1.0pp. | O8: Not supported at 53.5%. Revised Base to 54.5%, improving 0.75pp a year to 52.0%.
A9: Impairment / average gross financing | B9: =Sheet1!F151/AVERAGE(Sheet1!F212,Sheet1!E212) -> 0.019782831 | C9: =Sheet1!G151/AVERAGE(Sheet1!G212,Sheet1!F212) -> 0.011706973 | D9: =Sheet1!H151/AVERAGE(Sheet1!H212,Sheet1!G212) -> 0.0073009944 | E9: =Sheet1!I151/AVERAGE(Sheet1!I212,Sheet1!H212) -> 0.0078916871 | F9: 0.006443979 | G9: 0.007 | H9: =Sheet1!J151/AVERAGE(Sheet1!J212,Sheet1!I212) -> 0.007 | I9: =H9-G9 -> 0 | J9: 0.008 | K9: =Sheet1!N151/AVERAGE(Sheet1!N212,Sheet1!M212) -> 0.0075 | L9: =IF(ABS(I9)>0.001,"Review FY26E: template "&IF(I9>0,"higher","lower")&" than team evidence",IF(ABS(K9-J9)>0.002,"Review FY30E: template "&IF(K9>J9,"higher","lower")&" than team evidence","Within tolerance")) -> Within tolerance | M9: Ratio fell from 1.98% (FY22) to 0.73-0.79% (FY24-25). 1H26 annualised 0.64% (cost of credit about 0.6%). AR2025 guidance is cost of credit below 0.84% (p.236). Early adoption of PSAK 413 (expected credit loss) raised allowance coverage from 3.5% to 4.5% of gross financing and cut equity by Rp3.0tn, so reserves are front-loaded. NPF gross about 1.8% (stable), loan-at-risk 8.0% (from 8.5%), LAR coverage 55%. Offsets: recoveries covered 55% of FY25 impairment and fell 24% in 1H26, so net cost rises as they fade. Related-party musyarakah financing grew 45% YTD (Rp26.1tn to Rp37.9tn), a concentration to watch. | N9: Debtor stress from the 5.75% BI-Rate and weak rupiah. Consumer book (Rp189tn, mostly payroll-based ASN) is stable. State-linked wholesale borrowers carry policy risk. Bear 1.0% = 2020s stress-like normalisation; Bull 0.6% = current run-rate. | O9: Supported. Keep Base 0.70% rising to 0.80%.
A10: Dividend payout (on prior-year net income) | B10: =IFERROR(Sheet1!F339/Sheet1!E154,"") -> 0.25 | C10: =IFERROR(Sheet1!G339/Sheet1!F154,"") -> 0.1 | D10: =IFERROR(Sheet1!H339/Sheet1!G154,"") -> 0.15 | E10: =IFERROR(Sheet1!I339/Sheet1!H154,"") -> 0.15 | F10: 0.2 | G10: 0.2 | H10: =IFERROR(Sheet1!J339/Sheet1!I154,"") -> 0.2 | I10: =H10-G10 -> 0 | J10: 0.3 | K10: =IFERROR(Sheet1!N339/Sheet1!M154,"") -> 0.3 | L10: =IF(ABS(I10)>0.03,"Review FY26E: template "&IF(I10>0,"higher","lower")&" than team evidence",IF(ABS(K10-J10)>0.06,"Review FY30E: template "&IF(K10>J10,"higher","lower")&" than team evidence","Within tolerance")) -> Within tolerance | M10: Payout was 25%, 10%, 15%, 15% in FY22-25 and 20% in 2026 (Rp32.81 per share, paid Jun-26). CAR is 20.41% (Jun-26) against a 12.5% floor with buffer and an 18% internal target. Base rises 2.5pp a year to 30%. A rights issue of up to 6.8bn shares is planned (RUPSLB 15 Oct 2026, execution Q1 2027), which argues against faster payout increases. | N10: State shareholders (Danantara-linked banks) favour higher payout; large state banks pay far more than BSI. The same path is used in all scenarios, so payout does not drive the Bear/Bull spread. | O10: Judgement, low value impact (DDM weight 15%). Keep.
A11: ROE on average equity / terminal ROE | B11: =Sheet1!F347 -> 0.14559142 | C11: =Sheet1!G347 -> 0.15789974 | D11: =Sheet1!H347 -> 0.1672435 | E11: =Sheet1!I347 -> 0.15604034 | F11: 0.16625882 | G11: 0.15059693 | H11: =Sheet1!J347 -> 0.15199023 | I11: =H11-G11 -> 0.001393294 | J11: 0.14 | K11: =Sheet1!N347 -> 0.15271595 | L11: =IF(ABS(I11)>0.01,"Review FY26E: template "&IF(I11>0,"higher","lower")&" than team evidence",IF(ABS(K11-J11)>0.02,"Review FY30E: template "&IF(K11>J11,"higher","lower")&" than team evidence","Within tolerance")) -> Within tolerance | M11: ROE was 14.6%, 15.8%, 16.7%, 15.6% in FY22-25 (net income / average equity; AR2025 reports 16.85% on the OJK basis). 1H26 annualised is higher because equity was reset down by PSAK 413. Terminal ROE of 14% sits just above Ke (13.85%), meaning excess return fades to almost zero. Bear 12% is below Ke (value destruction); Bull 16% matches the FY23-25 range. Sensitivity from the v3 grid (beta 1.00): each 1pp of terminal ROE is worth about Rp135 per share (12%: 1,044; 14%: 1,314; 16%: 1,587). | N11: Competitive convergence is the argument: HBH / assets has fallen every year since FY22, fee growth cannot be extrapolated, and a Q1-2027 rights issue dilutes ROE until deployed. Counter-argument: BSI leads its niche with about 43% share and growing CASA, so a higher terminal ROE is arguable. This is the second most sensitive input after beta. | O11: Judgement, conservative. Keep 14% as Base and show the 12-16% range.
A13: Tolerances (FY30E allowed twice the FY26E band): asset growth 2pp, HBH and other income per assets 0.15pp and 0.10pp, CIR 1pp, impairment 0.10pp, payout 3pp, ROE 1pp. Payout in the template is measured as dividends paid over prior-year net profit; FY22A-FY25A columns use the same definition. The two largest items to settle are CIR (52.5% template vs 54.5% team evidence) and total financing growth (14.4% vs 13%).

Sheet CF_Direct
B1: 2c-bis. Cash flow statement - DIRECT method, BSI reporting format (Rp bn)
B2: FY21A-FY25A: as reported in the audited annual-report cash flow statement (latest restated comparatives; FY21 from AR22, FY24 from AR25). FY26E-FY35E: derived from Sheet1 drivers; ties to the indirect statement (Sheet1 rows 183-202) via the reconciliation block. Blue = hardcoded from filings, black = formula, green = link to Sheet1.
B4: A. CASH FLOW FROM OPERATIONS (BSI classification) | E4: FY21A | F4: FY22A | G4: FY23A | H4: FY24A | I4: FY25A | J4: FY26E | K4: FY27E | L4: FY28E | M4: FY29E | N4: FY30E | O4: FY31E | P4: FY32E | Q4: FY33E | R4: FY34E | S4: FY35E
B5: Receipts of margin, profit-sharing, ijarah & other main income | C5: Rp bn | D5: Hist: reported. Fcst: gross margin income (Sheet1 row 141), accrual = cash proxy | E5: 17729.782 | F5: 19343.529 | G5: 22356.599 | H5: 25260.645 | I5: 26738.36 | J5: =Sheet1!J141 -> 29781.905 | K5: =Sheet1!K141 -> 33832.448 | L5: =Sheet1!L141 -> 37885.334 | M5: =Sheet1!M141 -> 41841.252 | N5: =Sheet1!N141 -> 46062.669 | O5: =Sheet1!O141 -> 50371.515 | P5: =Sheet1!P141 -> 54759.067 | Q5: =Sheet1!Q141 -> 59174.157 | ... S5: =Sheet1!S141 -> 67856.489
B6: Payment of profit-sharing to temporary syirkah funds | C6: Rp bn | D6: Fcst: Sheet1 row 142 | E6: -4390.339 | F6: -3997.872 | G6: -5930.162 | H6: -7854.159 | I6: -9169.468 | J6: =-Sheet1!J142 -> -8654.9786 | K6: =-Sheet1!K142 -> -9059.8208 | L6: =-Sheet1!L142 -> -9318.8925 | M6: =-Sheet1!M142 -> -9900.3845 | N6: =-Sheet1!N142 -> -10942.06 | O6: =-Sheet1!O142 -> -11935.533 | P6: =-Sheet1!P142 -> -12878.93 | Q6: =-Sheet1!Q142 -> -13828.248 | ... S6: =-Sheet1!S142 -> -15695.095
B7: Recoveries of written-off financing & receivables | C7: Rp bn | D7: Hist: reported. Fcst: inside provisions net (not modelled separately) | E7: 998.496 | F7: 1377.882 | G7: 1703.364 | H7: 2097.759 | I7: 2163.537 | J7: 0 | K7: 0 | L7: 0 | M7: 0 | N7: 0 | O7: 0 | P7: 0 | Q7: 0 | R7: 0 | S7: 0
B8: Other operating income received (fees etc.) | C8: Rp bn | D8: Fcst: fee-based income, Sheet1 row 144 | E8: 2249.71 | F8: 2723.083 | G8: 3115.816 | H8: 4266.371 | I8: 5333.634 | J8: =Sheet1!J144 -> 8670.745 | K8: =Sheet1!K144 -> 9971.3567 | L8: =Sheet1!L144 -> 11167.92 | M8: =Sheet1!M144 -> 12284.712 | N8: =Sheet1!N144 -> 13513.183 | O8: =Sheet1!O144 -> 14783.422 | P8: =Sheet1!P144 -> 16084.363 | Q8: =Sheet1!Q144 -> 17403.281 | ... S8: =Sheet1!S144 -> 20036.745
B9: Tantiem paid | C9: Rp bn | D9: Fcst: inside cash opex | E9: -51.66 | F9: -75.784 | G9: -91.574 | H9: -110.228 | I9: -142.299 | J9: 0 | K9: 0 | L9: 0 | M9: 0 | N9: 0 | O9: 0 | P9: 0 | Q9: 0 | R9: 0 | S9: 0
B10: Operating expenses paid (cash) | C10: Rp bn | D10: Fcst: overhead less D&A (Sheet1 row 149 less row 265) | E10: -10191.04 | F10: -11781.973 | G10: -12698.368 | H10: -14283.894 | I10: -12984.707 | J10: =-(Sheet1!J149-Sheet1!J265) -> -13718.99 | K10: =-(Sheet1!K149-Sheet1!K265) -> -15531.353 | L10: =-(Sheet1!L149-Sheet1!L265) -> -17836.139 | M10: =-(Sheet1!M149-Sheet1!M265) -> -19779.965 | N10: =-(Sheet1!N149-Sheet1!N265) -> -21597.307 | O10: =-(Sheet1!O149-Sheet1!O265) -> -23693.286 | P10: =-(Sheet1!P149-Sheet1!P265) -> -25841.667 | Q10: =-(Sheet1!Q149-Sheet1!Q265) -> -27986.127 | ... S10: =-(Sheet1!S149-Sheet1!S265) -> -32161.553
B11: Non-operating income / (expense), net | C11: Rp bn | D11: Fcst: inside tax & other line | E11: 65.766 | F11: 24.903 | G11: 25.571 | H11: 112.287 | I11: 58.064 | J11: 0 | K11: 0 | L11: 0 | M11: 0 | N11: 0 | O11: 0 | P11: 0 | Q11: 0 | R11: 0 | S11: 0
B12: Corporate income tax paid | C12: Rp bn | D12: Fcst: tax & other (Sheet1 row 153) | E12: -1344.08 | F12: -1446.72 | G12: -1855.197 | H12: -1985.972 | I12: -2571.361 | J12: =-Sheet1!J153 -> -2744.2647 | K12: =-Sheet1!K153 -> -3383.1334 | L12: =-Sheet1!L153 -> -3933.386 | M12: =-Sheet1!M153 -> -4434.047 | N12: =-Sheet1!N153 -> -4933.4402 | O12: =-Sheet1!O153 -> -5398.177 | P12: =-Sheet1!P153 -> -5880.6152 | Q12: =-Sheet1!Q153 -> -6367.2752 | ... S12: =-Sheet1!S153 -> -7329.1398
B13: Zakat paid | C13: Rp bn | D13: Fcst: inside tax & other line | E13: -127.611 | F13: -170.771 | G13: -205.881 | H13: -268.348 | I13: -316.136 | J13: 0 | K13: 0 | L13: 0 | M13: 0 | N13: 0 | O13: 0 | P13: 0 | Q13: 0 | R13: 0 | S13: 0
B14: Qardhul hasan funds distributed | C14: Rp bn | D14: Fcst: inside cash opex | E14: -59.529 | F14: -108.831 | G14: -80.736 | H14: -117.028 | I14: -130.947 | J14: 0 | K14: 0 | L14: 0 | M14: 0 | N14: 0 | O14: 0 | P14: 0 | Q14: 0 | R14: 0 | S14: 0
B15: Cash flow before changes in operating assets & liabilities | C15: Rp bn | D15: Check vs reported subtotal in row below (hist) | E15: =SUM(E5:E14) -> 4879.495 | F15: =SUM(F5:F14) -> 5887.446 | G15: =SUM(G5:G14) -> 6339.432 | H15: =SUM(H5:H14) -> 7117.433 | I15: =SUM(I5:I14) -> 8978.677 | J15: =SUM(J5:J14) -> 13334.416 | K15: =SUM(K5:K14) -> 15829.498 | L15: =SUM(L5:L14) -> 17964.837 | ... S15: =SUM(S5:S14) -> 32707.446
B16: Reported subtotal (memo) | C16: Rp bn | D16: From annual report | E16: 4879.495 | F16: 5887.446 | G16: 6339.432 | H16: 7117.433 | I16: 8978.677
B17: Change in financing, receivables & qardh (net of write-offs) | C17: Rp bn | D17: Hist: piutang + qardh + pembiayaan. Fcst: Sheet1 row 190 | E17: -15205.329 | F17: -35830.69 | G17: -31905.654 | H17: -37233.05 | I17: -42243.814 | J17: =Sheet1!J190 -> -46440.808 | K17: =Sheet1!K190 -> -48449.859 | L17: =Sheet1!L190 -> -49569.127 | M17: =Sheet1!M190 -> -51037.885 | N17: =Sheet1!N190 -> -52225.042 | O17: =Sheet1!O190 -> -53768.851 | P17: =Sheet1!P190 -> -54772.977 | Q17: =Sheet1!Q190 -> -55166.999 | ... S17: =Sheet1!S190 -> -53895.018
B18: Change in customer deposits & temporary syirkah funds | C18: Rp bn | D18: Hist: simpanan nasabah/wadiah + syirkah temporer. Fcst: Sheet1 row 194 | E18: 23434.96 | F18: 28163.358 | G18: 32131.213 | H18: 35314.814 | I18: 52388.062 | J18: =Sheet1!J194 -> 48564.694 | K18: =Sheet1!K194 -> 49890.789 | L18: =Sheet1!L194 -> 49134.1 | M18: =Sheet1!M194 -> 56421.687 | N18: =Sheet1!N194 -> 57392.638 | O18: =Sheet1!O194 -> 58778.898 | P18: =Sheet1!P194 -> 59514.626 | Q18: =Sheet1!Q194 -> 59521.371 | ... S18: =Sheet1!S194 -> 57098.645
B19: Other operating assets & liabilities, net | C19: Rp bn | D19: Hist: sum of reported lines (securities at FV, acceptance, ijarah, other assets/liabs, interbank). Fcst: Sheet1 rows 187+188 | E19: 3587.668 | F19: 3665.416 | G19: -4523.956 | H19: 1623.655 | I19: -4957.365 | J19: =Sheet1!J187+Sheet1!J188 -> -218.61223 | K19: =Sheet1!K187+Sheet1!K188 -> -289.74483 | L19: =Sheet1!L187+Sheet1!L188 -> -292.32603 | M19: =Sheet1!M187+Sheet1!M188 -> -263.08632 | N19: =Sheet1!N187+Sheet1!N188 -> -258.22403 | O19: =Sheet1!O187+Sheet1!O188 -> -268.61569 | P19: =Sheet1!P187+Sheet1!P188 -> -277.95796 | Q19: =Sheet1!Q187+Sheet1!Q188 -> -280.27729 | ... S19: =Sheet1!S187+Sheet1!S188 -> -274.3374
B20: NET CASH FROM OPERATING ACTIVITIES | C20: Rp bn | E20: =E15+E17+E18+E19 -> 16696.794 | F20: =F15+F17+F18+F19 -> 1885.53 | G20: =G15+G17+G18+G19 -> 2041.035 | H20: =H15+H17+H18+H19 -> 6822.852 | I20: =I15+I17+I18+I19 -> 14165.56 | J20: =J15+J17+J18+J19 -> 15239.691 | K20: =K15+K17+K18+K19 -> 16980.683 | L20: =L15+L17+L18+L19 -> 17237.484 | ... S20: =S15+S17+S18+S19 -> 35636.736
B21: Reported CFO (memo) | C21: Rp bn | D21: From annual report | E21: 16696.794 | F21: 1885.53 | G21: 2041.035 | H21: 6822.852 | I21: 14165.56
B23: B. CASH FLOW FROM INVESTING | E23: FY21A | F23: FY22A | G23: FY23A | H23: FY24A | I23: FY25A | J23: FY26E | K23: FY27E | L23: FY28E | M23: FY29E | N23: FY30E | O23: FY31E | P23: FY32E | Q23: FY33E | R23: FY34E | S23: FY35E
B24: Net purchase / sale of securities (investing portion) | C24: Rp bn | D24: Hist: sale less acquisition. Fcst: Sheet1 row 191 | E24: -15803.52 | F24: 8036.505 | G24: -9592.005 | H24: 10424.931 | I24: 9370.466 | J24: =Sheet1!J191 -> -7705.4589 | K24: =Sheet1!K191 -> -7915.8622 | L24: =Sheet1!L191 -> -7795.803 | M24: =Sheet1!M191 -> -8952.0793 | N24: =Sheet1!N191 -> -9106.134 | O24: =Sheet1!O191 -> -9326.0833 | P24: =Sheet1!P191 -> -9442.8167 | Q24: =Sheet1!Q191 -> -9443.8869 | ... S24: =Sheet1!S191 -> -9059.488
B25: Capex incl. ROU and intangibles (net of disposals) | C25: Rp bn | D25: Fcst: Sheet1 row 192 | E25: -787.504 | F25: -2041.797 | G25: -1812.354 | H25: -4079.448 | I25: -2956.639 | J25: =Sheet1!J192 -> -2383.8137 | K25: =Sheet1!K192 -> -2779.5187 | L25: =Sheet1!L192 -> -3178.7489 | M25: =Sheet1!M192 -> -3538.0463 | N25: =Sheet1!N192 -> -3890.7034 | O25: =Sheet1!O192 -> -4257.5523 | P25: =Sheet1!P192 -> -4637.16 | Q25: =Sheet1!Q192 -> -5019.9352 | ... S25: =Sheet1!S192 -> -5775.8511
B26: NET CASH FROM INVESTING ACTIVITIES | C26: Rp bn | E26: =E24+E25 -> -16591.024 | F26: =F24+F25 -> 5994.708 | G26: =G24+G25 -> -11404.359 | H26: =H24+H25 -> 6345.483 | I26: =I24+I25 -> 6413.827 | J26: =J24+J25 -> -10089.273 | K26: =K24+K25 -> -10695.381 | L26: =L24+L25 -> -10974.552 | ... S26: =S24+S25 -> -14835.339
B27: Reported CFI (memo) | C27: Rp bn | D27: From annual report | E27: -16591.024 | F27: 5994.708 | G27: -11404.359 | H27: 6345.483 | I27: 6413.827
B29: C. CASH FLOW FROM FINANCING | E29: FY21A | F29: FY22A | G29: FY23A | H29: FY24A | I29: FY25A | J29: FY26E | K29: FY27E | L29: FY28E | M29: FY29E | N29: FY30E | O29: FY31E | P29: FY32E | Q29: FY33E | R29: FY34E | S29: FY35E
B30: Lease liabilities paid / change in lease liabilities | C30: Rp bn | D30: Fcst: Sheet1 row 196 | E30: -130.215 | F30: -124.192 | G30: -134.742 | H30: -151.913 | I30: -474.177 | J30: =Sheet1!J196 -> -287.84192 | K30: =Sheet1!K196 -> -141.23991 | L30: =Sheet1!L196 -> -23.165134 | M30: =Sheet1!M196 -> 62.30982 | N30: =Sheet1!N196 -> 129.19568 | O30: =Sheet1!O196 -> 185.89756 | P30: =Sheet1!P196 -> 234.12977 | Q30: =Sheet1!Q196 -> 273.42824 | ... S30: =Sheet1!S196 -> 327.91879
B31: Dividends paid | C31: Rp bn | D31: Fcst: Sheet1 row 197 | E31: 0 | F31: -757.051 | G31: -426.018 | H31: -855.561 | I31: -1050.883 | J31: =Sheet1!J197 -> -1513.5046 | K31: =Sheet1!K197 -> -1852.6831 | L31: =Sheet1!L197 -> -2595.4436 | M31: =Sheet1!M197 -> -3258.9882 | N31: =Sheet1!N197 -> -4082.0095 | O31: =Sheet1!O197 -> -4541.7537 | P31: =Sheet1!P197 -> -6626.1242 | Q31: =Sheet1!Q197 -> -9022.881 | ... S31: =Sheet1!S197 -> -12616.437
B32: Equity issued (net of issuance cost) / rights issue | C32: Rp bn | D32: Fcst: Sheet1 row 199 | E32: 52.286 | F32: 4937.652 | G32: 0 | H32: 0 | I32: 0 | J32: =Sheet1!J199 -> 0 | K32: =Sheet1!K199 -> 6392 | L32: =Sheet1!L199 -> 0 | M32: =Sheet1!M199 -> 0 | N32: =Sheet1!N199 -> 0 | O32: =Sheet1!O199 -> 0 | P32: =Sheet1!P199 -> 0 | Q32: =Sheet1!Q199 -> 0 | ... S32: =Sheet1!S199 -> 0
B33: Sukuk, mudharabah term financing, borrowings & BI funding, net | C33: Rp bn | D33: Hist: all debt-type lines incl. BI liabilities (gross flows netted). Fcst: Sheet1 row 195 | E33: 0 | F33: 742.5 | G33: 10723.757 | H33: 9745.889 | I33: -16119.911 | J33: =Sheet1!J195 -> -48.6 | K33: =Sheet1!K195 -> 1745 | L33: =Sheet1!L195 -> 1314 | M33: =Sheet1!M195 -> 2000 | N33: =Sheet1!N195 -> 2000 | O33: =Sheet1!O195 -> 0 | P33: =Sheet1!P195 -> 0 | Q33: =Sheet1!Q195 -> 0 | ... S33: =Sheet1!S195 -> 0
B34: OCI treated as cash-equivalent movement (model convention) | C34: Rp bn | D34: Fcst only: Sheet1 row 198 | E34: 0 | F34: 0 | G34: 0 | H34: 0 | I34: 0 | J34: =Sheet1!J198 -> 0 | K34: =Sheet1!K198 -> 0 | L34: =Sheet1!L198 -> 0 | M34: =Sheet1!M198 -> 0 | N34: =Sheet1!N198 -> 0 | O34: =Sheet1!O198 -> 0 | P34: =Sheet1!P198 -> 0 | Q34: =Sheet1!Q198 -> 0 | ... S34: =Sheet1!S198 -> 0
B35: NET CASH FROM FINANCING ACTIVITIES | C35: Rp bn | E35: =SUM(E30:E34) -> -77.929 | F35: =SUM(F30:F34) -> 4798.909 | G35: =SUM(G30:G34) -> 10162.997 | H35: =SUM(H30:H34) -> 8738.415 | I35: =SUM(I30:I34) -> -17644.971 | J35: =SUM(J30:J34) -> -1849.9465 | K35: =SUM(K30:K34) -> 6143.077 | L35: =SUM(L30:L34) -> -1304.6087 | ... S35: =SUM(S30:S34) -> -12288.518
B36: Reported CFF (memo) | C36: Rp bn | D36: From annual report (FY24 as reclassified in AR25) | E36: -77.929 | F36: 4798.909 | G36: 10162.997 | H36: 8738.415 | I36: -17644.971
B38: D. NET CHANGE IN CASH | E38: FY21A | F38: FY22A | G38: FY23A | H38: FY24A | I38: FY25A | J38: FY26E | K38: FY27E | L38: FY28E | M38: FY29E | N38: FY30E | O38: FY31E | P38: FY32E | Q38: FY33E | R38: FY34E | S38: FY35E
B39: Net change in cash & cash equivalents | C39: Rp bn | E39: =E20+E26+E35 -> 27.841 | F39: =F20+F26+F35 -> 12679.147 | G39: =G20+G26+G35 -> 799.673 | H39: =H20+H26+H35 -> 21906.75 | I39: =I20+I26+I35 -> 2934.416 | J39: =J20+J26+J35 -> 3300.4716 | K39: =K20+K26+K35 -> 12428.379 | L39: =L20+L26+L35 -> 4958.3231 | ... S39: =S20+S26+S35 -> 8512.8789
B40: Opening cash & cash equivalents | C40: Rp bn | E40: 26514.431 | F40: 26542.272 | G40: 39221.419 | H40: 40021.092 | I40: 61927.842 | J40: =Sheet1!I163 -> 64845 | K40: =J41 -> 68145.472 | L40: =K41 -> 80573.85 | M40: =L41 -> 85532.173 | N40: =M41 -> 96977.652 | O40: =N41 -> 109040.42 | P40: =O41 -> 119970.3 | Q40: =P41 -> 130204.24 | R40: =Q41 -> 139460.84 | S40: =R41 -> 148423.06
B41: Closing cash & cash equivalents | C41: Rp bn | E41: =E40+E39 -> 26542.272 | F41: =F40+F39 -> 39221.419 | G41: =G40+G39 -> 40021.092 | H41: =H40+H39 -> 61927.842 | I41: =I40+I39 -> 64862.258 | J41: =J40+J39 -> 68145.472 | K41: =K40+K39 -> 80573.85 | L41: =L40+L39 -> 85532.173 | ... S41: =S40+S39 -> 156935.94
B42: Reported closing cash (memo) | C42: Rp bn | D42: From annual report. BS cash (Sheet1 row 163) FY25A 64,845 vs CFS 64,862: Rp17bn classification gap (cash equivalents definition) | E42: 26542.272 | F42: 39221.419 | G42: 40021.092 | H42: 61927.842 | I42: 64862.258
B44: E. RECONCILIATION & CHECKS (all must be 0) | E44: FY21A | F44: FY22A | G44: FY23A | H44: FY24A | I44: FY25A | J44: FY26E | K44: FY27E | L44: FY28E | M44: FY29E | N44: FY30E | O44: FY31E | P44: FY32E | Q44: FY33E | R44: FY34E | S44: FY35E
B45: Hist: direct pre-change subtotal vs reported | C45: Rp bn | E45: =ROUND(E15-E16,1) -> 0 | F45: =ROUND(F15-F16,1) -> 0 | G45: =ROUND(G15-G16,1) -> 0 | H45: =ROUND(H15-H16,1) -> 0 | I45: =ROUND(I15-I16,1) -> 0
B46: Hist: CFO vs reported | C46: Rp bn | E46: =ROUND(E20-E21,1) -> 0 | F46: =ROUND(F20-F21,1) -> 0 | G46: =ROUND(G20-G21,1) -> 0 | H46: =ROUND(H20-H21,1) -> 0 | I46: =ROUND(I20-I21,1) -> 0
B47: Hist: CFI vs reported | C47: Rp bn | E47: =ROUND(E26-E27,1) -> 0 | F47: =ROUND(F26-F27,1) -> 0 | G47: =ROUND(G26-G27,1) -> 0 | H47: =ROUND(H26-H27,1) -> 0 | I47: =ROUND(I26-I27,1) -> 0
B48: Hist: CFF vs reported | C48: Rp bn | E48: =ROUND(E35-E36,1) -> 0 | F48: =ROUND(F35-F36,1) -> 0 | G48: =ROUND(G35-G36,1) -> 0 | H48: =ROUND(H35-H36,1) -> 0 | I48: =ROUND(I35-I36,1) -> 0
B49: Hist: closing cash vs reported | C49: Rp bn | E49: =ROUND(E41-E42,1) -> 0 | F49: =ROUND(F41-F42,1) -> 0 | G49: =ROUND(G41-G42,1) -> 0 | H49: =ROUND(H41-H42,1) -> 0 | I49: =ROUND(I41-I42,1) -> 0
B50: Fcst: direct net change vs indirect (Sheet1 row 201) | C50: Rp bn | J50: =ROUND(J39-Sheet1!J201,3) -> 0 | K50: =ROUND(K39-Sheet1!K201,3) -> 0 | L50: =ROUND(L39-Sheet1!L201,3) -> 0 | M50: =ROUND(M39-Sheet1!M201,3) -> 0 | N50: =ROUND(N39-Sheet1!N201,3) -> 0 | O50: =ROUND(O39-Sheet1!O201,3) -> 0 | P50: =ROUND(P39-Sheet1!P201,3) -> 0 | Q50: =ROUND(Q39-Sheet1!Q201,3) -> 0 | ... S50: =ROUND(S39-Sheet1!S201,3) -> 0
B51: Fcst: direct closing cash vs balance sheet cash (Sheet1 row 163) | C51: Rp bn | J51: =ROUND(J41-Sheet1!J163,3) -> 0 | K51: =ROUND(K41-Sheet1!K163,3) -> 0 | L51: =ROUND(L41-Sheet1!L163,3) -> 0 | M51: =ROUND(M41-Sheet1!M163,3) -> 0 | N51: =ROUND(N41-Sheet1!N163,3) -> 0 | O51: =ROUND(O41-Sheet1!O163,3) -> 0 | P51: =ROUND(P41-Sheet1!P163,3) -> 0 | Q51: =ROUND(Q41-Sheet1!Q163,3) -> 0 | ... S51: =ROUND(S41-Sheet1!S163,3) -> 0
B52: Fcst: opening cash vs prior-year BS cash | C52: Rp bn | J52: =ROUND(J40-Sheet1!I163,3) -> 0 | K52: =ROUND(K40-Sheet1!J163,3) -> 0 | L52: =ROUND(L40-Sheet1!K163,3) -> 0 | M52: =ROUND(M40-Sheet1!L163,3) -> 0 | N52: =ROUND(N40-Sheet1!M163,3) -> 0 | O52: =ROUND(O40-Sheet1!N163,3) -> 0 | P52: =ROUND(P40-Sheet1!O163,3) -> 0 | Q52: =ROUND(Q40-Sheet1!P163,3) -> 0 | ... S52: =ROUND(S40-Sheet1!R163,3) -> 0
B53: TOTAL OF CHECKS (0 = OK) | C53: Rp bn | E53: =ABS(E45)+ABS(E46)+ABS(E47)+ABS(E48)+ABS(E49) -> 0 | F53: =ABS(F45)+ABS(F46)+ABS(F47)+ABS(F48)+ABS(F49) -> 0 | G53: =ABS(G45)+ABS(G46)+ABS(G47)+ABS(G48)+ABS(G49) -> 0 | H53: =ABS(H45)+ABS(H46)+ABS(H47)+ABS(H48)+ABS(H49) -> 0 | I53: =ABS(I45)+ABS(I46)+ABS(I47)+ABS(I48)+ABS(I49) -> 0 | J53: =ABS(J50)+ABS(J51)+ABS(J52) -> 0 | K53: =ABS(K50)+ABS(K51)+ABS(K52) -> 0 | L53: =ABS(L50)+ABS(L51)+ABS(L52) -> 0 | M53: =ABS(M50)+ABS(M51)+ABS(M52) -> 0 | N53: =ABS(N50)+ABS(N51)+ABS(N52) -> 0 | O53: =ABS(O50)+ABS(O51)+ABS(O52) -> 0 | P53: =ABS(P50)+ABS(P51)+ABS(P52) -> 0 | Q53: =ABS(Q50)+ABS(Q51)+ABS(Q52) -> 0 | ... S53: =ABS(S50)+ABS(S51)+ABS(S52) -> 0
B55: Note: the forecast opening cash for FY26E starts from the audited BS cash (64,845) while reported FY25 closing cash equivalents is 64,862; the difference is not carried forward.

Sheet Input_Register
B1: Input register - every market input and orange (estimate) cell on Sheet1
B2: Status: VERIFIED = traced to a filing or market source; ESTIMATE = analyst estimate, needs a source before the report; JUDGMENT = analyst choice; PLACEHOLDER = not yet researched. Values are live links to Sheet1.
B4: Item | C4: Value (base col E) | D4: Source / note on Sheet1 | E4: Status | F4: Action before submission
B5: [Sheet1 row 20] Current share price | C5: =Sheet1!E20 -> 1095 | D5: Close Fri 16-Oct-26 = 1,095 (user-supplied from market screen). Earlier values 1,335 (8-Oct), 1,385 (6-Oct close) are superseded | E5: VERIFIED (user) | F5: Refresh to latest close on submission date
B6: [Sheet1 row 21] Shares outstanding (pre rights issue) | C6: =Sheet1!E21 -> 46129.26 | D6: 46,129,260,138 sh at 31-Aug-26 (BSI IR/IDX) | E6: VERIFIED | F6: Adjust for rights issue shares when executed
B7: [Sheet1 row 22] Valuation date | C7: =Sheet1!E22 -> 46304 | E7: INPUT | F7: -
B8: [Sheet1 row 23] FY25 dividend payment date (paid in FY26) | C8: =Sheet1!E23 -> 46178 | D8: RUPST May-26: Rp1,513.5bn, DPS 32.81, 20% payout | E8: VERIFIED | F8: -
B9: [Sheet1 row 24] Risk-free rate, IDR (10Y INDOGB less sovereign default spread) | C9: =Sheet1!E24 -> 0.0556 | D9: G33 = 10Y INDOGB 7.18% (6-Oct-26). H33 = Damodaran default spread for Baa2, 1.62% (Jan-26). Net rf = gross - spread (CRP is added once, inside the ERP) | E9: VERIFIED | F9: Refresh gross yield; check Damodaran Jul-26 update
B10: [Sheet1 row 25] Equity risk premium (Indonesia) | C10: =Sheet1!E25 -> 0.0669 | D10: Damodaran Jan-26: 4.23% mature + 2.46% CRP | E10: VERIFIED | F10: Damodaran Jan-26 Indonesia: 4.23% mature + 2.46% CRP; update if July file available
B11: [Sheet1 row 26] Beta (TradingView 1Y raw 0.64, Blume-adjusted) | C11: =Sheet1!E26 -> 0.7588 | D11: Blume-adjusted from raw 0.64 (1y); 60m monthly regression vs IHSG gives 0.69 (SE 0.29, R2 0.09); peer avg about 0.9. Low precision, see Input_Register | E11: ESTIMATE | F11: Beta evidence 0.64-1.0; decide final (BRIS 1y 0.64 / 60m 0.69 / peers 0.9)
B12: [Sheet1 row 27] Size / liquidity premium | C12: =Sheet1!E27 -> 0 | D12: Set to 0 in v4.0 (was +1.0%, pure judgment, would double count the CRP). Kept as a toggle. Lambda approach (beta on mature ERP, full CRP) equals about +0.6% here | E12: JUDGMENT | F12: Now 0; keep documented as toggle
B13: [Sheet1 row 35] Target CAR (internal floor) | C13: =Sheet1!E35 -> 0.2 | D13: Reported CAR 20.41% at Jun-26 (Q2-26 statement); mgmt aim to stay >20%; post-rights-issue 22-24% (prospectus) | E13: ESTIMATE | F13: Mgmt target "unverified": confirm in 1H26 analyst call / prospectus
B14: [Sheet1 row 36] Regulatory minimum CAR incl. buffers | C14: =Sheet1!E36 -> 0.1349 | D14: AR2025: 9.99% risk profile + 2.5% CCB + 1.0% D-SIB = 13.49% | E14: VERIFIED (AR2025) | F14: OJK/POJK rules
B15: [Sheet1 row 37] FDR cap | C15: =Sheet1!E37 -> 0.92 | E15: ESTIMATE | F15: Confirm regulatory FDR cap
B16: [Sheet1 row 38] Min cash & BI placements / DPK (GWM proxy) | C16: =Sheet1!E38 -> 0.075 | D16: Sharia GWM 7.5% (conventional 9.0%) | E16: VERIFIED | F16: BI sharia GWM 7.5%
B17: [Sheet1 row 45] Pass-through of BI rate change to time-deposit rate | C17: =Sheet1!E45 -> 0.6 | E17: ESTIMATE / PLACEHOLDER | F17: Orange cell: replace with filing data (BS detail, debt, fixed assets, rates)
B18: [Sheet1 row 46] Pass-through to CASA rate | C18: =Sheet1!E46 -> 0.1 | E18: ESTIMATE / PLACEHOLDER | F18: Orange cell: replace with filing data (BS detail, debt, fixed assets, rates)
B19: [Sheet1 row 47] Pass-through to gross financing yield | C19: =Sheet1!E47 -> 0.15 | E19: ESTIMATE / PLACEHOLDER | F19: Orange cell: replace with filing data (BS detail, debt, fixed assets, rates)
B20: [Sheet1 row 121] Interbank & other borrowings rate | C20: =Sheet1!E121 -> 0.06 | E20: ESTIMATE / PLACEHOLDER | F20: Orange cell: replace with filing data (BS detail, debt, fixed assets, rates)
B21: [Sheet1 row 122] Capex as % of operating income | C21: =Sheet1!E122 -> 0.08 | D21: FY25 capex ~2.5tn (unverified) / op income 25.9tn | E21: ESTIMATE / PLACEHOLDER | F21: Orange cell: replace with filing data (BS detail, debt, fixed assets, rates)
B22: [Sheet1 row 123] Capex mix - Land & buildings | C22: =Sheet1!E123 -> 0.1 | E22: ESTIMATE / PLACEHOLDER | F22: Orange cell: replace with filing data (BS detail, debt, fixed assets, rates)
B23: [Sheet1 row 124] Depreciation / amortisation rate (declining balance on NBV) - Land & buildings | C23: =Sheet1!E124 -> 0.05 | E23: ESTIMATE / PLACEHOLDER | F23: Orange cell: replace with filing data (BS detail, debt, fixed assets, rates)
B24: [Sheet1 row 125] Capex mix - Equipment & IT | C24: =Sheet1!E125 -> 0.4 | E24: ESTIMATE / PLACEHOLDER | F24: Orange cell: replace with filing data (BS detail, debt, fixed assets, rates)
B25: [Sheet1 row 126] Depreciation / amortisation rate (declining balance on NBV) - Equipment & IT | C25: =Sheet1!E126 -> 0.25 | E25: ESTIMATE / PLACEHOLDER | F25: Orange cell: replace with filing data (BS detail, debt, fixed assets, rates)
B26: [Sheet1 row 127] Capex mix - Right-of-use assets | C26: =Sheet1!E127 -> 0.25 | E26: ESTIMATE / PLACEHOLDER | F26: Orange cell: replace with filing data (BS detail, debt, fixed assets, rates)
B27: [Sheet1 row 128] Depreciation / amortisation rate (declining balance on NBV) - Right-of-use assets | C27: =Sheet1!E128 -> 0.2 | E27: ESTIMATE / PLACEHOLDER | F27: Orange cell: replace with filing data (BS detail, debt, fixed assets, rates)
B28: [Sheet1 row 129] Capex mix - Intangibles / software | C28: =Sheet1!E129 -> 0.25 | E28: ESTIMATE / PLACEHOLDER | F28: Orange cell: replace with filing data (BS detail, debt, fixed assets, rates)
B29: [Sheet1 row 130] Depreciation / amortisation rate (declining balance on NBV) - Intangibles / software | C29: =Sheet1!E130 -> 0.2 | E29: ESTIMATE / PLACEHOLDER | F29: Orange cell: replace with filing data (BS detail, debt, fixed assets, rates)
B30: [Sheet1 row 131] Lease liability / ROU net book value | C30: =Sheet1!E131 -> 1 | E30: ESTIMATE / PLACEHOLDER | F30: Orange cell: replace with filing data (BS detail, debt, fixed assets, rates)
B31: [Sheet1 row 132] Regulatory capital / book equity (ex Tier-2 sukuk) | C31: =Sheet1!E132 -> 0.97344259 | D31: FY24 0.97, FY25 0.92, Jun-26 0.94 (capital/equity) | E31: ESTIMATE / PLACEHOLDER | F31: Orange cell: replace with filing data (BS detail, debt, fixed assets, rates)
B32: [Sheet1 row 135] Rights issue price | C32: =Sheet1!E135 -> 940 | D32: Not disclosed. Placeholder = 14% discount to latest close. Size up to 6.8 bn shares, Q1-27 (disclosure 30-Sep-26) | E32: ESTIMATE / PLACEHOLDER | F32: Orange cell: replace with filing data (BS detail, debt, fixed assets, rates)
B33: [Sheet1 row 136] Pre-tax return on deployed rights-issue capital | C33: =Sheet1!E136 -> 0.09 | D33: JUDGMENT: proceeds earmarked for financing growth | E33: ESTIMATE / PLACEHOLDER | F33: Orange cell: replace with filing data (BS detail, debt, fixed assets, rates)
B35: Items that came from Gemini research (not independently traced): market data, BS detail FY23-25, dividend data. Re-trace each to the annual report / IDX before use.
B36: [Sheet1 rows 141-154, 327, 330] FY21A-FY25A income statement, capital, RWA | C36: AR2021-AR2025 | D36: =Sheet1!I154 -> 7567.523 | E36: AR financial statements and capital adequacy notes | F36: VERIFIED (AR)
B37: [Sheet1 rows 459-463] Peer price, net profit 1H26, equity, shares | C37: 1H26 statements / presentations | D37: =Sheet1!G466 -> 1.1117615 | E37: Profit and equity from 1H26 statements and presentations (BBRI, BMRI, BBNI, BBCA, BTPS); 16-Oct closes from team, to verify on IDX | F37: VERIFIED (fundamentals); PRICES TO CHECK
B38: [Sheet1 row 479] BRIS 1H25 / 1H26 net profit, 30-Jun-26 equity | C38: 1H26 statement | D38: =Sheet1!F479 -> 4155.709 | E38: Interim statement 30 Jun 2026 | F38: VERIFIED

Sheet Beta
A1: Regression beta vs IHSG, monthly simple returns (formulas)
A3: Last 12 months | B3: BRIS | C3: BBCA | D3: BBRI | E3: BMRI | F3: BBNI | G3: BTPS
A4: Beta (SLOPE) | B4: =IFERROR(SLOPE(Returns!C59:C70,Returns!B59:B70),"") -> 0.30100224 | C4: =IFERROR(SLOPE(Returns!D59:D70,Returns!B59:B70),"") -> 0.62371873 | D4: =IFERROR(SLOPE(Returns!E59:E70,Returns!B59:B70),"") -> 0.66277363 | E4: =IFERROR(SLOPE(Returns!F59:F70,Returns!B59:B70),"") -> 0.74426056 | F4: =IFERROR(SLOPE(Returns!G59:G70,Returns!B59:B70),"") -> 0.91415673 | G4: =IFERROR(SLOPE(Returns!H59:H70,Returns!B59:B70),"") -> 0.17610487
A5: R-squared | B5: =IFERROR(RSQ(Returns!C59:C70,Returns!B59:B70),"") -> 0.051631034 | C5: =IFERROR(RSQ(Returns!D59:D70,Returns!B59:B70),"") -> 0.49901209 | D5: =IFERROR(RSQ(Returns!E59:E70,Returns!B59:B70),"") -> 0.41276554 | E5: =IFERROR(RSQ(Returns!F59:F70,Returns!B59:B70),"") -> 0.64307436 | F5: =IFERROR(RSQ(Returns!G59:G70,Returns!B59:B70),"") -> 0.60944215 | G5: =IFERROR(RSQ(Returns!H59:H70,Returns!B59:B70),"") -> 0.08669111
A6: Std error of beta | B6: =IFERROR(STEYX(Returns!C59:C70,Returns!B59:B70)/SQRT(DEVSQ(Returns!B59:B70)),"") -> 0.40794629 | C6: =IFERROR(STEYX(Returns!D59:D70,Returns!B59:B70)/SQRT(DEVSQ(Returns!B59:B70)),"") -> 0.19762727 | D6: =IFERROR(STEYX(Returns!E59:E70,Returns!B59:B70)/SQRT(DEVSQ(Returns!B59:B70)),"") -> 0.24998806 | E6: =IFERROR(STEYX(Returns!F59:F70,Returns!B59:B70)/SQRT(DEVSQ(Returns!B59:B70)),"") -> 0.17534092 | F6: =IFERROR(STEYX(Returns!G59:G70,Returns!B59:B70)/SQRT(DEVSQ(Returns!B59:B70)),"") -> 0.23141799 | G6: =IFERROR(STEYX(Returns!H59:H70,Returns!B59:B70)/SQRT(DEVSQ(Returns!B59:B70)),"") -> 0.18075608
A7: Blume-adjusted beta | B7: =IFERROR(0.67*B4+0.33,"") -> 0.5316715 | C7: =IFERROR(0.67*C4+0.33,"") -> 0.74789155 | D7: =IFERROR(0.67*D4+0.33,"") -> 0.77405833 | E7: =IFERROR(0.67*E4+0.33,"") -> 0.82865457 | F7: =IFERROR(0.67*F4+0.33,"") -> 0.94248501 | G7: =IFERROR(0.67*G4+0.33,"") -> 0.44799026
A8: Observations | B8: =SUMPRODUCT(ISNUMBER(Returns!C59:C70)*ISNUMBER(Returns!B59:B70)) -> 12 | C8: =SUMPRODUCT(ISNUMBER(Returns!D59:D70)*ISNUMBER(Returns!B59:B70)) -> 12 | D8: =SUMPRODUCT(ISNUMBER(Returns!E59:E70)*ISNUMBER(Returns!B59:B70)) -> 12 | E8: =SUMPRODUCT(ISNUMBER(Returns!F59:F70)*ISNUMBER(Returns!B59:B70)) -> 12 | F8: =SUMPRODUCT(ISNUMBER(Returns!G59:G70)*ISNUMBER(Returns!B59:B70)) -> 12 | G8: =SUMPRODUCT(ISNUMBER(Returns!H59:H70)*ISNUMBER(Returns!B59:B70)) -> 12
A11: Last 24 months | B11: BRIS | C11: BBCA | D11: BBRI | E11: BMRI | F11: BBNI | G11: BTPS
A12: Beta (SLOPE) | B12: =IFERROR(SLOPE(Returns!C47:C70,Returns!B47:B70),"") -> 0.6376022 | C12: =IFERROR(SLOPE(Returns!D47:D70,Returns!B47:B70),"") -> 0.59044719 | D12: =IFERROR(SLOPE(Returns!E47:E70,Returns!B47:B70),"") -> 0.98273538 | E12: =IFERROR(SLOPE(Returns!F47:F70,Returns!B47:B70),"") -> 0.82943066 | F12: =IFERROR(SLOPE(Returns!G47:G70,Returns!B47:B70),"") -> 0.89668911 | G12: =IFERROR(SLOPE(Returns!H47:H70,Returns!B47:B70),"") -> 0.58315931
A13: R-squared | B13: =IFERROR(RSQ(Returns!C47:C70,Returns!B47:B70),"") -> 0.17966895 | C13: =IFERROR(RSQ(Returns!D47:D70,Returns!B47:B70),"") -> 0.37912242 | D13: =IFERROR(RSQ(Returns!E47:E70,Returns!B47:B70),"") -> 0.42076288 | E13: =IFERROR(RSQ(Returns!F47:F70,Returns!B47:B70),"") -> 0.39658023 | F13: =IFERROR(RSQ(Returns!G47:G70,Returns!B47:B70),"") -> 0.47896596 | G13: =IFERROR(RSQ(Returns!H47:H70,Returns!B47:B70),"") -> 0.18581641
A14: Std error of beta | B14: =IFERROR(STEYX(Returns!C47:C70,Returns!B47:B70)/SQRT(DEVSQ(Returns!B47:B70)),"") -> 0.29046681 | C14: =IFERROR(STEYX(Returns!D47:D70,Returns!B47:B70)/SQRT(DEVSQ(Returns!B47:B70)),"") -> 0.16109534 | D14: =IFERROR(STEYX(Returns!E47:E70,Returns!B47:B70)/SQRT(DEVSQ(Returns!B47:B70)),"") -> 0.24582992 | E14: =IFERROR(STEYX(Returns!F47:F70,Returns!B47:B70)/SQRT(DEVSQ(Returns!B47:B70)),"") -> 0.21972257 | F14: =IFERROR(STEYX(Returns!G47:G70,Returns!B47:B70)/SQRT(DEVSQ(Returns!B47:B70)),"") -> 0.19939363 | G14: =IFERROR(STEYX(Returns!H47:H70,Returns!B47:B70)/SQRT(DEVSQ(Returns!B47:B70)),"") -> 0.26025256
A15: Blume-adjusted beta | B15: =IFERROR(0.67*B12+0.33,"") -> 0.75719348 | C15: =IFERROR(0.67*C12+0.33,"") -> 0.72559962 | D15: =IFERROR(0.67*D12+0.33,"") -> 0.9884327 | E15: =IFERROR(0.67*E12+0.33,"") -> 0.88571854 | F15: =IFERROR(0.67*F12+0.33,"") -> 0.93078171 | G15: =IFERROR(0.67*G12+0.33,"") -> 0.72071674
A16: Observations | B16: =SUMPRODUCT(ISNUMBER(Returns!C47:C70)*ISNUMBER(Returns!B47:B70)) -> 24 | C16: =SUMPRODUCT(ISNUMBER(Returns!D47:D70)*ISNUMBER(Returns!B47:B70)) -> 24 | D16: =SUMPRODUCT(ISNUMBER(Returns!E47:E70)*ISNUMBER(Returns!B47:B70)) -> 24 | E16: =SUMPRODUCT(ISNUMBER(Returns!F47:F70)*ISNUMBER(Returns!B47:B70)) -> 23 | F16: =SUMPRODUCT(ISNUMBER(Returns!G47:G70)*ISNUMBER(Returns!B47:B70)) -> 24 | G16: =SUMPRODUCT(ISNUMBER(Returns!H47:H70)*ISNUMBER(Returns!B47:B70)) -> 24
A19: Last 36 months | B19: BRIS | C19: BBCA | D19: BBRI | E19: BMRI | F19: BBNI | G19: BTPS
A20: Beta (SLOPE) | B20: =IFERROR(SLOPE(Returns!C35:C70,Returns!B35:B70),"") -> 0.72171799 | C20: =IFERROR(SLOPE(Returns!D35:D70,Returns!B35:B70),"") -> 0.62690894 | D20: =IFERROR(SLOPE(Returns!E35:E70,Returns!B35:B70),"") -> 1.0900636 | E20: =IFERROR(SLOPE(Returns!F35:F70,Returns!B35:B70),"") -> 0.82943066 | F20: =IFERROR(SLOPE(Returns!G35:G70,Returns!B35:B70),"") -> 1.0062704 | G20: =IFERROR(SLOPE(Returns!H35:H70,Returns!B35:B70),"") -> 0.61537197
A21: R-squared | B21: =IFERROR(RSQ(Returns!C35:C70,Returns!B35:B70),"") -> 0.12101862 | C21: =IFERROR(RSQ(Returns!D35:D70,Returns!B35:B70),"") -> 0.37935206 | D21: =IFERROR(RSQ(Returns!E35:E70,Returns!B35:B70),"") -> 0.41655903 | E21: =IFERROR(RSQ(Returns!F35:F70,Returns!B35:B70),"") -> 0.39658023 | F21: =IFERROR(RSQ(Returns!G35:G70,Returns!B35:B70),"") -> 0.46007241 | G21: =IFERROR(RSQ(Returns!H35:H70,Returns!B35:B70),"") -> 0.16939433
A22: Std error of beta | B22: =IFERROR(STEYX(Returns!C35:C70,Returns!B35:B70)/SQRT(DEVSQ(Returns!B35:B70)),"") -> 0.33357371 | C22: =IFERROR(STEYX(Returns!D35:D70,Returns!B35:B70)/SQRT(DEVSQ(Returns!B35:B70)),"") -> 0.13752018 | D22: =IFERROR(STEYX(Returns!E35:E70,Returns!B35:B70)/SQRT(DEVSQ(Returns!B35:B70)),"") -> 0.22124454 | E22: =IFERROR(STEYX(Returns!F35:F70,Returns!B35:B70)/SQRT(DEVSQ(Returns!B35:B70)),"") -> 0.20886528 | F22: =IFERROR(STEYX(Returns!G35:G70,Returns!B35:B70)/SQRT(DEVSQ(Returns!B35:B70)),"") -> 0.18695191 | G22: =IFERROR(STEYX(Returns!H35:H70,Returns!B35:B70)/SQRT(DEVSQ(Returns!B35:B70)),"") -> 0.2336933
A23: Blume-adjusted beta | B23: =IFERROR(0.67*B20+0.33,"") -> 0.81355105 | C23: =IFERROR(0.67*C20+0.33,"") -> 0.75002899 | D23: =IFERROR(0.67*D20+0.33,"") -> 1.0603426 | E23: =IFERROR(0.67*E20+0.33,"") -> 0.88571854 | F23: =IFERROR(0.67*F20+0.33,"") -> 1.0042012 | G23: =IFERROR(0.67*G20+0.33,"") -> 0.74229922
A24: Observations | B24: =SUMPRODUCT(ISNUMBER(Returns!C35:C70)*ISNUMBER(Returns!B35:B70)) -> 36 | C24: =SUMPRODUCT(ISNUMBER(Returns!D35:D70)*ISNUMBER(Returns!B35:B70)) -> 36 | D24: =SUMPRODUCT(ISNUMBER(Returns!E35:E70)*ISNUMBER(Returns!B35:B70)) -> 36 | E24: =SUMPRODUCT(ISNUMBER(Returns!F35:F70)*ISNUMBER(Returns!B35:B70)) -> 23 | F24: =SUMPRODUCT(ISNUMBER(Returns!G35:G70)*ISNUMBER(Returns!B35:B70)) -> 36 | G24: =SUMPRODUCT(ISNUMBER(Returns!H35:H70)*ISNUMBER(Returns!B35:B70)) -> 36
A27: Last 60 months | B27: BRIS | C27: BBCA | D27: BBRI | E27: BMRI | F27: BBNI | G27: BTPS
A28: Beta (SLOPE) | B28: =IFERROR(SLOPE(Returns!C11:C70,Returns!B11:B70),"") -> 0.69327187 | C28: =IFERROR(SLOPE(Returns!D11:D70,Returns!B11:B70),"") -> 0.67349884 | D28: =IFERROR(SLOPE(Returns!E11:E70,Returns!B11:B70),"") -> 1.0819357 | E28: =IFERROR(SLOPE(Returns!F11:F70,Returns!B11:B70),"") -> 0.82943066 | F28: =IFERROR(SLOPE(Returns!G11:G70,Returns!B11:B70),"") -> 1.0744751 | G28: =IFERROR(SLOPE(Returns!H11:H70,Returns!B11:B70),"") -> 0.75546226
A29: R-squared | B29: =IFERROR(RSQ(Returns!C11:C70,Returns!B11:B70),"") -> 0.092553864 | C29: =IFERROR(RSQ(Returns!D11:D70,Returns!B11:B70),"") -> 0.34435591 | D29: =IFERROR(RSQ(Returns!E11:E70,Returns!B11:B70),"") -> 0.36575159 | E29: =IFERROR(RSQ(Returns!F11:F70,Returns!B11:B70),"") -> 0.39658023 | F29: =IFERROR(RSQ(Returns!G11:G70,Returns!B11:B70),"") -> 0.40226372 | G29: =IFERROR(RSQ(Returns!H11:H70,Returns!B11:B70),"") -> 0.17914962
A30: Std error of beta | B30: =IFERROR(STEYX(Returns!C11:C70,Returns!B11:B70)/SQRT(DEVSQ(Returns!B11:B70)),"") -> 0.28503798 | C30: =IFERROR(STEYX(Returns!D11:D70,Returns!B11:B70)/SQRT(DEVSQ(Returns!B11:B70)),"") -> 0.12202622 | D30: =IFERROR(STEYX(Returns!E11:E70,Returns!B11:B70)/SQRT(DEVSQ(Returns!B11:B70)),"") -> 0.18707856 | E30: =IFERROR(STEYX(Returns!F11:F70,Returns!B11:B70)/SQRT(DEVSQ(Returns!B11:B70)),"") -> 0.19883535 | F30: =IFERROR(STEYX(Returns!G11:G70,Returns!B11:B70)/SQRT(DEVSQ(Returns!B11:B70)),"") -> 0.17198149 | G30: =IFERROR(STEYX(Returns!H11:H70,Returns!B11:B70)/SQRT(DEVSQ(Returns!B11:B70)),"") -> 0.21233561
A31: Blume-adjusted beta | B31: =IFERROR(0.67*B28+0.33,"") -> 0.79449216 | C31: =IFERROR(0.67*C28+0.33,"") -> 0.78124423 | D31: =IFERROR(0.67*D28+0.33,"") -> 1.0548969 | E31: =IFERROR(0.67*E28+0.33,"") -> 0.88571854 | F31: =IFERROR(0.67*F28+0.33,"") -> 1.0498983 | G31: =IFERROR(0.67*G28+0.33,"") -> 0.83615971
A32: Observations | B32: =SUMPRODUCT(ISNUMBER(Returns!C11:C70)*ISNUMBER(Returns!B11:B70)) -> 60 | C32: =SUMPRODUCT(ISNUMBER(Returns!D11:D70)*ISNUMBER(Returns!B11:B70)) -> 60 | D32: =SUMPRODUCT(ISNUMBER(Returns!E11:E70)*ISNUMBER(Returns!B11:B70)) -> 60 | E32: =SUMPRODUCT(ISNUMBER(Returns!F11:F70)*ISNUMBER(Returns!B11:B70)) -> 23 | F32: =SUMPRODUCT(ISNUMBER(Returns!G11:G70)*ISNUMBER(Returns!B11:B70)) -> 60 | G32: =SUMPRODUCT(ISNUMBER(Returns!H11:H70)*ISNUMBER(Returns!B11:B70)) -> 60
A35: All available | B35: BRIS | C35: BBCA | D35: BBRI | E35: BMRI | F35: BBNI | G35: BTPS
A36: Beta (SLOPE) | B36: =IFERROR(SLOPE(Returns!C3:C70,Returns!B3:B70),"") -> 0.76084242 | C36: =IFERROR(SLOPE(Returns!D3:D70,Returns!B3:B70),"") -> 0.71725339 | D36: =IFERROR(SLOPE(Returns!E3:E70,Returns!B3:B70),"") -> 1.0940887 | E36: =IFERROR(SLOPE(Returns!F3:F70,Returns!B3:B70),"") -> 0.82943066 | F36: =IFERROR(SLOPE(Returns!G3:G70,Returns!B3:B70),"") -> 1.1723965 | G36: =IFERROR(SLOPE(Returns!H3:H70,Returns!B3:B70),"") -> 0.87003125
A37: R-squared | B37: =IFERROR(RSQ(Returns!C3:C70,Returns!B3:B70),"") -> 0.091042256 | C37: =IFERROR(RSQ(Returns!D3:D70,Returns!B3:B70),"") -> 0.34408737 | D37: =IFERROR(RSQ(Returns!E3:E70,Returns!B3:B70),"") -> 0.35554846 | E37: =IFERROR(RSQ(Returns!F3:F70,Returns!B3:B70),"") -> 0.39658023 | F37: =IFERROR(RSQ(Returns!G3:G70,Returns!B3:B70),"") -> 0.35967426 | G37: =IFERROR(RSQ(Returns!H3:H70,Returns!B3:B70),"") -> 0.16969218
A38: Std error of beta | B38: =IFERROR(STEYX(Returns!C3:C70,Returns!B3:B70)/SQRT(DEVSQ(Returns!B3:B70)),"") -> 0.29591917 | C38: =IFERROR(STEYX(Returns!D3:D70,Returns!B3:B70)/SQRT(DEVSQ(Returns!B3:B70)),"") -> 0.12189595 | D38: =IFERROR(STEYX(Returns!E3:E70,Returns!B3:B70)/SQRT(DEVSQ(Returns!B3:B70)),"") -> 0.18131189 | E38: =IFERROR(STEYX(Returns!F3:F70,Returns!B3:B70)/SQRT(DEVSQ(Returns!B3:B70)),"") -> 0.19479744 | F38: =IFERROR(STEYX(Returns!G3:G70,Returns!B3:B70)/SQRT(DEVSQ(Returns!B3:B70)),"") -> 0.19255213 | G38: =IFERROR(STEYX(Returns!H3:H70,Returns!B3:B70)/SQRT(DEVSQ(Returns!B3:B70)),"") -> 0.23689262
A39: Blume-adjusted beta | B39: =IFERROR(0.67*B36+0.33,"") -> 0.83976442 | C39: =IFERROR(0.67*C36+0.33,"") -> 0.81055977 | D39: =IFERROR(0.67*D36+0.33,"") -> 1.0630394 | E39: =IFERROR(0.67*E36+0.33,"") -> 0.88571854 | F39: =IFERROR(0.67*F36+0.33,"") -> 1.1155056 | G39: =IFERROR(0.67*G36+0.33,"") -> 0.91292094
A40: Observations | B40: =SUMPRODUCT(ISNUMBER(Returns!C3:C70)*ISNUMBER(Returns!B3:B70)) -> 68 | C40: =SUMPRODUCT(ISNUMBER(Returns!D3:D70)*ISNUMBER(Returns!B3:B70)) -> 68 | D40: =SUMPRODUCT(ISNUMBER(Returns!E3:E70)*ISNUMBER(Returns!B3:B70)) -> 68 | E40: =SUMPRODUCT(ISNUMBER(Returns!F3:F70)*ISNUMBER(Returns!B3:B70)) -> 23 | F40: =SUMPRODUCT(ISNUMBER(Returns!G3:G70)*ISNUMBER(Returns!B3:B70)) -> 68 | G40: =SUMPRODUCT(ISNUMBER(Returns!H3:H70)*ISNUMBER(Returns!B3:B70)) -> 68
A43: Annualised volatility (monthly stdev x sqrt 12), last 60 months
B44: IHSG | C44: BRIS | D44: BBCA | E44: BBRI | F44: BMRI | G44: BBNI | H44: BTPS
B45: =IFERROR(STDEV(Returns!B11:B70)*SQRT(12),"") -> 0.15539413 | C45: =IFERROR(STDEV(Returns!C11:C70)*SQRT(12),"") -> 0.35411221 | D45: =IFERROR(STDEV(Returns!D11:D70)*SQRT(12),"") -> 0.17834777 | E45: =IFERROR(STDEV(Returns!E11:E70)*SQRT(12),"") -> 0.27799881 | F45: =IFERROR(STDEV(Returns!F11:F70)*SQRT(12),"") -> 0.2984989 | G45: =IFERROR(STDEV(Returns!G11:G70)*SQRT(12),"") -> 0.26325432 | H45: =IFERROR(STDEV(Returns!H11:H70)*SQRT(12),"") -> 0.27735719

Sheet Returns
A1: Month | B1: IHSG | C1: BRIS | D1: BBCA | E1: BBRI | F1: BMRI | G1: BBNI | H1: BTPS
A3: =Prices!A3 -> 44256 | B3: =IF(AND(ISNUMBER(Prices!B3),ISNUMBER(Prices!B2)),Prices!B3/Prices!B2-1,"") -> -0.041058669 | C3: =IF(AND(ISNUMBER(Prices!C3),ISNUMBER(Prices!C2)),Prices!C3/Prices!C2-1,"") -> -0.22113708 | D3: =IF(AND(ISNUMBER(Prices!D3),ISNUMBER(Prices!D2)),Prices!D3/Prices!D2-1,"") -> -0.073770492 | E3: =IF(AND(ISNUMBER(Prices!E3),ISNUMBER(Prices!E2)),Prices!E3/Prices!E2-1,"") -> -0.065723613 | F3: =IF(AND(ISNUMBER(Prices!F3),ISNUMBER(Prices!F2)),Prices!F3/Prices!F2-1,"") | G3: =IF(AND(ISNUMBER(Prices!G3),ISNUMBER(Prices!G2)),Prices!G3/Prices!G2-1,"") -> -0.037647059 | H3: =IF(AND(ISNUMBER(Prices!H3),ISNUMBER(Prices!H2)),Prices!H3/Prices!H2-1,"") -> -0.15121951
A4: =Prices!A4 -> 44287 | B4: =IF(AND(ISNUMBER(Prices!B4),ISNUMBER(Prices!B3)),Prices!B4/Prices!B3-1,"") -> 0.0016874056 | C4: =IF(AND(ISNUMBER(Prices!C4),ISNUMBER(Prices!C3)),Prices!C4/Prices!C3-1,"") -> -0.0040304523 | D4: =IF(AND(ISNUMBER(Prices!D4),ISNUMBER(Prices!D3)),Prices!D4/Prices!D3-1,"") -> 0.030571199 | E4: =IF(AND(ISNUMBER(Prices!E4),ISNUMBER(Prices!E3)),Prices!E4/Prices!E3-1,"") -> -0.07966457 | F4: =IF(AND(ISNUMBER(Prices!F4),ISNUMBER(Prices!F3)),Prices!F4/Prices!F3-1,"") | G4: =IF(AND(ISNUMBER(Prices!G4),ISNUMBER(Prices!G3)),Prices!G4/Prices!G3-1,"") -> -0.0045406916 | H4: =IF(AND(ISNUMBER(Prices!H4),ISNUMBER(Prices!H3)),Prices!H4/Prices!H3-1,"") -> -0.060344828
A5: =Prices!A5 -> 44317 | B5: =IF(AND(ISNUMBER(Prices!B5),ISNUMBER(Prices!B4)),Prices!B5/Prices!B4-1,"") -> -0.0080325304 | C5: =IF(AND(ISNUMBER(Prices!C5),ISNUMBER(Prices!C4)),Prices!C5/Prices!C4-1,"") -> -0.16456835 | D5: =IF(AND(ISNUMBER(Prices!D5),ISNUMBER(Prices!D4)),Prices!D5/Prices!D4-1,"") -> -0.0046838407 | E5: =IF(AND(ISNUMBER(Prices!E5),ISNUMBER(Prices!E4)),Prices!E5/Prices!E4-1,"") -> 0.051885599 | F5: =IF(AND(ISNUMBER(Prices!F5),ISNUMBER(Prices!F4)),Prices!F5/Prices!F4-1,"") | G5: =IF(AND(ISNUMBER(Prices!G5),ISNUMBER(Prices!G4)),Prices!G5/Prices!G4-1,"") -> -0.052631579 | H5: =IF(AND(ISNUMBER(Prices!H5),ISNUMBER(Prices!H4)),Prices!H5/Prices!H4-1,"") -> -0.11314985
A6: =Prices!A6 -> 44348 | B6: =IF(AND(ISNUMBER(Prices!B6),ISNUMBER(Prices!B5)),Prices!B6/Prices!B5-1,"") -> 0.0063943263 | C6: =IF(AND(ISNUMBER(Prices!C6),ISNUMBER(Prices!C5)),Prices!C6/Prices!C5-1,"") -> 0.20721206 | D6: =IF(AND(ISNUMBER(Prices!D6),ISNUMBER(Prices!D5)),Prices!D6/Prices!D5-1,"") -> -0.054901961 | E6: =IF(AND(ISNUMBER(Prices!E6),ISNUMBER(Prices!E5)),Prices!E6/Prices!E5-1,"") -> -0.075072185 | F6: =IF(AND(ISNUMBER(Prices!F6),ISNUMBER(Prices!F5)),Prices!F6/Prices!F5-1,"") | G6: =IF(AND(ISNUMBER(Prices!G6),ISNUMBER(Prices!G5)),Prices!G6/Prices!G5-1,"") -> -0.14259259 | H6: =IF(AND(ISNUMBER(Prices!H6),ISNUMBER(Prices!H5)),Prices!H6/Prices!H5-1,"") -> -0.0068965517
A7: =Prices!A7 -> 44378 | B7: =IF(AND(ISNUMBER(Prices!B7),ISNUMBER(Prices!B6)),Prices!B7/Prices!B6-1,"") -> 0.014125828 | C7: =IF(AND(ISNUMBER(Prices!C7),ISNUMBER(Prices!C6)),Prices!C7/Prices!C6-1,"") -> 0.14355774 | D7: =IF(AND(ISNUMBER(Prices!D7),ISNUMBER(Prices!D6)),Prices!D7/Prices!D6-1,"") -> -0.0091286307 | E7: =IF(AND(ISNUMBER(Prices!E7),ISNUMBER(Prices!E6)),Prices!E7/Prices!E6-1,"") -> -0.058272633 | F7: =IF(AND(ISNUMBER(Prices!F7),ISNUMBER(Prices!F6)),Prices!F7/Prices!F6-1,"") | G7: =IF(AND(ISNUMBER(Prices!G7),ISNUMBER(Prices!G6)),Prices!G7/Prices!G6-1,"") -> 0.032397408 | H7: =IF(AND(ISNUMBER(Prices!H7),ISNUMBER(Prices!H6)),Prices!H7/Prices!H6-1,"") -> -0.17708333
A8: =Prices!A8 -> 44409 | B8: =IF(AND(ISNUMBER(Prices!B8),ISNUMBER(Prices!B7)),Prices!B8/Prices!B7-1,"") -> 0.013222318 | C8: =IF(AND(ISNUMBER(Prices!C8),ISNUMBER(Prices!C7)),Prices!C8/Prices!C7-1,"") -> -0.15594542 | D8: =IF(AND(ISNUMBER(Prices!D8),ISNUMBER(Prices!D7)),Prices!D8/Prices!D7-1,"") -> 0.097152429 | E8: =IF(AND(ISNUMBER(Prices!E8),ISNUMBER(Prices!E7)),Prices!E8/Prices!E7-1,"") -> 0.059116022 | F8: =IF(AND(ISNUMBER(Prices!F8),ISNUMBER(Prices!F7)),Prices!F8/Prices!F7-1,"") | G8: =IF(AND(ISNUMBER(Prices!G8),ISNUMBER(Prices!G7)),Prices!G8/Prices!G7-1,"") -> 0.12970711 | H8: =IF(AND(ISNUMBER(Prices!H8),ISNUMBER(Prices!H7)),Prices!H8/Prices!H7-1,"") -> 0.1814346
A9: =Prices!A9 -> 44440 | B9: =IF(AND(ISNUMBER(Prices!B9),ISNUMBER(Prices!B8)),Prices!B9/Prices!B8-1,"") -> 0.022216802 | C9: =IF(AND(ISNUMBER(Prices!C9),ISNUMBER(Prices!C8)),Prices!C9/Prices!C8-1,"") -> -0.080831409 | D9: =IF(AND(ISNUMBER(Prices!D9),ISNUMBER(Prices!D8)),Prices!D9/Prices!D8-1,"") -> 0.06870229 | E9: =IF(AND(ISNUMBER(Prices!E9),ISNUMBER(Prices!E8)),Prices!E9/Prices!E8-1,"") -> 0.0041731873 | F9: =IF(AND(ISNUMBER(Prices!F9),ISNUMBER(Prices!F8)),Prices!F9/Prices!F8-1,"") | G9: =IF(AND(ISNUMBER(Prices!G9),ISNUMBER(Prices!G8)),Prices!G9/Prices!G8-1,"") -> -0.0044444444 | H9: =IF(AND(ISNUMBER(Prices!H9),ISNUMBER(Prices!H8)),Prices!H9/Prices!H8-1,"") -> 0.23928571
A10: =Prices!A10 -> 44470 | B10: =IF(AND(ISNUMBER(Prices!B10),ISNUMBER(Prices!B9)),Prices!B10/Prices!B9-1,"") -> 0.048419422 | C10: =IF(AND(ISNUMBER(Prices!C10),ISNUMBER(Prices!C9)),Prices!C10/Prices!C9-1,"") -> 0.034170854 | D10: =IF(AND(ISNUMBER(Prices!D10),ISNUMBER(Prices!D9)),Prices!D10/Prices!D9-1,"") -> 0.067857143 | E10: =IF(AND(ISNUMBER(Prices!E10),ISNUMBER(Prices!E9)),Prices!E10/Prices!E9-1,"") -> 0.1038961 | F10: =IF(AND(ISNUMBER(Prices!F10),ISNUMBER(Prices!F9)),Prices!F10/Prices!F9-1,"") | G10: =IF(AND(ISNUMBER(Prices!G10),ISNUMBER(Prices!G9)),Prices!G10/Prices!G9-1,"") -> 0.30208333 | H10: =IF(AND(ISNUMBER(Prices!H10),ISNUMBER(Prices!H9)),Prices!H10/Prices!H9-1,"") -> 0.097982709
A11: =Prices!A11 -> 44501 | B11: =IF(AND(ISNUMBER(Prices!B11),ISNUMBER(Prices!B10)),Prices!B11/Prices!B10-1,"") -> -0.0087114172 | C11: =IF(AND(ISNUMBER(Prices!C11),ISNUMBER(Prices!C10)),Prices!C11/Prices!C10-1,"") -> -0.073372206 | D11: =IF(AND(ISNUMBER(Prices!D11),ISNUMBER(Prices!D10)),Prices!D11/Prices!D10-1,"") -> -0.026755853 | E11: =IF(AND(ISNUMBER(Prices!E11),ISNUMBER(Prices!E10)),Prices!E11/Prices!E10-1,"") -> -0.037647059 | F11: =IF(AND(ISNUMBER(Prices!F11),ISNUMBER(Prices!F10)),Prices!F11/Prices!F10-1,"") | G11: =IF(AND(ISNUMBER(Prices!G11),ISNUMBER(Prices!G10)),Prices!G11/Prices!G10-1,"") -> -0.028571429 | H11: =IF(AND(ISNUMBER(Prices!H11),ISNUMBER(Prices!H10)),Prices!H11/Prices!H10-1,"") -> -0.062992126
A12: =Prices!A12 -> 44531 | B12: =IF(AND(ISNUMBER(Prices!B12),ISNUMBER(Prices!B11)),Prices!B12/Prices!B11-1,"") -> 0.0072773966 | C12: =IF(AND(ISNUMBER(Prices!C12),ISNUMBER(Prices!C11)),Prices!C12/Prices!C11-1,"") -> -0.089669638 | D12: =IF(AND(ISNUMBER(Prices!D12),ISNUMBER(Prices!D11)),Prices!D12/Prices!D11-1,"") -> 0.0034364261 | E12: =IF(AND(ISNUMBER(Prices!E12),ISNUMBER(Prices!E11)),Prices!E12/Prices!E11-1,"") -> 0.0048899756 | F12: =IF(AND(ISNUMBER(Prices!F12),ISNUMBER(Prices!F11)),Prices!F12/Prices!F11-1,"") | G12: =IF(AND(ISNUMBER(Prices!G12),ISNUMBER(Prices!G11)),Prices!G12/Prices!G11-1,"") -> -0.0073529412 | H12: =IF(AND(ISNUMBER(Prices!H12),ISNUMBER(Prices!H11)),Prices!H12/Prices!H11-1,"") -> 0.0028011204
A13: =Prices!A13 -> 44562 | B13: =IF(AND(ISNUMBER(Prices!B13),ISNUMBER(Prices!B12)),Prices!B13/Prices!B12-1,"") -> 0.0075469347 | C13: =IF(AND(ISNUMBER(Prices!C13),ISNUMBER(Prices!C12)),Prices!C13/Prices!C12-1,"") -> -0.13191244 | D13: =IF(AND(ISNUMBER(Prices!D13),ISNUMBER(Prices!D12)),Prices!D13/Prices!D12-1,"") -> 0.044520548 | E13: =IF(AND(ISNUMBER(Prices!E13),ISNUMBER(Prices!E12)),Prices!E13/Prices!E12-1,"") -> -0.0097323601 | F13: =IF(AND(ISNUMBER(Prices!F13),ISNUMBER(Prices!F12)),Prices!F13/Prices!F12-1,"") | G13: =IF(AND(ISNUMBER(Prices!G13),ISNUMBER(Prices!G12)),Prices!G13/Prices!G12-1,"") -> 0.085333333 | H13: =IF(AND(ISNUMBER(Prices!H13),ISNUMBER(Prices!H12)),Prices!H13/Prices!H12-1,"") -> -0.027932961
A14: =Prices!A14 -> 44593 | B14: =IF(AND(ISNUMBER(Prices!B14),ISNUMBER(Prices!B13)),Prices!B14/Prices!B13-1,"") -> 0.038759491 | C14: =IF(AND(ISNUMBER(Prices!C14),ISNUMBER(Prices!C13)),Prices!C14/Prices!C13-1,"") -> 0.077637691 | D14: =IF(AND(ISNUMBER(Prices!D14),ISNUMBER(Prices!D13)),Prices!D14/Prices!D13-1,"") -> 0.055737705 | E14: =IF(AND(ISNUMBER(Prices!E14),ISNUMBER(Prices!E13)),Prices!E14/Prices!E13-1,"") -> 0.11793612 | F14: =IF(AND(ISNUMBER(Prices!F14),ISNUMBER(Prices!F13)),Prices!F14/Prices!F13-1,"") | G14: =IF(AND(ISNUMBER(Prices!G14),ISNUMBER(Prices!G13)),Prices!G14/Prices!G13-1,"") -> 0.092001092 | H14: =IF(AND(ISNUMBER(Prices!H14),ISNUMBER(Prices!H13)),Prices!H14/Prices!H13-1,"") -> 0.031609195
... A70: =Prices!A70 -> 46296 | B70: =IF(AND(ISNUMBER(Prices!B70),ISNUMBER(Prices!B69)),Prices!B70/Prices!B69-1,"") -> 0.01255942 | C70: =IF(AND(ISNUMBER(Prices!C70),ISNUMBER(Prices!C69)),Prices!C70/Prices!C69-1,"") -> -0.031690141 | D70: =IF(AND(ISNUMBER(Prices!D70),ISNUMBER(Prices!D69)),Prices!D70/Prices!D69-1,"") -> -0.0041152263 | E70: =IF(AND(ISNUMBER(Prices!E70),ISNUMBER(Prices!E69)),Prices!E70/Prices!E69-1,"") -> 0 | F70: =IF(AND(ISNUMBER(Prices!F70),ISNUMBER(Prices!F69)),Prices!F70/Prices!F69-1,"") -> 0.024937656 | G70: =IF(AND(ISNUMBER(Prices!G70),ISNUMBER(Prices!G69)),Prices!G70/Prices!G69-1,"") -> 0.014749263 | H70: =IF(AND(ISNUMBER(Prices!H70),ISNUMBER(Prices!H69)),Prices!H70/Prices!H69-1,"") -> 0.021276596

Sheet Prices
A1: Month | B1: IHSG | C1: BRIS | D1: BBCA | E1: BBRI | F1: BMRI | G1: BBNI | H1: BTPS
A2: 44228 | B2: 6241.8 | C2: 2867 | D2: 6710 | E2: 4595 | G2: 2975 | H2: 4100
A3: 44256 | B3: 5985.52 | C3: 2233 | D3: 6215 | E3: 4293 | G3: 2863 | H3: 3480
A4: 44287 | B4: 5995.62 | C4: 2224 | D4: 6405 | E4: 3951 | G4: 2850 | H4: 3270
A5: 44317 | B5: 5947.46 | C5: 1858 | D5: 6375 | E5: 4156 | G5: 2700 | H5: 2900
A6: 44348 | B6: 5985.49 | C6: 2243 | D6: 6025 | E6: 3844 | G6: 2315 | H6: 2880
A7: 44378 | B7: 6070.04 | C7: 2565 | D7: 5970 | E7: 3620 | G7: 2390 | H7: 2370
A8: 44409 | B8: 6150.3 | C8: 2165 | D8: 6550 | E8: 3834 | G8: 2700 | H8: 2800
A9: 44440 | B9: 6286.94 | C9: 1990 | D9: 7000 | E9: 3850 | G9: 2688 | H9: 3470
A10: 44470 | B10: 6591.35 | C10: 2058 | D10: 7475 | E10: 4250 | G10: 3500 | H10: 3810
A11: 44501 | B11: 6533.93 | C11: 1907 | D11: 7275 | E11: 4090 | G11: 3400 | H11: 3570
A12: 44531 | B12: 6581.48 | C12: 1736 | D12: 7300 | E12: 4110 | G12: 3375 | H12: 3580
A13: 44562 | B13: 6631.15 | C13: 1507 | D13: 7625 | E13: 4070 | G13: 3663 | H13: 3480
... A46: 45566 | B46: 7574.02 | C46: 3030 | D46: 10250 | E46: 4800 | G46: 5250 | H46: 1065
A47: 45597 | B47: 7114.27 | C47: 2900 | D47: 10000 | E47: 4250 | F47: 6150 | G47: 4980 | H47: 910
A48: 45627 | B48: 7079.9 | C48: 2730 | D48: 9675 | E48: 4080 | F48: 5700 | G48: 4350 | H48: 925
A49: 45658 | B49: 7109.2 | C49: 2930 | D49: 9450 | E49: 4220 | F49: 6025 | G49: 4770 | H49: 925
A50: 45689 | B50: 6270.6 | C50: 2500 | D50: 8425 | E50: 3360 | F50: 4600 | G50: 4030 | H50: 875
A51: 45717 | B51: 6510.62 | C51: 2340 | D51: 8500 | E51: 4050 | F51: 5200 | G51: 4240 | H51: 905
A52: 45748 | B52: 6766.79 | C52: 2850 | D52: 8825 | E52: 3850 | F52: 4890 | G52: 4180 | H52: 1185
A53: 45778 | B53: 7175.82 | C53: 3000 | D53: 9400 | E53: 4450 | F53: 5300 | G53: 4490 | H53: 1295
A54: 45809 | B54: 6927.68 | C54: 2580 | D54: 8675 | E54: 3740 | F54: 4880 | G54: 4120 | H54: 1315
A55: 45839 | B55: 7484.34 | C55: 2730 | D55: 8275 | E55: 3710 | F55: 4510 | G55: 4010 | H55: 1410
A56: 45870 | B56: 7830.49 | C56: 2710 | D56: 8075 | E56: 4050 | F56: 4730 | G56: 4380 | H56: 1490
A57: 45901 | B57: 8061.06 | C57: 2590 | D57: 7625 | E57: 3900 | F57: 4400 | G57: 4100 | H57: 1350
A58: 45931 | B58: 8163.88 | C58: 2550 | D58: 8525 | E58: 3980 | F58: 4720 | G58: 4380 | H58: 1370
... A70: 46296 | B70: 6147.39 | C70: 1375 | D70: 6050 | E70: 3140 | F70: 4110 | G70: 3440 | H70: 960
A72: Source: Investing.com monthly history (Terakhir = month close), uploaded by user. Oct-26 is partial month (to 7 Oct 2026). BMRI file has only Nov-24 onward.

Sheet Change_Log
A1: Change log
A2: One line per version; detail lives in the sheets themselves.
A4: Version | B4: Date | C4: Change
A5: v4.0 | B5: 10-Oct-2026 | C5: Fixes to Quick FM (Alip): ratio-driven securities, CFS-driven cash, direct cash flow sheet, rf net of default spread, CRP counted once, specific premium and scenario Ke adders set to 0, GWM and CF tie checks.
A6: v4.0 | B6: 1 | C6: (1) direct cash flow sheet CF_Direct; (2) securities no longer the balancing plug, cash = CFS closing cash, genuine balance check + GWM check (row 383) + CF tie check (row 384); (3) rf net of sovereign spread, size premium and scenario Ke adders set to 0; (4) probabilities linked to Prob_Justification; (5) Input_Register added.
A7: v5.0 | B7: 11-Oct-2026 | C7: merged team analysis into the Quick FM engine. Beta (E35) now linked to Beta_Evidence. Sheet README lists every sheet, source and open decision.
A8: v6.0 | B8: 17-Oct-2026 | C8: added Valuation_Detail (outputs, relative valuation, football field, beta x ROE grid) and Driver_Check. No input changed, so snapshots 4h/4i remain valid.
A9: v7.0 | B9: 17-Oct-2026 | C9: added Model_Comparison and, in Valuation_Detail, banking FCFE, justified and exit P/B cross-checks, composite view and Ke x g grid, adopted from the second model. No input of the engine changed.
A10: v8.0 | B10: 17-Oct-2026 | C10: Base CIR FY26E 52.5% -> 54.5% (Bear 55.5%, Bull 53.5%) following 2H25 and 1H26 evidence; scenario, tornado and beta snapshots regenerated; Dashboard sheet added.
A11: v8.1 | B11: 17-Oct-2026 | C11: price updated to 1,095 (close 16-Oct-26). Upside snapshot row 467 now formula-driven. Rights issue price placeholder (E146 = 1,150) now sits above market and needs review.
A12: v9.0 | B12: 17-Oct-2026 | C12: terminal ROE = Ke + spread (row 50: Bear 0, Base 2pp, Bull 4pp). DDM terminal DPS = payout x ROE_T x BV35; RI terminal = BV35 x (ROE_T - Ke)/(Ke - g); omega fade retired. DDM = RI, master check OK. Snapshots regenerated.
A13: v10.0 | B13: 17-Oct-2026 | C13: History FY21A-FY25A synced to the annual reports (income statement, regulatory capital, RWA); regulatory minimum CAR 13.49% (AR2025); peers moved to a trailing basis (StockAnalysis, 16-Oct-26 closes; BTPS removed); 1H26 net profit and equity from the interim statement; rights-issue price placeholder tied to the latest close; duplicate sheets removed (Valuation_Detail, Model_Comparison, Reconciliation, Fix_Log) and cross-checks moved to Valuation_Checks; Damodaran_Audit section 2 removed (duplicate of Terminal_ROE); 11 broken charts replaced with live charts; fonts, titles and tab colours unified; snapshots regenerated.
A14: v11.0 | B14: 17-Oct-2026 | C14: Cost of equity: raw-beta selector (Beta_Evidence B38), country risk added in full (lambda = 1, B41), beta converging to 1.0 by FY35E (B42), yearly Ke in Sheet1 row 389; terminal ROE = stable Ke + spread. Target price = 2/3 intrinsic (DDM = RI) + 1/3 relative valuation (Sheet1 E38, E422), reflecting the MSCI consultation on Standalone status (15 Oct 2026). Terminal_ROE anchors realigned; Valuation_Checks section 4 adds the weight sensitivity; snapshots regenerated.
A15: v11.1 | B15: 17-Oct-2026 | C15: Formatted layout adopted. Sheet1 duplicates removed (825 to 480 rows): control panel (= Dashboard section 1), retired omega inputs and grid, Ke x g grid (moved to Valuation_Checks section 3 on the yearly-Ke basis), chart data and charts moved to sheet Charts, notes moved to README. Values unchanged.
A16: v11.2 | B16: 17-Oct-2026 | C16: Peer table re-based on 1H26 filings (BBRI, BBCA presentations; BMRI, BBNI 1H26; BTPS Q2-26 publication), annualised 1H26 earnings, Jun-26 book value; BTPS added at user-supplied close Rp880 (16-Oct-26). Relative value 1,216 to 1,142; 12m Base PT 1,909 to 1,881; prob-weighted 1,855. Scenario, tornado and beta snapshots regenerated. Open: peer closes, BTPS shares (par assumption), BBCA rounded figures.

Sheet 00_Dashboard
A1: BSI / BRIS | 00 Dashboard
A3: Investment overview and outputs | Linked to original calculation engine; source inputs unchanged
B5: Metric / source location | C5: Unit | D5: Original cell | E5: =Sheet1!E40 -> FY21A | F5: =Sheet1!F40 -> FY22A | G5: =Sheet1!G40 -> FY23A | H5: =Sheet1!H40 -> FY24A | I5: =Sheet1!I40 -> FY25A | J5: =Sheet1!J40 -> FY26E | K5: =Sheet1!K40 -> FY27E | L5: =Sheet1!L40 -> FY28E | ... S5: =Sheet1!S40 -> FY35E
B6: DECISION & MARKET
B7: Current share price | D7: Sheet1!B20:S20 | E7: =IF(Sheet1!E20="","",Sheet1!E20) -> 1095 | F7: =IF(Sheet1!F20="","",Sheet1!F20) | G7: =IF(Sheet1!G20="","",Sheet1!G20) | H7: =IF(Sheet1!H20="","",Sheet1!H20) | I7: =IF(Sheet1!I20="","",Sheet1!I20) | J7: =IF(Sheet1!J20="","",Sheet1!J20) | K7: =IF(Sheet1!K20="","",Sheet1!K20) | L7: =IF(Sheet1!L20="","",Sheet1!L20) | ... S7: =IF(Sheet1!S20="","",Sheet1!S20)
B8: Shares outstanding (pre rights issue) | D8: Sheet1!B21:S21 | E8: =IF(Sheet1!E21="","",Sheet1!E21) -> 46129.26 | F8: =IF(Sheet1!F21="","",Sheet1!F21) | G8: =IF(Sheet1!G21="","",Sheet1!G21) | H8: =IF(Sheet1!H21="","",Sheet1!H21) | I8: =IF(Sheet1!I21="","",Sheet1!I21) | J8: =IF(Sheet1!J21="","",Sheet1!J21) | K8: =IF(Sheet1!K21="","",Sheet1!K21) | L8: =IF(Sheet1!L21="","",Sheet1!L21) | ... S8: =IF(Sheet1!S21="","",Sheet1!S21)
B9: Valuation date | D9: Sheet1!B22:S22 | E9: =IF(Sheet1!E22="","",Sheet1!E22) -> 46304 | F9: =IF(Sheet1!F22="","",Sheet1!F22) | G9: =IF(Sheet1!G22="","",Sheet1!G22) | H9: =IF(Sheet1!H22="","",Sheet1!H22) | I9: =IF(Sheet1!I22="","",Sheet1!I22) | J9: =IF(Sheet1!J22="","",Sheet1!J22) | K9: =IF(Sheet1!K22="","",Sheet1!K22) | L9: =IF(Sheet1!L22="","",Sheet1!L22) | ... S9: =IF(Sheet1!S22="","",Sheet1!S22)
B10: Cost of equity year 1 (method per Beta_Evidence B41) | D10: Sheet1!B28:S28 | E10: =IF(Sheet1!E28="","",Sheet1!E28) -> 0.11229724 | F10: =IF(Sheet1!F28="","",Sheet1!F28) | G10: =IF(Sheet1!G28="","",Sheet1!G28) | H10: =IF(Sheet1!H28="","",Sheet1!H28) | I10: =IF(Sheet1!I28="","",Sheet1!I28) | J10: =IF(Sheet1!J28="","",Sheet1!J28) | K10: =IF(Sheet1!K28="","",Sheet1!K28) | L10: =IF(Sheet1!L28="","",Sheet1!L28) | ... S10: =IF(Sheet1!S28="","",Sheet1!S28)
B11: Cost of equity year 1 (live); yearly path in row 378 | D11: Sheet1!B34:S34 | E11: =IF(Sheet1!E34="","",Sheet1!E34) -> 0.11229724 | F11: =IF(Sheet1!F34="","",Sheet1!F34) | G11: =IF(Sheet1!G34="","",Sheet1!G34) | H11: =IF(Sheet1!H34="","",Sheet1!H34) | I11: =IF(Sheet1!I34="","",Sheet1!I34) | J11: =IF(Sheet1!J34="","",Sheet1!J34) | K11: =IF(Sheet1!K34="","",Sheet1!K34) | L11: =IF(Sheet1!L34="","",Sheet1!L34) | ... S11: =IF(Sheet1!S34="","",Sheet1!S34)
B12: Target CAR (internal floor) | D12: Sheet1!B35:S35 | E12: =IF(Sheet1!E35="","",Sheet1!E35) -> 0.2 | F12: =IF(Sheet1!F35="","",Sheet1!F35) | G12: =IF(Sheet1!G35="","",Sheet1!G35) | H12: =IF(Sheet1!H35="","",Sheet1!H35) | I12: =IF(Sheet1!I35="","",Sheet1!I35) | J12: =IF(Sheet1!J35="","",Sheet1!J35) | K12: =IF(Sheet1!K35="","",Sheet1!K35) | L12: =IF(Sheet1!L35="","",Sheet1!L35) | ... S12: =IF(Sheet1!S35="","",Sheet1!S35)
B13: TARGET VALUATION
B14: DDM value at valuation date | D14: Sheet1!B402:S402 | E14: =IF(Sheet1!E402="","",Sheet1!E402) -> 2019.8393 | F14: =IF(Sheet1!F402="","",Sheet1!F402) | G14: =IF(Sheet1!G402="","",Sheet1!G402) | H14: =IF(Sheet1!H402="","",Sheet1!H402) | I14: =IF(Sheet1!I402="","",Sheet1!I402) | J14: =IF(Sheet1!J402="","",Sheet1!J402) | K14: =IF(Sheet1!K402="","",Sheet1!K402) | L14: =IF(Sheet1!L402="","",Sheet1!L402) | ... S14: =IF(Sheet1!S402="","",Sheet1!S402)
B15: RI value at valuation date | D15: Sheet1!B403:S403 | E15: =IF(Sheet1!E403="","",Sheet1!E403) -> 2019.8393 | F15: =IF(Sheet1!F403="","",Sheet1!F403) | G15: =IF(Sheet1!G403="","",Sheet1!G403) | H15: =IF(Sheet1!H403="","",Sheet1!H403) | I15: =IF(Sheet1!I403="","",Sheet1!I403) | J15: =IF(Sheet1!J403="","",Sheet1!J403) | K15: =IF(Sheet1!K403="","",Sheet1!K403) | L15: =IF(Sheet1!L403="","",Sheet1!L403) | ... S15: =IF(Sheet1!S403="","",Sheet1!S403)
B16: 12m target price - DDM | D16: Sheet1!B404:S404 | E16: =IF(Sheet1!E404="","",Sheet1!E404) -> 2206.4988 | F16: =IF(Sheet1!F404="","",Sheet1!F404) | G16: =IF(Sheet1!G404="","",Sheet1!G404) | H16: =IF(Sheet1!H404="","",Sheet1!H404) | I16: =IF(Sheet1!I404="","",Sheet1!I404) | J16: =IF(Sheet1!J404="","",Sheet1!J404) | K16: =IF(Sheet1!K404="","",Sheet1!K404) | L16: =IF(Sheet1!L404="","",Sheet1!L404) | ... S16: =IF(Sheet1!S404="","",Sheet1!S404)
B17: 12m target price - RI | D17: Sheet1!B405:S405 | E17: =IF(Sheet1!E405="","",Sheet1!E405) -> 2206.4988 | F17: =IF(Sheet1!F405="","",Sheet1!F405) | G17: =IF(Sheet1!G405="","",Sheet1!G405) | H17: =IF(Sheet1!H405="","",Sheet1!H405) | I17: =IF(Sheet1!I405="","",Sheet1!I405) | J17: =IF(Sheet1!J405="","",Sheet1!J405) | K17: =IF(Sheet1!K405="","",Sheet1!K405) | L17: =IF(Sheet1!L405="","",Sheet1!L405) | ... S17: =IF(Sheet1!S405="","",Sheet1!S405)
B18: 12m TARGET PRICE (intrinsic and relative blend, weight E29) | D18: Sheet1!B406:S406 | E18: =IF(Sheet1!E406="","",Sheet1!E406) -> 1881.1248 | F18: =IF(Sheet1!F406="","",Sheet1!F406) | G18: =IF(Sheet1!G406="","",Sheet1!G406) | H18: =IF(Sheet1!H406="","",Sheet1!H406) | I18: =IF(Sheet1!I406="","",Sheet1!I406) | J18: =IF(Sheet1!J406="","",Sheet1!J406) | K18: =IF(Sheet1!K406="","",Sheet1!K406) | L18: =IF(Sheet1!L406="","",Sheet1!L406) | ... S18: =IF(Sheet1!S406="","",Sheet1!S406)
B19: Upside / (downside) vs current price | D19: Sheet1!B407:S407 | E19: =IF(Sheet1!E407="","",Sheet1!E407) -> 0.71792219 | F19: =IF(Sheet1!F407="","",Sheet1!F407) | G19: =IF(Sheet1!G407="","",Sheet1!G407) | H19: =IF(Sheet1!H407="","",Sheet1!H407) | I19: =IF(Sheet1!I407="","",Sheet1!I407) | J19: =IF(Sheet1!J407="","",Sheet1!J407) | K19: =IF(Sheet1!K407="","",Sheet1!K407) | L19: =IF(Sheet1!L407="","",Sheet1!L407) | ... S19: =IF(Sheet1!S407="","",Sheet1!S407)
B20: Rating | D20: Sheet1!B408:S408 | E20: =IF(Sheet1!E408="","",Sheet1!E408) -> BUY | F20: =IF(Sheet1!F408="","",Sheet1!F408) | G20: =IF(Sheet1!G408="","",Sheet1!G408) | H20: =IF(Sheet1!H408="","",Sheet1!H408) | I20: =IF(Sheet1!I408="","",Sheet1!I408) | J20: =IF(Sheet1!J408="","",Sheet1!J408) | K20: =IF(Sheet1!K408="","",Sheet1!K408) | L20: =IF(Sheet1!L408="","",Sheet1!L408) | ... S20: =IF(Sheet1!S408="","",Sheet1!S408)
B21: Implied P/B at PT (FY26E BVPS) | D21: Sheet1!B409:S409 | E21: =IF(Sheet1!E409="","",Sheet1!E409) -> 1.4742427 | F21: =IF(Sheet1!F409="","",Sheet1!F409) | G21: =IF(Sheet1!G409="","",Sheet1!G409) | H21: =IF(Sheet1!H409="","",Sheet1!H409) | I21: =IF(Sheet1!I409="","",Sheet1!I409) | J21: =IF(Sheet1!J409="","",Sheet1!J409) | K21: =IF(Sheet1!K409="","",Sheet1!K409) | L21: =IF(Sheet1!L409="","",Sheet1!L409) | ... S21: =IF(Sheet1!S409="","",Sheet1!S409)
B22: Implied P/E at PT (FY27E EPS) | D22: Sheet1!B410:S410 | E22: =IF(Sheet1!E410="","",Sheet1!E410) -> 8.9744506 | F22: =IF(Sheet1!F410="","",Sheet1!F410) | G22: =IF(Sheet1!G410="","",Sheet1!G410) | H22: =IF(Sheet1!H410="","",Sheet1!H410) | I22: =IF(Sheet1!I410="","",Sheet1!I410) | J22: =IF(Sheet1!J410="","",Sheet1!J410) | K22: =IF(Sheet1!K410="","",Sheet1!K410) | L22: =IF(Sheet1!L410="","",Sheet1!L410) | ... S22: =IF(Sheet1!S410="","",Sheet1!S410)
B23: Relative value per share today = P/B share x P/B-implied + rest x P/E-implied | D23: Sheet1!B411:S411 | E23: =IF(Sheet1!E411="","",Sheet1!E411) -> 1142.2663 | F23: =IF(Sheet1!F411="","",Sheet1!F411) -> 0.7 | G23: =IF(Sheet1!G411="","",Sheet1!G411) | H23: =IF(Sheet1!H411="","",Sheet1!H411) | I23: =IF(Sheet1!I411="","",Sheet1!I411) | J23: =IF(Sheet1!J411="","",Sheet1!J411) | K23: =IF(Sheet1!K411="","",Sheet1!K411) | L23: =IF(Sheet1!L411="","",Sheet1!L411) | ... S23: =IF(Sheet1!S411="","",Sheet1!S411)
B24: ECONOMIC PERFORMANCE
B25: Tax & other (net, incl. non-operating) | D25: Sheet1!B153:S153 | E25: =IF(Sheet1!E153="","",Sheet1!E153) -> 1079.644 | F25: =IF(Sheet1!F153="","",Sheet1!F153) -> 1387.674 | G25: =IF(Sheet1!G153="","",Sheet1!G153) -> 1887.615 | H25: =IF(Sheet1!H153="","",Sheet1!H153) -> 2272.256 | I25: =IF(Sheet1!I153="","",Sheet1!I153) -> 2440.494 | J25: =IF(Sheet1!J153="","",Sheet1!J153) -> 2744.2647 | K25: =IF(Sheet1!K153="","",Sheet1!K153) -> 3383.1334 | L25: =IF(Sheet1!L153="","",Sheet1!L153) -> 3933.386 | ... S25: =IF(Sheet1!S153="","",Sheet1!S153) -> 7329.1398
B26: TOTAL ASSETS | D26: Sheet1!B169:S169 | E26: =IF(Sheet1!E169="","",Sheet1!E169) -> 265289 | F26: =IF(Sheet1!F169="","",Sheet1!F169) -> 305727 | G26: =IF(Sheet1!G169="","",Sheet1!G169) -> 353624 | H26: =IF(Sheet1!H169="","",Sheet1!H169) -> 408613 | I26: =IF(Sheet1!I169="","",Sheet1!I169) -> 456193 | J26: =IF(Sheet1!J169="","",Sheet1!J169) -> 512440.96 | K26: =IF(Sheet1!K169="","",Sheet1!K169) -> 580330.33 | L26: =IF(Sheet1!L169="","",Sheet1!L169) -> 641717 | ... S26: =IF(Sheet1!S169="","",Sheet1!S169) -> 1139887.2
B27: (-) Increase in other assets | D27: Sheet1!B187:S187 | E27: =IF(Sheet1!E187="","",Sheet1!E187) | F27: =IF(Sheet1!F187="","",Sheet1!F187) | G27: =IF(Sheet1!G187="","",Sheet1!G187) | H27: =IF(Sheet1!H187="","",Sheet1!H187) | I27: =IF(Sheet1!I187="","",Sheet1!I187) | J27: =IF(Sheet1!J187="","",Sheet1!J187) -> -1330.5377 | K27: =IF(Sheet1!K187="","",Sheet1!K187) -> -1763.4714 | L27: =IF(Sheet1!L187="","",Sheet1!L187) -> -1779.1814 | ... S27: =IF(Sheet1!S187="","",Sheet1!S187) -> -1669.6974
B28: CAR - reported | D28: Sheet1!B315:S315 | E28: =IF(Sheet1!E315="","",Sheet1!E315) -> 0.2209 | F28: =IF(Sheet1!F315="","",Sheet1!F315) -> 0.2029 | G28: =IF(Sheet1!G315="","",Sheet1!G315) -> 0.2104 | H28: =IF(Sheet1!H315="","",Sheet1!H315) -> 0.214 | I28: =IF(Sheet1!I315="","",Sheet1!I315) -> 0.22 | J28: =IF(Sheet1!J315="","",Sheet1!J315) | K28: =IF(Sheet1!K315="","",Sheet1!K315) | L28: =IF(Sheet1!L315="","",Sheet1!L315) | ... S28: =IF(Sheet1!S315="","",Sheet1!S315)
B29: CAR (model) | D29: Sheet1!B328:S328 | E29: =IF(Sheet1!E328="","",Sheet1!E328) -> 0.22086522 | F29: =IF(Sheet1!F328="","",Sheet1!F328) -> 0.20293206 | G29: =IF(Sheet1!G328="","",Sheet1!G328) -> 0.21044249 | H29: =IF(Sheet1!H328="","",Sheet1!H328) -> 0.21403664 | I29: =IF(Sheet1!I328="","",Sheet1!I328) -> 0.21996525 | J29: =IF(Sheet1!J328="","",Sheet1!J328) -> 0.22000884 | K29: =IF(Sheet1!K328="","",Sheet1!K328) -> 0.24524347 | L29: =IF(Sheet1!L328="","",Sheet1!L328) -> 0.24758547 | ... S29: =IF(Sheet1!S328="","",Sheet1!S328) -> 0.26696653
B30: ROA (avg assets) | D30: Sheet1!B346:S346 | E30: =IF(Sheet1!E346="","",Sheet1!E346) | F30: =IF(Sheet1!F346="","",Sheet1!F346) -> 0.014920773 | G30: =IF(Sheet1!G346="","",Sheet1!G346) -> 0.017301082 | H30: =IF(Sheet1!H346="","",Sheet1!H346) -> 0.01838244 | I30: =IF(Sheet1!I346="","",Sheet1!I346) -> 0.017501088 | J30: =IF(Sheet1!J346="","",Sheet1!J346) -> 0.017387965 | K30: =IF(Sheet1!K346="","",Sheet1!K346) -> 0.019000818 | L30: =IF(Sheet1!L346="","",Sheet1!L346) -> 0.019754271 | ... S30: =IF(Sheet1!S346="","",Sheet1!S346) -> 0.020343768
B31: ROE (avg common equity) | D31: Sheet1!B347:S347 | E31: =IF(Sheet1!E347="","",Sheet1!E347) | F31: =IF(Sheet1!F347="","",Sheet1!F347) -> 0.14559142 | G31: =IF(Sheet1!G347="","",Sheet1!G347) -> 0.15789974 | H31: =IF(Sheet1!H347="","",Sheet1!H347) -> 0.1672435 | I31: =IF(Sheet1!I347="","",Sheet1!I347) -> 0.15604034 | J31: =IF(Sheet1!J347="","",Sheet1!J347) -> 0.15199023 | K31: =IF(Sheet1!K347="","",Sheet1!K347) -> 0.15653779 | L31: =IF(Sheet1!L347="","",Sheet1!L347) -> 0.15372455 | ... S31: =IF(Sheet1!S347="","",Sheet1!S347) -> 0.14619715
B32: EPS (avg shares) | D32: Sheet1!B350:S350 | E32: =IF(Sheet1!E350="","",Sheet1!E350) -> 73.626453 | F32: =IF(Sheet1!F350="","",Sheet1!F350) -> 92.349194 | G32: =IF(Sheet1!G350="","",Sheet1!G350) -> 123.64697 | H32: =IF(Sheet1!H350="","",Sheet1!H350) -> 151.87514 | I32: =IF(Sheet1!I350="","",Sheet1!I350) -> 164.05039 | J32: =IF(Sheet1!J350="","",Sheet1!J350) -> 182.55846 | K32: =IF(Sheet1!K350="","",Sheet1!K350) -> 209.60891 | L32: =IF(Sheet1!L350="","",Sheet1!L350) -> 228.04639 | ... S32: =IF(Sheet1!S350="","",Sheet1!S350) -> 424.92242
B33: BVPS (period-end shares) | D33: Sheet1!B351:S351 | E33: =IF(Sheet1!E351="","",Sheet1!E351) -> 608.17786 | F33: =IF(Sheet1!F351="","",Sheet1!F351) -> 726.35026 | G33: =IF(Sheet1!G351="","",Sheet1!G351) -> 839.79498 | H33: =IF(Sheet1!H351="","",Sheet1!H351) -> 976.42087 | I33: =IF(Sheet1!I351="","",Sheet1!I351) -> 1126.2456 | J33: =IF(Sheet1!J351="","",Sheet1!J351) -> 1275.9939 | K33: =IF(Sheet1!K351="","",Sheet1!K351) -> 1393.969 | L33: =IF(Sheet1!L351="","",Sheet1!L351) -> 1572.9793 | ... S33: =IF(Sheet1!S351="","",Sheet1!S351) -> 2999.7819

Sheet 01_Sources_Control
A1: BSI / BRIS | 01 Sources Control
A3: Original source and research flags | Linked to original calculation engine; source inputs unchanged
B5: Metric / source location | C5: Unit | D5: Original cell | E5: =Sheet1!E40 -> FY21A | F5: =Sheet1!F40 -> FY22A | G5: =Sheet1!G40 -> FY23A | H5: =Sheet1!H40 -> FY24A | I5: =Sheet1!I40 -> FY25A | J5: =Sheet1!J40 -> FY26E | K5: =Sheet1!K40 -> FY27E | L5: =Sheet1!L40 -> FY28E | ... S5: =Sheet1!S40 -> FY35E
B6: SOURCE REGISTER / KEY CONTROLS
B7: Current share price | D7: Sheet1!B20:S20 | E7: =IF(Sheet1!E20="","",Sheet1!E20) -> 1095 | F7: =IF(Sheet1!F20="","",Sheet1!F20) | G7: =IF(Sheet1!G20="","",Sheet1!G20) | H7: =IF(Sheet1!H20="","",Sheet1!H20) | I7: =IF(Sheet1!I20="","",Sheet1!I20) | J7: =IF(Sheet1!J20="","",Sheet1!J20) | K7: =IF(Sheet1!K20="","",Sheet1!K20) | L7: =IF(Sheet1!L20="","",Sheet1!L20) | ... S7: =IF(Sheet1!S20="","",Sheet1!S20)
B8: Shares outstanding (pre rights issue) | D8: Sheet1!B21:S21 | E8: =IF(Sheet1!E21="","",Sheet1!E21) -> 46129.26 | F8: =IF(Sheet1!F21="","",Sheet1!F21) | G8: =IF(Sheet1!G21="","",Sheet1!G21) | H8: =IF(Sheet1!H21="","",Sheet1!H21) | I8: =IF(Sheet1!I21="","",Sheet1!I21) | J8: =IF(Sheet1!J21="","",Sheet1!J21) | K8: =IF(Sheet1!K21="","",Sheet1!K21) | L8: =IF(Sheet1!L21="","",Sheet1!L21) | ... S8: =IF(Sheet1!S21="","",Sheet1!S21)
B9: Valuation date | D9: Sheet1!B22:S22 | E9: =IF(Sheet1!E22="","",Sheet1!E22) -> 46304 | F9: =IF(Sheet1!F22="","",Sheet1!F22) | G9: =IF(Sheet1!G22="","",Sheet1!G22) | H9: =IF(Sheet1!H22="","",Sheet1!H22) | I9: =IF(Sheet1!I22="","",Sheet1!I22) | J9: =IF(Sheet1!J22="","",Sheet1!J22) | K9: =IF(Sheet1!K22="","",Sheet1!K22) | L9: =IF(Sheet1!L22="","",Sheet1!L22) | ... S9: =IF(Sheet1!S22="","",Sheet1!S22)
B10: FY25 dividend payment date (paid in FY26) | D10: Sheet1!B23:S23 | E10: =IF(Sheet1!E23="","",Sheet1!E23) -> 46178 | F10: =IF(Sheet1!F23="","",Sheet1!F23) | G10: =IF(Sheet1!G23="","",Sheet1!G23) | H10: =IF(Sheet1!H23="","",Sheet1!H23) | I10: =IF(Sheet1!I23="","",Sheet1!I23) | J10: =IF(Sheet1!J23="","",Sheet1!J23) | K10: =IF(Sheet1!K23="","",Sheet1!K23) | L10: =IF(Sheet1!L23="","",Sheet1!L23) | ... S10: =IF(Sheet1!S23="","",Sheet1!S23)
B11: Risk-free rate, IDR (10Y INDOGB less sovereign default spread) | D11: Sheet1!B24:S24 | E11: =IF(Sheet1!E24="","",Sheet1!E24) -> 0.0556 | F11: =IF(Sheet1!F24="","",Sheet1!F24) -> gross / spread | G11: =IF(Sheet1!G24="","",Sheet1!G24) -> 0.0718 | H11: =IF(Sheet1!H24="","",Sheet1!H24) -> 0.0162 | I11: =IF(Sheet1!I24="","",Sheet1!I24) | J11: =IF(Sheet1!J24="","",Sheet1!J24) | K11: =IF(Sheet1!K24="","",Sheet1!K24) | L11: =IF(Sheet1!L24="","",Sheet1!L24) | ... S11: =IF(Sheet1!S24="","",Sheet1!S24)
B12: Equity risk premium (Indonesia) | D12: Sheet1!B25:S25 | E12: =IF(Sheet1!E25="","",Sheet1!E25) -> 0.0669 | F12: =IF(Sheet1!F25="","",Sheet1!F25) | G12: =IF(Sheet1!G25="","",Sheet1!G25) | H12: =IF(Sheet1!H25="","",Sheet1!H25) | I12: =IF(Sheet1!I25="","",Sheet1!I25) | J12: =IF(Sheet1!J25="","",Sheet1!J25) | K12: =IF(Sheet1!K25="","",Sheet1!K25) | L12: =IF(Sheet1!L25="","",Sheet1!L25) | ... S12: =IF(Sheet1!S25="","",Sheet1!S25)
B13: Beta, Blume-adjusted year 1 (raw beta chosen in Beta_Evidence B38) | D13: Sheet1!B26:S26 | E13: =IF(Sheet1!E26="","",Sheet1!E26) -> 0.7588 | F13: =IF(Sheet1!F26="","",Sheet1!F26) | G13: =IF(Sheet1!G26="","",Sheet1!G26) | H13: =IF(Sheet1!H26="","",Sheet1!H26) | I13: =IF(Sheet1!I26="","",Sheet1!I26) | J13: =IF(Sheet1!J26="","",Sheet1!J26) | K13: =IF(Sheet1!K26="","",Sheet1!K26) | L13: =IF(Sheet1!L26="","",Sheet1!L26) | ... S13: =IF(Sheet1!S26="","",Sheet1!S26)
B14: Size / liquidity premium | D14: Sheet1!B27:S27 | E14: =IF(Sheet1!E27="","",Sheet1!E27) -> 0 | F14: =IF(Sheet1!F27="","",Sheet1!F27) | G14: =IF(Sheet1!G27="","",Sheet1!G27) | H14: =IF(Sheet1!H27="","",Sheet1!H27) | I14: =IF(Sheet1!I27="","",Sheet1!I27) | J14: =IF(Sheet1!J27="","",Sheet1!J27) | K14: =IF(Sheet1!K27="","",Sheet1!K27) | L14: =IF(Sheet1!L27="","",Sheet1!L27) | ... S14: =IF(Sheet1!S27="","",Sheet1!S27)
B15: Weight on relative valuation in the 12m target price (rest = DDM = RI) | D15: Sheet1!B29:S29 | E15: =IF(Sheet1!E29="","",Sheet1!E29) -> 0.33333333 | F15: =IF(Sheet1!F29="","",Sheet1!F29) | G15: =IF(Sheet1!G29="","",Sheet1!G29) | H15: =IF(Sheet1!H29="","",Sheet1!H29) | I15: =IF(Sheet1!I29="","",Sheet1!I29) | J15: =IF(Sheet1!J29="","",Sheet1!J29) | K15: =IF(Sheet1!K29="","",Sheet1!K29) | L15: =IF(Sheet1!L29="","",Sheet1!L29) | ... S15: =IF(Sheet1!S29="","",Sheet1!S29)
B16: Terminal growth (g) - Bear / Base / Bull | D16: Sheet1!B30:S30 | E16: =IF(Sheet1!E30="","",Sheet1!E30) -> 0.04 | F16: =IF(Sheet1!F30="","",Sheet1!F30) -> 0.045 | G16: =IF(Sheet1!G30="","",Sheet1!G30) -> 0.05 | H16: =IF(Sheet1!H30="","",Sheet1!H30) | I16: =IF(Sheet1!I30="","",Sheet1!I30) | J16: =IF(Sheet1!J30="","",Sheet1!J30) | K16: =IF(Sheet1!K30="","",Sheet1!K30) | L16: =IF(Sheet1!L30="","",Sheet1!L30) | ... S16: =IF(Sheet1!S30="","",Sheet1!S30)
B17: Terminal growth (g) (live) | D17: Sheet1!B31:S31 | E17: =IF(Sheet1!E31="","",Sheet1!E31) -> 0.045 | F17: =IF(Sheet1!F31="","",Sheet1!F31) | G17: =IF(Sheet1!G31="","",Sheet1!G31) | H17: =IF(Sheet1!H31="","",Sheet1!H31) | I17: =IF(Sheet1!I31="","",Sheet1!I31) | J17: =IF(Sheet1!J31="","",Sheet1!J31) | K17: =IF(Sheet1!K31="","",Sheet1!K31) | L17: =IF(Sheet1!L31="","",Sheet1!L31) | ... S17: =IF(Sheet1!S31="","",Sheet1!S31)
B18: Scenario CoE adder - Bear / Base / Bull | D18: Sheet1!B32:S32 | E18: =IF(Sheet1!E32="","",Sheet1!E32) -> 0 | F18: =IF(Sheet1!F32="","",Sheet1!F32) -> 0 | G18: =IF(Sheet1!G32="","",Sheet1!G32) -> 0 | H18: =IF(Sheet1!H32="","",Sheet1!H32) | I18: =IF(Sheet1!I32="","",Sheet1!I32) | J18: =IF(Sheet1!J32="","",Sheet1!J32) | K18: =IF(Sheet1!K32="","",Sheet1!K32) | L18: =IF(Sheet1!L32="","",Sheet1!L32) | ... S18: =IF(Sheet1!S32="","",Sheet1!S32)
B19: Scenario CoE adder (live) | D19: Sheet1!B33:S33 | E19: =IF(Sheet1!E33="","",Sheet1!E33) -> 0 | F19: =IF(Sheet1!F33="","",Sheet1!F33) | G19: =IF(Sheet1!G33="","",Sheet1!G33) | H19: =IF(Sheet1!H33="","",Sheet1!H33) | I19: =IF(Sheet1!I33="","",Sheet1!I33) | J19: =IF(Sheet1!J33="","",Sheet1!J33) | K19: =IF(Sheet1!K33="","",Sheet1!K33) | L19: =IF(Sheet1!L33="","",Sheet1!L33) | ... S19: =IF(Sheet1!S33="","",Sheet1!S33)
B20: Target CAR (internal floor) | D20: Sheet1!B35:S35 | E20: =IF(Sheet1!E35="","",Sheet1!E35) -> 0.2 | F20: =IF(Sheet1!F35="","",Sheet1!F35) | G20: =IF(Sheet1!G35="","",Sheet1!G35) | H20: =IF(Sheet1!H35="","",Sheet1!H35) | I20: =IF(Sheet1!I35="","",Sheet1!I35) | J20: =IF(Sheet1!J35="","",Sheet1!J35) | K20: =IF(Sheet1!K35="","",Sheet1!K35) | L20: =IF(Sheet1!L35="","",Sheet1!L35) | ... S20: =IF(Sheet1!S35="","",Sheet1!S35)
B21: Regulatory minimum CAR incl. buffers | D21: Sheet1!B36:S36 | E21: =IF(Sheet1!E36="","",Sheet1!E36) -> 0.1349 | F21: =IF(Sheet1!F36="","",Sheet1!F36) | G21: =IF(Sheet1!G36="","",Sheet1!G36) | H21: =IF(Sheet1!H36="","",Sheet1!H36) | I21: =IF(Sheet1!I36="","",Sheet1!I36) | J21: =IF(Sheet1!J36="","",Sheet1!J36) | K21: =IF(Sheet1!K36="","",Sheet1!K36) | L21: =IF(Sheet1!L36="","",Sheet1!L36) | ... S21: =IF(Sheet1!S36="","",Sheet1!S36)
B22: FDR cap | D22: Sheet1!B37:S37 | E22: =IF(Sheet1!E37="","",Sheet1!E37) -> 0.92 | F22: =IF(Sheet1!F37="","",Sheet1!F37) | G22: =IF(Sheet1!G37="","",Sheet1!G37) | H22: =IF(Sheet1!H37="","",Sheet1!H37) | I22: =IF(Sheet1!I37="","",Sheet1!I37) | J22: =IF(Sheet1!J37="","",Sheet1!J37) | K22: =IF(Sheet1!K37="","",Sheet1!K37) | L22: =IF(Sheet1!L37="","",Sheet1!L37) | ... S22: =IF(Sheet1!S37="","",Sheet1!S37)
B23: Min cash & BI placements / DPK (GWM proxy) | D23: Sheet1!B38:S38 | E23: =IF(Sheet1!E38="","",Sheet1!E38) -> 0.075 | F23: =IF(Sheet1!F38="","",Sheet1!F38) | G23: =IF(Sheet1!G38="","",Sheet1!G38) | H23: =IF(Sheet1!H38="","",Sheet1!H38) | I23: =IF(Sheet1!I38="","",Sheet1!I38) | J23: =IF(Sheet1!J38="","",Sheet1!J38) | K23: =IF(Sheet1!K38="","",Sheet1!K38) | L23: =IF(Sheet1!L38="","",Sheet1!L38) | ... S23: =IF(Sheet1!S38="","",Sheet1!S38)
B24: Terminal ROE spread over Ke - Bear / Base / Bull | D24: Sheet1!B39:S39 | E24: =IF(Sheet1!E39="","",Sheet1!E39) -> 0 | F24: =IF(Sheet1!F39="","",Sheet1!F39) -> 0.02 | G24: =IF(Sheet1!G39="","",Sheet1!G39) -> 0.04 | H24: =IF(Sheet1!H39="","",Sheet1!H39) | I24: =IF(Sheet1!I39="","",Sheet1!I39) | J24: =IF(Sheet1!J39="","",Sheet1!J39) | K24: =IF(Sheet1!K39="","",Sheet1!K39) | L24: =IF(Sheet1!L39="","",Sheet1!L39) | ... S24: =IF(Sheet1!S39="","",Sheet1!S39)
B25: Rights issue toggle (1 = on) | D25: Sheet1!B133:S133 | E25: =IF(Sheet1!E133="","",Sheet1!E133) -> 1 | F25: =IF(Sheet1!F133="","",Sheet1!F133) | G25: =IF(Sheet1!G133="","",Sheet1!G133) | H25: =IF(Sheet1!H133="","",Sheet1!H133) | I25: =IF(Sheet1!I133="","",Sheet1!I133) | J25: =IF(Sheet1!J133="","",Sheet1!J133) | K25: =IF(Sheet1!K133="","",Sheet1!K133) | L25: =IF(Sheet1!L133="","",Sheet1!L133) | ... S25: =IF(Sheet1!S133="","",Sheet1!S133)
B26: New shares issued (rights issue) | D26: Sheet1!B134:S134 | E26: =IF(Sheet1!E134="","",Sheet1!E134) | F26: =IF(Sheet1!F134="","",Sheet1!F134) | G26: =IF(Sheet1!G134="","",Sheet1!G134) | H26: =IF(Sheet1!H134="","",Sheet1!H134) | I26: =IF(Sheet1!I134="","",Sheet1!I134) | J26: =IF(Sheet1!J134="","",Sheet1!J134) -> 0 | K26: =IF(Sheet1!K134="","",Sheet1!K134) -> 6800 | L26: =IF(Sheet1!L134="","",Sheet1!L134) -> 0 | ... S26: =IF(Sheet1!S134="","",Sheet1!S134) -> 0
B27: Rights issue price | D27: Sheet1!B135:S135 | E27: =IF(Sheet1!E135="","",Sheet1!E135) -> 940 | F27: =IF(Sheet1!F135="","",Sheet1!F135) | G27: =IF(Sheet1!G135="","",Sheet1!G135) | H27: =IF(Sheet1!H135="","",Sheet1!H135) | I27: =IF(Sheet1!I135="","",Sheet1!I135) | J27: =IF(Sheet1!J135="","",Sheet1!J135) | K27: =IF(Sheet1!K135="","",Sheet1!K135) | L27: =IF(Sheet1!L135="","",Sheet1!L135) | ... S27: =IF(Sheet1!S135="","",Sheet1!S135)

Sheet 02_Historical_FS
A1: BSI / BRIS | 02 Historical FS
A3: Historical financial statements FY21–FY25 | Linked to original calculation engine; source inputs unchanged
B5: Metric / source location | C5: Unit | D5: Original cell | E5: =Sheet1!E40 -> FY21A | F5: =Sheet1!F40 -> FY22A | G5: =Sheet1!G40 -> FY23A | H5: =Sheet1!H40 -> FY24A | I5: =Sheet1!I40 -> FY25A | J5: =Sheet1!J40 -> FY26E | K5: =Sheet1!K40 -> FY27E | L5: =Sheet1!L40 -> FY28E | ... S5: =Sheet1!S40 -> FY35E
B6: INCOME STATEMENT
B7: Gross margin income | D7: Sheet1!B141:S141 | E7: =IF(Sheet1!E141="","",Sheet1!E141) -> 17808.432 | F7: =IF(Sheet1!F141="","",Sheet1!F141) -> 19622.865 | G7: =IF(Sheet1!G141="","",Sheet1!G141) -> 22251.743 | H7: =IF(Sheet1!H141="","",Sheet1!H141) -> 25298.203 | I7: =IF(Sheet1!I141="","",Sheet1!I141) -> 28265.491 | J7: =IF(Sheet1!J141="","",Sheet1!J141) -> 29781.905 | K7: =IF(Sheet1!K141="","",Sheet1!K141) -> 33832.448 | L7: =IF(Sheet1!L141="","",Sheet1!L141) -> 37885.334 | ... S7: =IF(Sheet1!S141="","",Sheet1!S141) -> 67856.489
B8: Profit-sharing expense (funds owners) | D8: Sheet1!B142:S142 | E8: =IF(Sheet1!E142="","",Sheet1!E142) -> 4378.807 | F8: =IF(Sheet1!F142="","",Sheet1!F142) -> 4032.169 | G8: =IF(Sheet1!G142="","",Sheet1!G142) -> 5993.168 | H8: =IF(Sheet1!H142="","",Sheet1!H142) -> 7889.029 | I8: =IF(Sheet1!I142="","",Sheet1!I142) -> 9136.405 | J8: =IF(Sheet1!J142="","",Sheet1!J142) -> 8654.9786 | K8: =IF(Sheet1!K142="","",Sheet1!K142) -> 9059.8208 | L8: =IF(Sheet1!L142="","",Sheet1!L142) -> 9318.8925 | ... S8: =IF(Sheet1!S142="","",Sheet1!S142) -> 15695.095
B9: Net margin income | D9: Sheet1!B143:S143 | E9: =IF(Sheet1!E143="","",Sheet1!E143) -> 13429.625 | F9: =IF(Sheet1!F143="","",Sheet1!F143) -> 15590.696 | G9: =IF(Sheet1!G143="","",Sheet1!G143) -> 16258.575 | H9: =IF(Sheet1!H143="","",Sheet1!H143) -> 17409.174 | I9: =IF(Sheet1!I143="","",Sheet1!I143) -> 19129.086 | J9: =IF(Sheet1!J143="","",Sheet1!J143) -> 21126.926 | K9: =IF(Sheet1!K143="","",Sheet1!K143) -> 24772.627 | L9: =IF(Sheet1!L143="","",Sheet1!L143) -> 28566.442 | ... S9: =IF(Sheet1!S143="","",Sheet1!S143) -> 52161.394
B10: Fee-based income | D10: Sheet1!B144:S144 | E10: =IF(Sheet1!E144="","",Sheet1!E144) -> 3012.246 | F10: =IF(Sheet1!F144="","",Sheet1!F144) -> 3701.111 | G10: =IF(Sheet1!G144="","",Sheet1!G144) -> 4204.466 | H10: =IF(Sheet1!H144="","",Sheet1!H144) -> 5556.479 | I10: =IF(Sheet1!I144="","",Sheet1!I144) -> 6936.596 | J10: =IF(Sheet1!J144="","",Sheet1!J144) -> 8670.745 | K10: =IF(Sheet1!K144="","",Sheet1!K144) -> 9971.3567 | L10: =IF(Sheet1!L144="","",Sheet1!L144) -> 11167.92 | ... S10: =IF(Sheet1!S144="","",Sheet1!S144) -> 20036.745
B11: Operating income | D11: Sheet1!B145:S145 | E11: =IF(Sheet1!E145="","",Sheet1!E145) -> 16441.871 | F11: =IF(Sheet1!F145="","",Sheet1!F145) -> 19291.807 | G11: =IF(Sheet1!G145="","",Sheet1!G145) -> 20463.041 | H11: =IF(Sheet1!H145="","",Sheet1!H145) -> 22965.653 | I11: =IF(Sheet1!I145="","",Sheet1!I145) -> 26065.682 | J11: =IF(Sheet1!J145="","",Sheet1!J145) -> 29797.671 | K11: =IF(Sheet1!K145="","",Sheet1!K145) -> 34743.984 | L11: =IF(Sheet1!L145="","",Sheet1!L145) -> 39734.361 | ... S11: =IF(Sheet1!S145="","",Sheet1!S145) -> 72198.139
B12: Personnel expense | D12: Sheet1!B146:S146 | E12: =IF(Sheet1!E146="","",Sheet1!E146) -> 4400 | F12: =IF(Sheet1!F146="","",Sheet1!F146) -> 4847 | G12: =IF(Sheet1!G146="","",Sheet1!G146) -> 4944 | H12: =IF(Sheet1!H146="","",Sheet1!H146) -> 5141 | I12: =IF(Sheet1!I146="","",Sheet1!I146) -> 5380 | J12: =IF(Sheet1!J146="","",Sheet1!J146) -> 6377.0217 | K12: =IF(Sheet1!K146="","",Sheet1!K146) -> 7094.5039 | L12: =IF(Sheet1!L146="","",Sheet1!L146) -> 8035.4932 | ... S12: =IF(Sheet1!S146="","",Sheet1!S146) -> 14317.146
B13: G&A expense (incl. D&A) | D13: Sheet1!B147:S147 | E13: =IF(Sheet1!E147="","",Sheet1!E147) -> 3982.773 | F13: =IF(Sheet1!F147="","",Sheet1!F147) -> 4531.336 | G13: =IF(Sheet1!G147="","",Sheet1!G147) -> 4599.204 | H13: =IF(Sheet1!H147="","",Sheet1!H147) -> 5708.642 | I13: =IF(Sheet1!I147="","",Sheet1!I147) -> 7196.714 | J13: =IF(Sheet1!J147="","",Sheet1!J147) -> 8577.7787 | K13: =IF(Sheet1!K147="","",Sheet1!K147) -> 9474.1434 | L13: =IF(Sheet1!L147="","",Sheet1!L147) -> 10714.284 | ... S13: =IF(Sheet1!S147="","",Sheet1!S147) -> 19029.598
B14: Promotion expense | D14: Sheet1!B148:S148 | E14: =IF(Sheet1!E148="","",Sheet1!E148) -> 400 | F14: =IF(Sheet1!F148="","",Sheet1!F148) -> 517 | G14: =IF(Sheet1!G148="","",Sheet1!G148) -> 706 | H14: =IF(Sheet1!H148="","",Sheet1!H148) -> 944 | I14: =IF(Sheet1!I148="","",Sheet1!I148) -> 1124 | J14: =IF(Sheet1!J148="","",Sheet1!J148) -> 1284.9302 | K14: =IF(Sheet1!K148="","",Sheet1!K148) -> 1498.2243 | L14: =IF(Sheet1!L148="","",Sheet1!L148) -> 1713.4185 | ... S14: =IF(Sheet1!S148="","",Sheet1!S148) -> 3113.3161
B15: Overhead cost | D15: Sheet1!B149:S149 | E15: =IF(Sheet1!E149="","",Sheet1!E149) -> 8782.773 | F15: =IF(Sheet1!F149="","",Sheet1!F149) -> 9895.336 | G15: =IF(Sheet1!G149="","",Sheet1!G149) -> 10249.204 | H15: =IF(Sheet1!H149="","",Sheet1!H149) -> 11793.642 | I15: =IF(Sheet1!I149="","",Sheet1!I149) -> 13700.714 | J15: =IF(Sheet1!J149="","",Sheet1!J149) -> 16239.731 | K15: =IF(Sheet1!K149="","",Sheet1!K149) -> 18066.872 | L15: =IF(Sheet1!L149="","",Sheet1!L149) -> 20463.196 | ... S15: =IF(Sheet1!S149="","",Sheet1!S149) -> 36460.06
B16: Pre-provision operating profit (PPOP) | D16: Sheet1!B150:S150 | E16: =IF(Sheet1!E150="","",Sheet1!E150) -> 7659.098 | F16: =IF(Sheet1!F150="","",Sheet1!F150) -> 9396.471 | G16: =IF(Sheet1!G150="","",Sheet1!G150) -> 10213.837 | H16: =IF(Sheet1!H150="","",Sheet1!H150) -> 11172.011 | I16: =IF(Sheet1!I150="","",Sheet1!I150) -> 12364.968 | J16: =IF(Sheet1!J150="","",Sheet1!J150) -> 13557.94 | K16: =IF(Sheet1!K150="","",Sheet1!K150) -> 16677.112 | L16: =IF(Sheet1!L150="","",Sheet1!L150) -> 19271.165 | ... S16: =IF(Sheet1!S150="","",Sheet1!S150) -> 35738.079
B17: Provisions (CKPN charge) | D17: Sheet1!B151:S151 | E17: =IF(Sheet1!E151="","",Sheet1!E151) -> 3551.249 | F17: =IF(Sheet1!F151="","",Sheet1!F151) -> 3748.797 | G17: =IF(Sheet1!G151="","",Sheet1!G151) -> 2622.479 | H17: =IF(Sheet1!H151="","",Sheet1!H151) -> 1893.867 | I17: =IF(Sheet1!I151="","",Sheet1!I151) -> 2356.951 | J17: =IF(Sheet1!J151="","",Sheet1!J151) -> 2392.3887 | K17: =IF(Sheet1!K151="","",Sheet1!K151) -> 2912.2046 | L17: =IF(Sheet1!L151="","",Sheet1!L151) -> 3267.4523 | ... S17: =IF(Sheet1!S151="","",Sheet1!S151) -> 5918.1099
B18: Profit before tax & other | D18: Sheet1!B152:S152 | E18: =IF(Sheet1!E152="","",Sheet1!E152) -> 4107.849 | F18: =IF(Sheet1!F152="","",Sheet1!F152) -> 5647.674 | G18: =IF(Sheet1!G152="","",Sheet1!G152) -> 7591.358 | H18: =IF(Sheet1!H152="","",Sheet1!H152) -> 9278.144 | I18: =IF(Sheet1!I152="","",Sheet1!I152) -> 10008.017 | J18: =IF(Sheet1!J152="","",Sheet1!J152) -> 11165.552 | K18: =IF(Sheet1!K152="","",Sheet1!K152) -> 13764.908 | L18: =IF(Sheet1!L152="","",Sheet1!L152) -> 16003.713 | ... S18: =IF(Sheet1!S152="","",Sheet1!S152) -> 29819.969
... B22: Net profit growth | D22: Sheet1!B156:S156 | E22: =IF(Sheet1!E156="","",Sheet1!E156) | F22: =IF(Sheet1!F156="","",Sheet1!F156) -> 0.40677398 | G22: =IF(Sheet1!G156="","",Sheet1!G156) -> 0.33890681 | H22: =IF(Sheet1!H156="","",Sheet1!H156) -> 0.22829658 | I22: =IF(Sheet1!I156="","",Sheet1!I156) -> 0.08016614 | J22: =IF(Sheet1!J156="","",Sheet1!J156) -> 0.11281946 | K22: =IF(Sheet1!K156="","",Sheet1!K156) -> 0.2328014 | L22: =IF(Sheet1!L156="","",Sheet1!L156) -> 0.16264586 | ... S22: =IF(Sheet1!S156="","",Sheet1!S156) -> 0.069596569
B23: BALANCE SHEET
B24: Personnel as % of overhead | D24: Sheet1!B158:S158 | E24: =IF(Sheet1!E158="","",Sheet1!E158) -> 0.50098073 | F24: =IF(Sheet1!F158="","",Sheet1!F158) -> 0.48982672 | G24: =IF(Sheet1!G158="","",Sheet1!G158) -> 0.48237892 | H24: =IF(Sheet1!H158="","",Sheet1!H158) -> 0.43591284 | I24: =IF(Sheet1!I158="","",Sheet1!I158) -> 0.39268026 | J24: =IF(Sheet1!J158="","",Sheet1!J158) -> 0.39268026 | K24: =IF(Sheet1!K158="","",Sheet1!K158) -> 0.39268026 | L24: =IF(Sheet1!L158="","",Sheet1!L158) -> 0.39268026 | ... S24: =IF(Sheet1!S158="","",Sheet1!S158) -> 0.39268026
B25: Promotion as % of operating income | D25: Sheet1!B159:S159 | E25: =IF(Sheet1!E159="","",Sheet1!E159) -> 0.024328132 | F25: =IF(Sheet1!F159="","",Sheet1!F159) -> 0.026798941 | G25: =IF(Sheet1!G159="","",Sheet1!G159) -> 0.034501226 | H25: =IF(Sheet1!H159="","",Sheet1!H159) -> 0.041104862 | I25: =IF(Sheet1!I159="","",Sheet1!I159) -> 0.043121834 | J25: =IF(Sheet1!J159="","",Sheet1!J159) -> 0.043121834 | K25: =IF(Sheet1!K159="","",Sheet1!K159) -> 0.043121834 | L25: =IF(Sheet1!L159="","",Sheet1!L159) -> 0.043121834 | ... S25: =IF(Sheet1!S159="","",Sheet1!S159) -> 0.043121834
B26: Fee-based ratio (fee / operating income) | D26: Sheet1!B160:S160 | E26: =IF(Sheet1!E160="","",Sheet1!E160) -> 0.18320579 | F26: =IF(Sheet1!F160="","",Sheet1!F160) -> 0.19184885 | G26: =IF(Sheet1!G160="","",Sheet1!G160) -> 0.20546633 | H26: =IF(Sheet1!H160="","",Sheet1!H160) -> 0.24194736 | I26: =IF(Sheet1!I160="","",Sheet1!I160) -> 0.26611987 | J26: =IF(Sheet1!J160="","",Sheet1!J160) -> 0.29098734 | K26: =IF(Sheet1!K160="","",Sheet1!K160) -> 0.28699521 | L26: =IF(Sheet1!L160="","",Sheet1!L160) -> 0.28106453 | ... S26: =IF(Sheet1!S160="","",Sheet1!S160) -> 0.2775244
B27: Original metric row 161 | D27: Sheet1!B161:S161 | E27: =IF(Sheet1!E161="","",Sheet1!E161) | F27: =IF(Sheet1!F161="","",Sheet1!F161) | G27: =IF(Sheet1!G161="","",Sheet1!G161) | H27: =IF(Sheet1!H161="","",Sheet1!H161) | I27: =IF(Sheet1!I161="","",Sheet1!I161) | J27: =IF(Sheet1!J161="","",Sheet1!J161) | K27: =IF(Sheet1!K161="","",Sheet1!K161) | L27: =IF(Sheet1!L161="","",Sheet1!L161) | ... S27: =IF(Sheet1!S161="","",Sheet1!S161)
B28: 2b. Balance sheet | D28: Sheet1!B162:S162 | E28: =IF(Sheet1!E162="","",Sheet1!E162) -> FY21A | F28: =IF(Sheet1!F162="","",Sheet1!F162) -> FY22A | G28: =IF(Sheet1!G162="","",Sheet1!G162) -> FY23A | H28: =IF(Sheet1!H162="","",Sheet1!H162) -> FY24A | I28: =IF(Sheet1!I162="","",Sheet1!I162) -> FY25A | J28: =IF(Sheet1!J162="","",Sheet1!J162) -> FY26E | K28: =IF(Sheet1!K162="","",Sheet1!K162) -> FY27E | L28: =IF(Sheet1!L162="","",Sheet1!L162) -> FY28E | ... S28: =IF(Sheet1!S162="","",Sheet1!S162) -> FY35E
B29: Cash, BI placements & interbank | D29: Sheet1!B163:S163 | E29: =IF(Sheet1!E163="","",Sheet1!E163) -> 26525 | F29: =IF(Sheet1!F163="","",Sheet1!F163) -> 39206 | G29: =IF(Sheet1!G163="","",Sheet1!G163) -> 40001 | H29: =IF(Sheet1!H163="","",Sheet1!H163) -> 61913 | I29: =IF(Sheet1!I163="","",Sheet1!I163) -> 64845 | J29: =IF(Sheet1!J163="","",Sheet1!J163) -> 68145.472 | K29: =IF(Sheet1!K163="","",Sheet1!K163) -> 80573.85 | L29: =IF(Sheet1!L163="","",Sheet1!L163) -> 85532.173 | ... S29: =IF(Sheet1!S163="","",Sheet1!S163) -> 156935.94
B30: Securities & other earning assets (sukuk, placements) | D30: Sheet1!B164:S164 | E30: =IF(Sheet1!E164="","",Sheet1!E164) -> 67734.527 | F30: =IF(Sheet1!F164="","",Sheet1!F164) -> 58323.411 | G30: =IF(Sheet1!G164="","",Sheet1!G164) -> 71621.726 | H30: =IF(Sheet1!H164="","",Sheet1!H164) -> 62426.25 | I30: =IF(Sheet1!I164="","",Sheet1!I164) -> 60369.831 | J30: =IF(Sheet1!J164="","",Sheet1!J164) -> 68075.29 | K30: =IF(Sheet1!K164="","",Sheet1!K164) -> 75991.152 | L30: =IF(Sheet1!L164="","",Sheet1!L164) -> 83786.955 | ... S30: =IF(Sheet1!S164="","",Sheet1!S164) -> 148436.23
B31: Gross financing | D31: Sheet1!B165:S165 | E31: =IF(Sheet1!E165="","",Sheet1!E165) -> 171291 | F31: =IF(Sheet1!F165="","",Sheet1!F165) -> 207704 | G31: =IF(Sheet1!G165="","",Sheet1!G165) -> 240316 | H31: =IF(Sheet1!H165="","",Sheet1!H165) -> 278481 | I31: =IF(Sheet1!I165="","",Sheet1!I165) -> 318844 | J31: =IF(Sheet1!J165="","",Sheet1!J165) -> 364695.64 | K31: =IF(Sheet1!K165="","",Sheet1!K165) -> 411892.26 | L31: =IF(Sheet1!L165="","",Sheet1!L165) -> 459428.37 | ... S31: =IF(Sheet1!S165="","",Sheet1!S165) -> 813919.23
B32: Less: allowance for impairment (CKPN) | D32: Sheet1!B166:S166 | E32: =IF(Sheet1!E166="","",Sheet1!E166) -> -7471.5267 | F32: =IF(Sheet1!F166="","",Sheet1!F166) -> -9204.4111 | G32: =IF(Sheet1!G166="","",Sheet1!G166) -> -9714.7262 | H32: =IF(Sheet1!H166="","",Sheet1!H166) -> -10318.25 | I32: =IF(Sheet1!I166="","",Sheet1!I166) -> -11015.831 | J32: =IF(Sheet1!J166="","",Sheet1!J166) -> -12819.052 | K32: =IF(Sheet1!K166="","",Sheet1!K166) -> -14478.013 | L32: =IF(Sheet1!L166="","",Sheet1!L166) -> -15712.45 | ... S32: =IF(Sheet1!S166="","",Sheet1!S166) -> -27836.038
B33: Fixed assets & intangibles, net | D33: Sheet1!B167:S167 | E33: =IF(Sheet1!E167="","",Sheet1!E167) -> 4056 | F33: =IF(Sheet1!F167="","",Sheet1!F167) -> 5655 | G33: =IF(Sheet1!G167="","",Sheet1!G167) -> 6481 | H33: =IF(Sheet1!H167="","",Sheet1!H167) -> 9826 | I33: =IF(Sheet1!I167="","",Sheet1!I167) -> 13857 | J33: =IF(Sheet1!J167="","",Sheet1!J167) -> 13720.073 | K33: =IF(Sheet1!K167="","",Sheet1!K167) -> 13964.073 | L33: =IF(Sheet1!L167="","",Sheet1!L167) -> 14515.764 | ... S33: =IF(Sheet1!S167="","",Sheet1!S167) -> 22691.561
B34: Other assets (working capital) | D34: Sheet1!B168:S168 | E34: =IF(Sheet1!E168="","",Sheet1!E168) -> 3154 | F34: =IF(Sheet1!F168="","",Sheet1!F168) -> 4043 | G34: =IF(Sheet1!G168="","",Sheet1!G168) -> 4919 | H34: =IF(Sheet1!H168="","",Sheet1!H168) -> 6285 | I34: =IF(Sheet1!I168="","",Sheet1!I168) -> 9293 | J34: =IF(Sheet1!J168="","",Sheet1!J168) -> 10623.538 | K34: =IF(Sheet1!K168="","",Sheet1!K168) -> 12387.009 | L34: =IF(Sheet1!L168="","",Sheet1!L168) -> 14166.191 | ... S34: =IF(Sheet1!S168="","",Sheet1!S168) -> 25740.255
B35: TOTAL ASSETS | D35: Sheet1!B169:S169 | E35: =IF(Sheet1!E169="","",Sheet1!E169) -> 265289 | F35: =IF(Sheet1!F169="","",Sheet1!F169) -> 305727 | G35: =IF(Sheet1!G169="","",Sheet1!G169) -> 353624 | H35: =IF(Sheet1!H169="","",Sheet1!H169) -> 408613 | I35: =IF(Sheet1!I169="","",Sheet1!I169) -> 456193 | J35: =IF(Sheet1!J169="","",Sheet1!J169) -> 512440.96 | K35: =IF(Sheet1!K169="","",Sheet1!K169) -> 580330.33 | L35: =IF(Sheet1!L169="","",Sheet1!L169) -> 641717 | ... S35: =IF(Sheet1!S169="","",Sheet1!S169) -> 1139887.2
... B48: Original metric row 182 | D48: Sheet1!B182:S182 | E48: =IF(Sheet1!E182="","",Sheet1!E182) | F48: =IF(Sheet1!F182="","",Sheet1!F182) | G48: =IF(Sheet1!G182="","",Sheet1!G182) | H48: =IF(Sheet1!H182="","",Sheet1!H182) | I48: =IF(Sheet1!I182="","",Sheet1!I182) | J48: =IF(Sheet1!J182="","",Sheet1!J182) | K48: =IF(Sheet1!K182="","",Sheet1!K182) | L48: =IF(Sheet1!L182="","",Sheet1!L182) | ... S48: =IF(Sheet1!S182="","",Sheet1!S182)
B49: BALANCE SHEET CONTINUATION
B50: Net profit | D50: Sheet1!B184:S184 | E50: =IF(Sheet1!E184="","",Sheet1!E184) | F50: =IF(Sheet1!F184="","",Sheet1!F184) | G50: =IF(Sheet1!G184="","",Sheet1!G184) | H50: =IF(Sheet1!H184="","",Sheet1!H184) | I50: =IF(Sheet1!I184="","",Sheet1!I184) | J50: =IF(Sheet1!J184="","",Sheet1!J184) -> 8421.2868 | K50: =IF(Sheet1!K184="","",Sheet1!K184) -> 10381.774 | L50: =IF(Sheet1!L184="","",Sheet1!L184) -> 12070.327 | ... S50: =IF(Sheet1!S184="","",Sheet1!S184) -> 22490.829
B51: (+) Depreciation & amortisation | D51: Sheet1!B185:S185 | E51: =IF(Sheet1!E185="","",Sheet1!E185) | F51: =IF(Sheet1!F185="","",Sheet1!F185) | G51: =IF(Sheet1!G185="","",Sheet1!G185) | H51: =IF(Sheet1!H185="","",Sheet1!H185) | I51: =IF(Sheet1!I185="","",Sheet1!I185) | J51: =IF(Sheet1!J185="","",Sheet1!J185) -> 2520.7409 | K51: =IF(Sheet1!K185="","",Sheet1!K185) -> 2535.5187 | L51: =IF(Sheet1!L185="","",Sheet1!L185) -> 2627.0574 | ... S51: =IF(Sheet1!S185="","",Sheet1!S185) -> 4298.5073
B52: (+) Provision charge (non-cash) | D52: Sheet1!B186:S186 | E52: =IF(Sheet1!E186="","",Sheet1!E186) | F52: =IF(Sheet1!F186="","",Sheet1!F186) | G52: =IF(Sheet1!G186="","",Sheet1!G186) | H52: =IF(Sheet1!H186="","",Sheet1!H186) | I52: =IF(Sheet1!I186="","",Sheet1!I186) | J52: =IF(Sheet1!J186="","",Sheet1!J186) -> 2392.3887 | K52: =IF(Sheet1!K186="","",Sheet1!K186) -> 2912.2046 | L52: =IF(Sheet1!L186="","",Sheet1!L186) -> 3267.4523 | ... S52: =IF(Sheet1!S186="","",Sheet1!S186) -> 5918.1099
B53: (-) Increase in other assets | D53: Sheet1!B187:S187 | E53: =IF(Sheet1!E187="","",Sheet1!E187) | F53: =IF(Sheet1!F187="","",Sheet1!F187) | G53: =IF(Sheet1!G187="","",Sheet1!G187) | H53: =IF(Sheet1!H187="","",Sheet1!H187) | I53: =IF(Sheet1!I187="","",Sheet1!I187) | J53: =IF(Sheet1!J187="","",Sheet1!J187) -> -1330.5377 | K53: =IF(Sheet1!K187="","",Sheet1!K187) -> -1763.4714 | L53: =IF(Sheet1!L187="","",Sheet1!L187) -> -1779.1814 | ... S53: =IF(Sheet1!S187="","",Sheet1!S187) -> -1669.6974
B54: (+) Increase in other liabilities | D54: Sheet1!B188:S188 | E54: =IF(Sheet1!E188="","",Sheet1!E188) | F54: =IF(Sheet1!F188="","",Sheet1!F188) | G54: =IF(Sheet1!G188="","",Sheet1!G188) | H54: =IF(Sheet1!H188="","",Sheet1!H188) | I54: =IF(Sheet1!I188="","",Sheet1!I188) | J54: =IF(Sheet1!J188="","",Sheet1!J188) -> 1111.9255 | K54: =IF(Sheet1!K188="","",Sheet1!K188) -> 1473.7266 | L54: =IF(Sheet1!L188="","",Sheet1!L188) -> 1486.8554 | ... S54: =IF(Sheet1!S188="","",Sheet1!S188) -> 1395.3599
B55: Cash flow from operations | D55: Sheet1!B189:S189 | E55: =IF(Sheet1!E189="","",Sheet1!E189) | F55: =IF(Sheet1!F189="","",Sheet1!F189) | G55: =IF(Sheet1!G189="","",Sheet1!G189) | H55: =IF(Sheet1!H189="","",Sheet1!H189) | I55: =IF(Sheet1!I189="","",Sheet1!I189) | J55: =IF(Sheet1!J189="","",Sheet1!J189) -> 13115.804 | K55: =IF(Sheet1!K189="","",Sheet1!K189) -> 15539.753 | L55: =IF(Sheet1!L189="","",Sheet1!L189) -> 17672.51 | ... S55: =IF(Sheet1!S189="","",Sheet1!S189) -> 32433.109
B56: (-) Net new financing (gross change + write-offs) | D56: Sheet1!B190:S190 | E56: =IF(Sheet1!E190="","",Sheet1!E190) | F56: =IF(Sheet1!F190="","",Sheet1!F190) | G56: =IF(Sheet1!G190="","",Sheet1!G190) | H56: =IF(Sheet1!H190="","",Sheet1!H190) | I56: =IF(Sheet1!I190="","",Sheet1!I190) | J56: =IF(Sheet1!J190="","",Sheet1!J190) -> -46440.808 | K56: =IF(Sheet1!K190="","",Sheet1!K190) -> -48449.859 | L56: =IF(Sheet1!L190="","",Sheet1!L190) -> -49569.127 | ... S56: =IF(Sheet1!S190="","",Sheet1!S190) -> -53895.018
B57: (-) Increase in securities & other earning assets | D57: Sheet1!B191:S191 | E57: =IF(Sheet1!E191="","",Sheet1!E191) | F57: =IF(Sheet1!F191="","",Sheet1!F191) | G57: =IF(Sheet1!G191="","",Sheet1!G191) | H57: =IF(Sheet1!H191="","",Sheet1!H191) | I57: =IF(Sheet1!I191="","",Sheet1!I191) | J57: =IF(Sheet1!J191="","",Sheet1!J191) -> -7705.4589 | K57: =IF(Sheet1!K191="","",Sheet1!K191) -> -7915.8622 | L57: =IF(Sheet1!L191="","",Sheet1!L191) -> -7795.803 | ... S57: =IF(Sheet1!S191="","",Sheet1!S191) -> -9059.488
B58: (-) Capex (incl. ROU additions) | D58: Sheet1!B192:S192 | E58: =IF(Sheet1!E192="","",Sheet1!E192) | F58: =IF(Sheet1!F192="","",Sheet1!F192) | G58: =IF(Sheet1!G192="","",Sheet1!G192) | H58: =IF(Sheet1!H192="","",Sheet1!H192) | I58: =IF(Sheet1!I192="","",Sheet1!I192) | J58: =IF(Sheet1!J192="","",Sheet1!J192) -> -2383.8137 | K58: =IF(Sheet1!K192="","",Sheet1!K192) -> -2779.5187 | L58: =IF(Sheet1!L192="","",Sheet1!L192) -> -3178.7489 | ... S58: =IF(Sheet1!S192="","",Sheet1!S192) -> -5775.8511
B59: Cash flow from investing / lending | D59: Sheet1!B193:S193 | E59: =IF(Sheet1!E193="","",Sheet1!E193) | F59: =IF(Sheet1!F193="","",Sheet1!F193) | G59: =IF(Sheet1!G193="","",Sheet1!G193) | H59: =IF(Sheet1!H193="","",Sheet1!H193) | I59: =IF(Sheet1!I193="","",Sheet1!I193) | J59: =IF(Sheet1!J193="","",Sheet1!J193) -> -56530.08 | K59: =IF(Sheet1!K193="","",Sheet1!K193) -> -59145.24 | L59: =IF(Sheet1!L193="","",Sheet1!L193) -> -60543.679 | ... S59: =IF(Sheet1!S193="","",Sheet1!S193) -> -68730.357
B60: (+) Increase in third-party funds (incl. syirkah) | D60: Sheet1!B194:S194 | E60: =IF(Sheet1!E194="","",Sheet1!E194) | F60: =IF(Sheet1!F194="","",Sheet1!F194) | G60: =IF(Sheet1!G194="","",Sheet1!G194) | H60: =IF(Sheet1!H194="","",Sheet1!H194) | I60: =IF(Sheet1!I194="","",Sheet1!I194) | J60: =IF(Sheet1!J194="","",Sheet1!J194) -> 48564.694 | K60: =IF(Sheet1!K194="","",Sheet1!K194) -> 49890.789 | L60: =IF(Sheet1!L194="","",Sheet1!L194) -> 49134.1 | ... S60: =IF(Sheet1!S194="","",Sheet1!S194) -> 57098.645
B61: (+) Net debt issuance / (repayment) | D61: Sheet1!B195:S195 | E61: =IF(Sheet1!E195="","",Sheet1!E195) | F61: =IF(Sheet1!F195="","",Sheet1!F195) | G61: =IF(Sheet1!G195="","",Sheet1!G195) | H61: =IF(Sheet1!H195="","",Sheet1!H195) | I61: =IF(Sheet1!I195="","",Sheet1!I195) | J61: =IF(Sheet1!J195="","",Sheet1!J195) -> -48.6 | K61: =IF(Sheet1!K195="","",Sheet1!K195) -> 1745 | L61: =IF(Sheet1!L195="","",Sheet1!L195) -> 1314 | ... S61: =IF(Sheet1!S195="","",Sheet1!S195) -> 0
B62: CASH FLOW
B63: (-) Dividends paid | D63: Sheet1!B197:S197 | E63: =IF(Sheet1!E197="","",Sheet1!E197) | F63: =IF(Sheet1!F197="","",Sheet1!F197) | G63: =IF(Sheet1!G197="","",Sheet1!G197) | H63: =IF(Sheet1!H197="","",Sheet1!H197) | I63: =IF(Sheet1!I197="","",Sheet1!I197) | J63: =IF(Sheet1!J197="","",Sheet1!J197) -> -1513.5046 | K63: =IF(Sheet1!K197="","",Sheet1!K197) -> -1852.6831 | L63: =IF(Sheet1!L197="","",Sheet1!L197) -> -2595.4436 | ... S63: =IF(Sheet1!S197="","",Sheet1!S197) -> -12616.437
B64: (+) OCI (treated as cash-equivalent movement) | D64: Sheet1!B198:S198 | E64: =IF(Sheet1!E198="","",Sheet1!E198) | F64: =IF(Sheet1!F198="","",Sheet1!F198) | G64: =IF(Sheet1!G198="","",Sheet1!G198) | H64: =IF(Sheet1!H198="","",Sheet1!H198) | I64: =IF(Sheet1!I198="","",Sheet1!I198) | J64: =IF(Sheet1!J198="","",Sheet1!J198) -> 0 | K64: =IF(Sheet1!K198="","",Sheet1!K198) -> 0 | L64: =IF(Sheet1!L198="","",Sheet1!L198) -> 0 | ... S64: =IF(Sheet1!S198="","",Sheet1!S198) -> 0
B65: (+) Equity raise | D65: Sheet1!B199:S199 | E65: =IF(Sheet1!E199="","",Sheet1!E199) | F65: =IF(Sheet1!F199="","",Sheet1!F199) | G65: =IF(Sheet1!G199="","",Sheet1!G199) | H65: =IF(Sheet1!H199="","",Sheet1!H199) | I65: =IF(Sheet1!I199="","",Sheet1!I199) | J65: =IF(Sheet1!J199="","",Sheet1!J199) -> 0 | K65: =IF(Sheet1!K199="","",Sheet1!K199) -> 6392 | L65: =IF(Sheet1!L199="","",Sheet1!L199) -> 0 | ... S65: =IF(Sheet1!S199="","",Sheet1!S199) -> 0
B66: Cash flow from funding & equity | D66: Sheet1!B200:S200 | E66: =IF(Sheet1!E200="","",Sheet1!E200) | F66: =IF(Sheet1!F200="","",Sheet1!F200) | G66: =IF(Sheet1!G200="","",Sheet1!G200) | H66: =IF(Sheet1!H200="","",Sheet1!H200) | I66: =IF(Sheet1!I200="","",Sheet1!I200) | J66: =IF(Sheet1!J200="","",Sheet1!J200) -> 46714.748 | K66: =IF(Sheet1!K200="","",Sheet1!K200) -> 56033.866 | L66: =IF(Sheet1!L200="","",Sheet1!L200) -> 47829.491 | ... S66: =IF(Sheet1!S200="","",Sheet1!S200) -> 44810.127
B67: Net change in cash | D67: Sheet1!B201:S201 | E67: =IF(Sheet1!E201="","",Sheet1!E201) | F67: =IF(Sheet1!F201="","",Sheet1!F201) | G67: =IF(Sheet1!G201="","",Sheet1!G201) | H67: =IF(Sheet1!H201="","",Sheet1!H201) | I67: =IF(Sheet1!I201="","",Sheet1!I201) | J67: =IF(Sheet1!J201="","",Sheet1!J201) -> 3300.4716 | K67: =IF(Sheet1!K201="","",Sheet1!K201) -> 12428.379 | L67: =IF(Sheet1!L201="","",Sheet1!L201) -> 4958.3231 | ... S67: =IF(Sheet1!S201="","",Sheet1!S201) -> 8512.8789
B68: Closing cash (feeds balance sheet) | D68: Sheet1!B202:S202 | E68: =IF(Sheet1!E202="","",Sheet1!E202) | F68: =IF(Sheet1!F202="","",Sheet1!F202) | G68: =IF(Sheet1!G202="","",Sheet1!G202) | H68: =IF(Sheet1!H202="","",Sheet1!H202) | I68: =IF(Sheet1!I202="","",Sheet1!I202) | J68: =IF(Sheet1!J202="","",Sheet1!J202) -> 68145.472 | K68: =IF(Sheet1!K202="","",Sheet1!K202) -> 80573.85 | L68: =IF(Sheet1!L202="","",Sheet1!L202) -> 85532.173 | ... S68: =IF(Sheet1!S202="","",Sheet1!S202) -> 156935.94
B69: Original metric row 203 | D69: Sheet1!B203:S203 | E69: =IF(Sheet1!E203="","",Sheet1!E203) | F69: =IF(Sheet1!F203="","",Sheet1!F203) | G69: =IF(Sheet1!G203="","",Sheet1!G203) | H69: =IF(Sheet1!H203="","",Sheet1!H203) | I69: =IF(Sheet1!I203="","",Sheet1!I203) | J69: =IF(Sheet1!J203="","",Sheet1!J203) | K69: =IF(Sheet1!K203="","",Sheet1!K203) | L69: =IF(Sheet1!L203="","",Sheet1!L203) | ... S69: =IF(Sheet1!S203="","",Sheet1!S203)
B70: Original metric row 204 | D70: Sheet1!B204:S204 | E70: =IF(Sheet1!E204="","",Sheet1!E204) | F70: =IF(Sheet1!F204="","",Sheet1!F204) | G70: =IF(Sheet1!G204="","",Sheet1!G204) | H70: =IF(Sheet1!H204="","",Sheet1!H204) | I70: =IF(Sheet1!I204="","",Sheet1!I204) | J70: =IF(Sheet1!J204="","",Sheet1!J204) | K70: =IF(Sheet1!K204="","",Sheet1!K204) | L70: =IF(Sheet1!L204="","",Sheet1!L204) | ... S70: =IF(Sheet1!S204="","",Sheet1!S204)
B71: 3. SUPPORTING SCHEDULES | D71: Sheet1!B205:S205 | E71: =IF(Sheet1!E205="","",Sheet1!E205) | F71: =IF(Sheet1!F205="","",Sheet1!F205) | G71: =IF(Sheet1!G205="","",Sheet1!G205) | H71: =IF(Sheet1!H205="","",Sheet1!H205) | I71: =IF(Sheet1!I205="","",Sheet1!I205) | J71: =IF(Sheet1!J205="","",Sheet1!J205) | K71: =IF(Sheet1!K205="","",Sheet1!K205) | L71: =IF(Sheet1!L205="","",Sheet1!L205) | ... S71: =IF(Sheet1!S205="","",Sheet1!S205)
B72: S1. Financing book by segment (revenue engine) | D72: Sheet1!B206:S206 | E72: =IF(Sheet1!E206="","",Sheet1!E206) -> FY21A | F72: =IF(Sheet1!F206="","",Sheet1!F206) -> FY22A | G72: =IF(Sheet1!G206="","",Sheet1!G206) -> FY23A | H72: =IF(Sheet1!H206="","",Sheet1!H206) -> FY24A | I72: =IF(Sheet1!I206="","",Sheet1!I206) -> FY25A | J72: =IF(Sheet1!J206="","",Sheet1!J206) -> FY26E | K72: =IF(Sheet1!K206="","",Sheet1!K206) -> FY27E | L72: =IF(Sheet1!L206="","",Sheet1!L206) -> FY28E | ... S72: =IF(Sheet1!S206="","",Sheet1!S206) -> FY35E

Sheet 03_Historical_Ratios
A1: BSI / BRIS | 03 Historical Ratios
A3: Capital, asset-quality and profitability indicators | Linked to original calculation engine; source inputs unchanged
B5: Metric / source location | C5: Unit | D5: Original cell | E5: =Sheet1!E40 -> FY21A | F5: =Sheet1!F40 -> FY22A | G5: =Sheet1!G40 -> FY23A | H5: =Sheet1!H40 -> FY24A | I5: =Sheet1!I40 -> FY25A | J5: =Sheet1!J40 -> FY26E | K5: =Sheet1!K40 -> FY27E | L5: =Sheet1!L40 -> FY28E | ... S5: =Sheet1!S40 -> FY35E
B6: INCOME AND MARGINS
B7: Net margin income | D7: Sheet1!B143:S143 | E7: =IF(Sheet1!E143="","",Sheet1!E143) -> 13429.625 | F7: =IF(Sheet1!F143="","",Sheet1!F143) -> 15590.696 | G7: =IF(Sheet1!G143="","",Sheet1!G143) -> 16258.575 | H7: =IF(Sheet1!H143="","",Sheet1!H143) -> 17409.174 | I7: =IF(Sheet1!I143="","",Sheet1!I143) -> 19129.086 | J7: =IF(Sheet1!J143="","",Sheet1!J143) -> 21126.926 | K7: =IF(Sheet1!K143="","",Sheet1!K143) -> 24772.627 | L7: =IF(Sheet1!L143="","",Sheet1!L143) -> 28566.442 | ... S7: =IF(Sheet1!S143="","",Sheet1!S143) -> 52161.394
B8: Operating income | D8: Sheet1!B145:S145 | E8: =IF(Sheet1!E145="","",Sheet1!E145) -> 16441.871 | F8: =IF(Sheet1!F145="","",Sheet1!F145) -> 19291.807 | G8: =IF(Sheet1!G145="","",Sheet1!G145) -> 20463.041 | H8: =IF(Sheet1!H145="","",Sheet1!H145) -> 22965.653 | I8: =IF(Sheet1!I145="","",Sheet1!I145) -> 26065.682 | J8: =IF(Sheet1!J145="","",Sheet1!J145) -> 29797.671 | K8: =IF(Sheet1!K145="","",Sheet1!K145) -> 34743.984 | L8: =IF(Sheet1!L145="","",Sheet1!L145) -> 39734.361 | ... S8: =IF(Sheet1!S145="","",Sheet1!S145) -> 72198.139
B9: Overhead cost | D9: Sheet1!B149:S149 | E9: =IF(Sheet1!E149="","",Sheet1!E149) -> 8782.773 | F9: =IF(Sheet1!F149="","",Sheet1!F149) -> 9895.336 | G9: =IF(Sheet1!G149="","",Sheet1!G149) -> 10249.204 | H9: =IF(Sheet1!H149="","",Sheet1!H149) -> 11793.642 | I9: =IF(Sheet1!I149="","",Sheet1!I149) -> 13700.714 | J9: =IF(Sheet1!J149="","",Sheet1!J149) -> 16239.731 | K9: =IF(Sheet1!K149="","",Sheet1!K149) -> 18066.872 | L9: =IF(Sheet1!L149="","",Sheet1!L149) -> 20463.196 | ... S9: =IF(Sheet1!S149="","",Sheet1!S149) -> 36460.06
B10: Pre-provision operating profit (PPOP) | D10: Sheet1!B150:S150 | E10: =IF(Sheet1!E150="","",Sheet1!E150) -> 7659.098 | F10: =IF(Sheet1!F150="","",Sheet1!F150) -> 9396.471 | G10: =IF(Sheet1!G150="","",Sheet1!G150) -> 10213.837 | H10: =IF(Sheet1!H150="","",Sheet1!H150) -> 11172.011 | I10: =IF(Sheet1!I150="","",Sheet1!I150) -> 12364.968 | J10: =IF(Sheet1!J150="","",Sheet1!J150) -> 13557.94 | K10: =IF(Sheet1!K150="","",Sheet1!K150) -> 16677.112 | L10: =IF(Sheet1!L150="","",Sheet1!L150) -> 19271.165 | ... S10: =IF(Sheet1!S150="","",Sheet1!S150) -> 35738.079
B11: Tax & other (net, incl. non-operating) | D11: Sheet1!B153:S153 | E11: =IF(Sheet1!E153="","",Sheet1!E153) -> 1079.644 | F11: =IF(Sheet1!F153="","",Sheet1!F153) -> 1387.674 | G11: =IF(Sheet1!G153="","",Sheet1!G153) -> 1887.615 | H11: =IF(Sheet1!H153="","",Sheet1!H153) -> 2272.256 | I11: =IF(Sheet1!I153="","",Sheet1!I153) -> 2440.494 | J11: =IF(Sheet1!J153="","",Sheet1!J153) -> 2744.2647 | K11: =IF(Sheet1!K153="","",Sheet1!K153) -> 3383.1334 | L11: =IF(Sheet1!L153="","",Sheet1!L153) -> 3933.386 | ... S11: =IF(Sheet1!S153="","",Sheet1!S153) -> 7329.1398
B12: CIR (model) | D12: Sheet1!B267:S267 | E12: =IF(Sheet1!E267="","",Sheet1!E267) -> 0.53417114 | F12: =IF(Sheet1!F267="","",Sheet1!F267) -> 0.51292945 | G12: =IF(Sheet1!G267="","",Sheet1!G267) -> 0.50086417 | H12: =IF(Sheet1!H267="","",Sheet1!H267) -> 0.51353393 | I12: =IF(Sheet1!I267="","",Sheet1!I267) -> 0.52562269 | J12: =IF(Sheet1!J267="","",Sheet1!J267) -> 0.545 | K12: =IF(Sheet1!K267="","",Sheet1!K267) -> 0.52 | L12: =IF(Sheet1!L267="","",Sheet1!L267) -> 0.515 | ... S12: =IF(Sheet1!S267="","",Sheet1!S267) -> 0.505
B13: CIR - reported | D13: Sheet1!B268:S268 | E13: =IF(Sheet1!E268="","",Sheet1!E268) -> 0.5257 | F13: =IF(Sheet1!F268="","",Sheet1!F268) -> 0.5101 | G13: =IF(Sheet1!G268="","",Sheet1!G268) -> 0.4986 | H13: =IF(Sheet1!H268="","",Sheet1!H268) -> 0.5089 | I13: =IF(Sheet1!I268="","",Sheet1!I268) -> 0.5209 | J13: =IF(Sheet1!J268="","",Sheet1!J268) | K13: =IF(Sheet1!K268="","",Sheet1!K268) | L13: =IF(Sheet1!L268="","",Sheet1!L268) | ... S13: =IF(Sheet1!S268="","",Sheet1!S268)
B14: Operating jaws (op. income growth - overhead growth) | D14: Sheet1!B269:S269 | E14: =IF(Sheet1!E269="","",Sheet1!E269) | F14: =IF(Sheet1!F269="","",Sheet1!F269) -> 0.046658449 | G14: =IF(Sheet1!G269="","",Sheet1!G269) -> 0.024950382 | H14: =IF(Sheet1!H269="","",Sheet1!H269) -> -0.028389456 | I14: =IF(Sheet1!I269="","",Sheet1!I269) -> -0.026717949 | J14: =IF(Sheet1!J269="","",Sheet1!J269) -> -0.042143685 | K14: =IF(Sheet1!K269="","",Sheet1!K269) -> 0.053486084 | L14: =IF(Sheet1!L269="","",Sheet1!L269) -> 0.01099647 | ... S14: =IF(Sheet1!S269="","",Sheet1!S269) -> 2.220446e-16
B15: CREDIT & FUNDS
B16: TOTAL ASSETS | D16: Sheet1!B169:S169 | E16: =IF(Sheet1!E169="","",Sheet1!E169) -> 265289 | F16: =IF(Sheet1!F169="","",Sheet1!F169) -> 305727 | G16: =IF(Sheet1!G169="","",Sheet1!G169) -> 353624 | H16: =IF(Sheet1!H169="","",Sheet1!H169) -> 408613 | I16: =IF(Sheet1!I169="","",Sheet1!I169) -> 456193 | J16: =IF(Sheet1!J169="","",Sheet1!J169) -> 512440.96 | K16: =IF(Sheet1!K169="","",Sheet1!K169) -> 580330.33 | L16: =IF(Sheet1!L169="","",Sheet1!L169) -> 641717 | ... S16: =IF(Sheet1!S169="","",Sheet1!S169) -> 1139887.2
B17: (-) Increase in other assets | D17: Sheet1!B187:S187 | E17: =IF(Sheet1!E187="","",Sheet1!E187) | F17: =IF(Sheet1!F187="","",Sheet1!F187) | G17: =IF(Sheet1!G187="","",Sheet1!G187) | H17: =IF(Sheet1!H187="","",Sheet1!H187) | I17: =IF(Sheet1!I187="","",Sheet1!I187) | J17: =IF(Sheet1!J187="","",Sheet1!J187) -> -1330.5377 | K17: =IF(Sheet1!K187="","",Sheet1!K187) -> -1763.4714 | L17: =IF(Sheet1!L187="","",Sheet1!L187) -> -1779.1814 | ... S17: =IF(Sheet1!S187="","",Sheet1!S187) -> -1669.6974
B18: S1. Financing book by segment (revenue engine) | D18: Sheet1!B206:S206 | E18: =IF(Sheet1!E206="","",Sheet1!E206) -> FY21A | F18: =IF(Sheet1!F206="","",Sheet1!F206) -> FY22A | G18: =IF(Sheet1!G206="","",Sheet1!G206) -> FY23A | H18: =IF(Sheet1!H206="","",Sheet1!H206) -> FY24A | I18: =IF(Sheet1!I206="","",Sheet1!I206) -> FY25A | J18: =IF(Sheet1!J206="","",Sheet1!J206) -> FY26E | K18: =IF(Sheet1!K206="","",Sheet1!K206) -> FY27E | L18: =IF(Sheet1!L206="","",Sheet1!L206) -> FY28E | ... S18: =IF(Sheet1!S206="","",Sheet1!S206) -> FY35E
B19: CIR (model) | D19: Sheet1!B267:S267 | E19: =IF(Sheet1!E267="","",Sheet1!E267) -> 0.53417114 | F19: =IF(Sheet1!F267="","",Sheet1!F267) -> 0.51292945 | G19: =IF(Sheet1!G267="","",Sheet1!G267) -> 0.50086417 | H19: =IF(Sheet1!H267="","",Sheet1!H267) -> 0.51353393 | I19: =IF(Sheet1!I267="","",Sheet1!I267) -> 0.52562269 | J19: =IF(Sheet1!J267="","",Sheet1!J267) -> 0.545 | K19: =IF(Sheet1!K267="","",Sheet1!K267) -> 0.52 | L19: =IF(Sheet1!L267="","",Sheet1!L267) -> 0.515 | ... S19: =IF(Sheet1!S267="","",Sheet1!S267) -> 0.505
B20: Allowance (CKPN) - closing = coverage x gross NPF | D20: Sheet1!B298:S298 | E20: =IF(Sheet1!E298="","",Sheet1!E298) -> 7471.5267 | F20: =IF(Sheet1!F298="","",Sheet1!F298) -> 9204.4111 | G20: =IF(Sheet1!G298="","",Sheet1!G298) -> 9714.7262 | H20: =IF(Sheet1!H298="","",Sheet1!H298) -> 10318.25 | I20: =IF(Sheet1!I298="","",Sheet1!I298) -> 11015.831 | J20: =IF(Sheet1!J298="","",Sheet1!J298) -> 12819.052 | K20: =IF(Sheet1!K298="","",Sheet1!K298) -> 14478.013 | L20: =IF(Sheet1!L298="","",Sheet1!L298) -> 15712.45 | ... S20: =IF(Sheet1!S298="","",Sheet1!S298) -> 27836.038
B21: Net write-off rate (% avg financing) | D21: Sheet1!B301:S301 | E21: =IF(Sheet1!E301="","",Sheet1!E301) | F21: =IF(Sheet1!F301="","",Sheet1!F301) -> 0.010638202 | G21: =IF(Sheet1!G301="","",Sheet1!G301) -> 0.0094288819 | H21: =IF(Sheet1!H301="","",Sheet1!H301) -> 0.004974366 | I21: =IF(Sheet1!I301="","",Sheet1!I301) -> 0.0055560056 | J21: =IF(Sheet1!J301="","",Sheet1!J301) -> 0.0017238726 | K21: =IF(Sheet1!K301="","",Sheet1!K301) -> 0.003227564 | L21: =IF(Sheet1!L301="","",Sheet1!L301) -> 0.004666514 | ... S21: =IF(Sheet1!S301="","",Sheet1!S301) -> 0.0053469734
B22: Cost of credit - reported | D22: Sheet1!B303:S303 | E22: =IF(Sheet1!E303="","",Sheet1!E303) | F22: =IF(Sheet1!F303="","",Sheet1!F303) -> 0.0197 | G22: =IF(Sheet1!G303="","",Sheet1!G303) -> 0.0114 | H22: =IF(Sheet1!H303="","",Sheet1!H303) -> 0.0083 | I22: =IF(Sheet1!I303="","",Sheet1!I303) -> 0.0084 | J22: =IF(Sheet1!J303="","",Sheet1!J303) | K22: =IF(Sheet1!K303="","",Sheet1!K303) | L22: =IF(Sheet1!L303="","",Sheet1!L303) | ... S22: =IF(Sheet1!S303="","",Sheet1!S303)
B23: NPF net - reported | D23: Sheet1!B304:S304 | E23: =IF(Sheet1!E304="","",Sheet1!E304) | F23: =IF(Sheet1!F304="","",Sheet1!F304) -> 0.0057 | G23: =IF(Sheet1!G304="","",Sheet1!G304) -> 0.0055 | H23: =IF(Sheet1!H304="","",Sheet1!H304) -> 0.005 | I23: =IF(Sheet1!I304="","",Sheet1!I304) -> 0.0047 | J23: =IF(Sheet1!J304="","",Sheet1!J304) | K23: =IF(Sheet1!K304="","",Sheet1!K304) | L23: =IF(Sheet1!L304="","",Sheet1!L304) | ... S23: =IF(Sheet1!S304="","",Sheet1!S304)
B24: CAR - reported | D24: Sheet1!B315:S315 | E24: =IF(Sheet1!E315="","",Sheet1!E315) -> 0.2209 | F24: =IF(Sheet1!F315="","",Sheet1!F315) -> 0.2029 | G24: =IF(Sheet1!G315="","",Sheet1!G315) -> 0.2104 | H24: =IF(Sheet1!H315="","",Sheet1!H315) -> 0.214 | I24: =IF(Sheet1!I315="","",Sheet1!I315) -> 0.22 | J24: =IF(Sheet1!J315="","",Sheet1!J315) | K24: =IF(Sheet1!K315="","",Sheet1!K315) | L24: =IF(Sheet1!L315="","",Sheet1!L315) | ... S24: =IF(Sheet1!S315="","",Sheet1!S315)
B25: CAR (model) | D25: Sheet1!B328:S328 | E25: =IF(Sheet1!E328="","",Sheet1!E328) -> 0.22086522 | F25: =IF(Sheet1!F328="","",Sheet1!F328) -> 0.20293206 | G25: =IF(Sheet1!G328="","",Sheet1!G328) -> 0.21044249 | H25: =IF(Sheet1!H328="","",Sheet1!H328) -> 0.21403664 | I25: =IF(Sheet1!I328="","",Sheet1!I328) -> 0.21996525 | J25: =IF(Sheet1!J328="","",Sheet1!J328) -> 0.22000884 | K25: =IF(Sheet1!K328="","",Sheet1!K328) -> 0.24524347 | L25: =IF(Sheet1!L328="","",Sheet1!L328) -> 0.24758547 | ... S25: =IF(Sheet1!S328="","",Sheet1!S328) -> 0.26696653
B26: RETURNS & RATIOS
B27: S13. Returns, per-share data & DuPont | D27: Sheet1!B345:S345 | E27: =IF(Sheet1!E345="","",Sheet1!E345) -> FY21A | F27: =IF(Sheet1!F345="","",Sheet1!F345) -> FY22A | G27: =IF(Sheet1!G345="","",Sheet1!G345) -> FY23A | H27: =IF(Sheet1!H345="","",Sheet1!H345) -> FY24A | I27: =IF(Sheet1!I345="","",Sheet1!I345) -> FY25A | J27: =IF(Sheet1!J345="","",Sheet1!J345) -> FY26E | K27: =IF(Sheet1!K345="","",Sheet1!K345) -> FY27E | L27: =IF(Sheet1!L345="","",Sheet1!L345) -> FY28E | ... S27: =IF(Sheet1!S345="","",Sheet1!S345) -> FY35E
B28: ROA (avg assets) | D28: Sheet1!B346:S346 | E28: =IF(Sheet1!E346="","",Sheet1!E346) | F28: =IF(Sheet1!F346="","",Sheet1!F346) -> 0.014920773 | G28: =IF(Sheet1!G346="","",Sheet1!G346) -> 0.017301082 | H28: =IF(Sheet1!H346="","",Sheet1!H346) -> 0.01838244 | I28: =IF(Sheet1!I346="","",Sheet1!I346) -> 0.017501088 | J28: =IF(Sheet1!J346="","",Sheet1!J346) -> 0.017387965 | K28: =IF(Sheet1!K346="","",Sheet1!K346) -> 0.019000818 | L28: =IF(Sheet1!L346="","",Sheet1!L346) -> 0.019754271 | ... S28: =IF(Sheet1!S346="","",Sheet1!S346) -> 0.020343768
B29: ROE (avg common equity) | D29: Sheet1!B347:S347 | E29: =IF(Sheet1!E347="","",Sheet1!E347) | F29: =IF(Sheet1!F347="","",Sheet1!F347) -> 0.14559142 | G29: =IF(Sheet1!G347="","",Sheet1!G347) -> 0.15789974 | H29: =IF(Sheet1!H347="","",Sheet1!H347) -> 0.1672435 | I29: =IF(Sheet1!I347="","",Sheet1!I347) -> 0.15604034 | J29: =IF(Sheet1!J347="","",Sheet1!J347) -> 0.15199023 | K29: =IF(Sheet1!K347="","",Sheet1!K347) -> 0.15653779 | L29: =IF(Sheet1!L347="","",Sheet1!L347) -> 0.15372455 | ... S29: =IF(Sheet1!S347="","",Sheet1!S347) -> 0.14619715
B30: ROE Tier-1 - reported | D30: Sheet1!B348:S348 | E30: =IF(Sheet1!E348="","",Sheet1!E348) -> 0.1371 | F30: =IF(Sheet1!F348="","",Sheet1!F348) -> 0.1684 | G30: =IF(Sheet1!G348="","",Sheet1!G348) -> 0.1688 | H30: =IF(Sheet1!H348="","",Sheet1!H348) -> 0.1777 | I30: =IF(Sheet1!I348="","",Sheet1!I348) -> 0.1685 | J30: =IF(Sheet1!J348="","",Sheet1!J348) | K30: =IF(Sheet1!K348="","",Sheet1!K348) | L30: =IF(Sheet1!L348="","",Sheet1!L348) | ... S30: =IF(Sheet1!S348="","",Sheet1!S348)
B31: Leverage (avg assets / avg equity) | D31: Sheet1!B349:S349 | E31: =IF(Sheet1!E349="","",Sheet1!E349) | F31: =IF(Sheet1!F349="","",Sheet1!F349) -> 9.7576323 | G31: =IF(Sheet1!G349="","",Sheet1!G349) -> 9.1265817 | H31: =IF(Sheet1!H349="","",Sheet1!H349) -> 9.098003 | I31: =IF(Sheet1!I349="","",Sheet1!I349) -> 8.9160363 | J31: =IF(Sheet1!J349="","",Sheet1!J349) -> 8.7411163 | K31: =IF(Sheet1!K349="","",Sheet1!K349) -> 8.2384762 | L31: =IF(Sheet1!L349="","",Sheet1!L349) -> 7.7818387 | ... S31: =IF(Sheet1!S349="","",Sheet1!S349) -> 7.1863359
B32: EPS (avg shares) | D32: Sheet1!B350:S350 | E32: =IF(Sheet1!E350="","",Sheet1!E350) -> 73.626453 | F32: =IF(Sheet1!F350="","",Sheet1!F350) -> 92.349194 | G32: =IF(Sheet1!G350="","",Sheet1!G350) -> 123.64697 | H32: =IF(Sheet1!H350="","",Sheet1!H350) -> 151.87514 | I32: =IF(Sheet1!I350="","",Sheet1!I350) -> 164.05039 | J32: =IF(Sheet1!J350="","",Sheet1!J350) -> 182.55846 | K32: =IF(Sheet1!K350="","",Sheet1!K350) -> 209.60891 | L32: =IF(Sheet1!L350="","",Sheet1!L350) -> 228.04639 | ... S32: =IF(Sheet1!S350="","",Sheet1!S350) -> 424.92242
B33: BVPS (period-end shares) | D33: Sheet1!B351:S351 | E33: =IF(Sheet1!E351="","",Sheet1!E351) -> 608.17786 | F33: =IF(Sheet1!F351="","",Sheet1!F351) -> 726.35026 | G33: =IF(Sheet1!G351="","",Sheet1!G351) -> 839.79498 | H33: =IF(Sheet1!H351="","",Sheet1!H351) -> 976.42087 | I33: =IF(Sheet1!I351="","",Sheet1!I351) -> 1126.2456 | J33: =IF(Sheet1!J351="","",Sheet1!J351) -> 1275.9939 | K33: =IF(Sheet1!K351="","",Sheet1!K351) -> 1393.969 | L33: =IF(Sheet1!L351="","",Sheet1!L351) -> 1572.9793 | ... S33: =IF(Sheet1!S351="","",Sheet1!S351) -> 2999.7819
B34: P/E at current price | D34: Sheet1!B352:S352 | E34: =IF(Sheet1!E352="","",Sheet1!E352) -> 14.872372 | F34: =IF(Sheet1!F352="","",Sheet1!F352) -> 11.857169 | G34: =IF(Sheet1!G352="","",Sheet1!G352) -> 8.8558583 | H34: =IF(Sheet1!H352="","",Sheet1!H352) -> 7.2098697 | I34: =IF(Sheet1!I352="","",Sheet1!I352) -> 6.6747785 | J34: =IF(Sheet1!J352="","",Sheet1!J352) -> 5.9980785 | K34: =IF(Sheet1!K352="","",Sheet1!K352) -> 5.2240146 | L34: =IF(Sheet1!L352="","",Sheet1!L352) -> 4.8016546 | ... S34: =IF(Sheet1!S352="","",Sheet1!S352) -> 2.576941
B35: P/B at current price | D35: Sheet1!B353:S353 | E35: =IF(Sheet1!E353="","",Sheet1!E353) -> 1.8004601 | F35: =IF(Sheet1!F353="","",Sheet1!F353) -> 1.5075371 | G35: =IF(Sheet1!G353="","",Sheet1!G353) -> 1.3038897 | H35: =IF(Sheet1!H353="","",Sheet1!H353) -> 1.1214426 | I35: =IF(Sheet1!I353="","",Sheet1!I353) -> 0.97225689 | J35: =IF(Sheet1!J353="","",Sheet1!J353) -> 0.85815455 | K35: =IF(Sheet1!K353="","",Sheet1!K353) -> 0.7855268 | L35: =IF(Sheet1!L353="","",Sheet1!L353) -> 0.69613122 | ... S35: =IF(Sheet1!S353="","",Sheet1!S353) -> 0.36502654
B36: DuPont: net margin income / avg equity | D36: Sheet1!B354:S354 | E36: =IF(Sheet1!E354="","",Sheet1!E354) | F36: =IF(Sheet1!F354="","",Sheet1!F354) -> 0.53283368 | G36: =IF(Sheet1!G354="","",Sheet1!G354) -> 0.45009475 | H36: =IF(Sheet1!H354="","",Sheet1!H354) -> 0.41558916 | I36: =IF(Sheet1!I354="","",Sheet1!I354) -> 0.39443673 | J36: =IF(Sheet1!J354="","",Sheet1!J354) -> 0.38130589 | K36: =IF(Sheet1!K354="","",Sheet1!K354) -> 0.373525 | L36: =IF(Sheet1!L354="","",Sheet1!L354) -> 0.36381478 | ... S36: =IF(Sheet1!S354="","",Sheet1!S354) -> 0.33906474
B37: DuPont: fee income / avg equity | D37: Sheet1!B355:S355 | E37: =IF(Sheet1!E355="","",Sheet1!E355) | F37: =IF(Sheet1!F355="","",Sheet1!F355) -> 0.12649061 | G37: =IF(Sheet1!G355="","",Sheet1!G355) -> 0.11639446 | H37: =IF(Sheet1!H355="","",Sheet1!H355) -> 0.13264342 | I37: =IF(Sheet1!I355="","",Sheet1!I355) -> 0.14303079 | J37: =IF(Sheet1!J355="","",Sheet1!J355) -> 0.15649253 | K37: =IF(Sheet1!K355="","",Sheet1!K355) -> 0.15034946 | L37: =IF(Sheet1!L355="","",Sheet1!L355) -> 0.14223172 | ... S37: =IF(Sheet1!S355="","",Sheet1!S355) -> 0.13024487
